Workbook

Sheet SALDOS
B1: TRANSPORTES FURLONG S.A. | D1: Acumulado | F1: T.C. Reales al 31/07/2026 | G1: 293.17575
D2: Reales
D3: Deudor | E3: Acreedor
B5: ACTIVO
C7: 1110100330 FONDO FIJO BS. AS. | D7: =IF(F7>0,F7,0) -> 16641.694 | E7: =IF(F7<0,-F7,0) -> 0 | F7: =IFERROR(VLOOKUP(C7,$C$228:$D$315,2,FALSE),0) -> 16641.694
C8: 1110100340 FONDO FIJO SENASA | D8: =IF(F8>0,F8,0) -> 0 | E8: =IF(F8<0,-F8,0) -> 0 | F8: =IFERROR(VLOOKUP(C8,$C$228:$D$315,2,FALSE),0) -> 0
C9: 1110100420 BANCO FRANCES C/C | D9: =IF(F9>0,F9,0) -> 749.53559 | E9: =IF(F9<0,-F9,0) -> 0 | F9: =IFERROR(VLOOKUP(C9,$C$228:$D$315,2,FALSE),0) -> 749.53559
C10: 1110101050 FONDO FIJO ADELANTOS PDT | D10: =IF(F10>0,F10,0) -> 0 | E10: =IF(F10<0,-F10,0) -> 0 | F10: =IFERROR(VLOOKUP(C10,$C$228:$D$315,2,FALSE),0) -> 0
C11: 1120100100 FORD | D11: =IF(F11>0,F11,0) -> 778.03901 | E11: =IF(F11<0,-F11,0) -> 0 | F11: =IFERROR(VLOOKUP(C11,$C$228:$D$315,2,FALSE),0) -> 778.03901
C12: 1120100400 TRANSPORTES FURLONG S.A. AR | D12: =IF(F12>0,F12,0) -> 0 | E12: =IF(F12<0,-F12,0) -> 1392772.1 | F12: =IFERROR(VLOOKUP(C12,$C$228:$D$315,2,FALSE),0) -> -1392772.1
C13: 1120100700 RENAULT ARG. S.A. | D13: =IF(F13>0,F13,0) -> 0 | E13: =IF(F13<0,-F13,0) -> 0 | F13: =IFERROR(VLOOKUP(C13,$C$228:$D$315,2,FALSE),0) -> 0
C14: 1120101300 VOLKSWAGEN ARGENTINA S.A. | D14: =IF(F14>0,F14,0) -> 2474.5724 | E14: =IF(F14<0,-F14,0) -> 0 | F14: =IFERROR(VLOOKUP(C14,$C$228:$D$315,2,FALSE),0) -> 2474.5724
C15: 1120101600 FCA AUTOMOBILES ARGENTINA S.A. | D15: =IF(F15>0,F15,0) -> 0 | E15: =IF(F15<0,-F15,0) -> 0 | F15: =IFERROR(VLOOKUP(C15,$C$228:$D$315,2,FALSE),0) -> 0
C16: 1120131000 CNH ARGENTINA S.A. | D16: =IF(F16>0,F16,0) -> 0 | E16: =IF(F16<0,-F16,0) -> 0 | F16: =IFERROR(VLOOKUP(C16,$C$228:$D$315,2,FALSE),0) -> 0
C17: 1120138000 STELLANTIS AUTOMOVILES DE ARGENTINA S. A | D17: =IF(F17>0,F17,0) -> 532.77103 | E17: =IF(F17<0,-F17,0) -> 0 | F17: =IFERROR(VLOOKUP(C17,$C$228:$D$315,2,FALSE),0) -> 532.77103
C18: 1140300100 ANTICIPO A PDT | D18: =IF(F18>0,F18,0) -> 96140.963 | E18: =IF(F18<0,-F18,0) -> 0 | F18: =IFERROR(VLOOKUP(C18,$C$228:$D$315,2,FALSE),0) -> 96140.963
... C45: 1220700000 AMORT. ACUM. RODADOS | D45: =IF(F45>0,F45,0) -> 0 | E45: =IF(F45<0,-F45,0) -> 309747.98 | F45: =IFERROR(VLOOKUP(C45,$C$228:$D$315,2,FALSE),0) -> -309747.98
F46: =SUM(F7:F45) -> -884362.58
B47: PASIVO
C48: 2110100300 COTELCAM | D48: =IF(F48>0,F48,0) -> 0 | E48: =IF(F48<0,-F48,0) -> 0 | F48: =IFERROR(VLOOKUP(C48,$C$228:$D$315,2,FALSE),0) -> 0
C49: 2110102400 OSDE | D49: =IF(F49>0,F49,0) -> 0 | E49: =IF(F49<0,-F49,0) -> 0 | F49: =IFERROR(VLOOKUP(C49,$C$228:$D$315,2,FALSE),0) -> 0
C50: 2110100900 ESTUDIO CORTES | D50: =IF(F50>0,F50,0) -> 0 | E50: =IF(F50<0,-F50,0) -> 0 | F50: =IFERROR(VLOOKUP(C50,$C$228:$D$315,2,FALSE),0) -> 0
C51: 2110101500 VENEZIA AUTOS SA | D51: =IF(F51>0,F51,0) -> 0 | E51: =IF(F51<0,-F51,0) -> 0 | F51: =IFERROR(VLOOKUP(C51,$C$228:$D$315,2,FALSE),0) -> 0
C52: 2110101800 TRANSPORTES FURLONG ARG. S.A | D52: =IF(F52>0,F52,0) -> 0 | E52: =IF(F52<0,-F52,0) -> 0 | F52: =IFERROR(VLOOKUP(C52,$C$228:$D$315,2,FALSE),0) -> 0
C53: 2110105400 MERCOVIA S.A. | D53: =IF(F53>0,F53,0) -> 0 | E53: =IF(F53<0,-F53,0) -> 0 | F53: =IFERROR(VLOOKUP(C53,$C$228:$D$315,2,FALSE),0) -> 0
C54: 2110106800 OKINET SRL | D54: =IF(F54>0,F54,0) -> 0 | E54: =IF(F54<0,-F54,0) -> 0 | F54: =IFERROR(VLOOKUP(C54,$C$228:$D$315,2,FALSE),0) -> 0
C55: 2110108900 LA MERIDIONAL S.A. | D55: =IF(F55>0,F55,0) -> 0 | E55: =IF(F55<0,-F55,0) -> 2870.8206 | F55: =IFERROR(VLOOKUP(C55,$C$228:$D$315,2,FALSE),0) -> -2870.8206
C56: 2110115100 GIULI SERGIO ALBERTO | D56: =IF(F56>0,F56,0) -> 0 | E56: =IF(F56<0,-F56,0) -> 0 | F56: =IFERROR(VLOOKUP(C56,$C$228:$D$315,2,FALSE),0) -> 0
C57: 2110116700 CARLOS ALEJANDRO DUMA | D57: =IF(F57>0,F57,0) -> 0 | E57: =IF(F57<0,-F57,0) -> 0 | F57: =IFERROR(VLOOKUP(C57,$C$228:$D$315,2,FALSE),0) -> 0
C58: 2110118000 MANGGINI PABLO Y ULISES S.H | D58: =IF(F58>0,F58,0) -> 0 | E58: =IF(F58<0,-F58,0) -> 22.171005 | F58: =IFERROR(VLOOKUP(C58,$C$228:$D$315,2,FALSE),0) -> -22.171005
C59: 2110120600 QBE SEGUROS LA BUENOS AIRES S.A. | D59: =IF(F59>0,F59,0) -> 0 | E59: =IF(F59<0,-F59,0) -> 44421.536 | F59: =IFERROR(VLOOKUP(C59,$C$228:$D$315,2,FALSE),0) -> -44421.536
... C106: 2116300000 Sistemas Bejerman | D106: =IF(F106>0,F106,0) -> 0 | E106: =IF(F106<0,-F106,0) -> 0 | F106: =IFERROR(VLOOKUP(C106,$C$228:$D$315,2,FALSE),0) -> 0
D108: =IF(F108>0,F108,0) -> 0 | F108: =SUM(F48:F106) -> -623635.92
B109: PATRIMONIO NETO
C111: 3310000000 RNA EJERCICIO ANTERIOR | D111: 0 | E111: =-F111 -> 3342261.5 | F111: =IFERROR(VLOOKUP(C111,$C$228:$D$315,2,FALSE),0) -> -3342261.5 | G111: =+F111+F112 -> -451561.39
C112: 3320000000 RESULTADOS DEL EJERCICIOS | D112: =+F112 -> 2890700.2 | E112: 0 | F112: =IFERROR(VLOOKUP(C112,$C$228:$D$315,2,FALSE),0) -> 2890700.2
B114: RESULTADO | F114: =SUM(F111:F113) -> -451561.39
C116: 4110100000 SERVICIOS PRESTADOS | D116: =IF(F116>0,F116,0) -> 0 | E116: =IF(F116<0,-F116,0) -> 115882.33 | F116: =IFERROR(VLOOKUP(C116,$C$228:$D$315,2,FALSE),0) -> -115882.33
C117: 4120500000 INTERESES GANADOS | D117: =IF(F117>0,F117,0) -> 0 | E117: =IF(F117<0,-F117,0) -> 0 | F117: =IFERROR(VLOOKUP(C117,$C$228:$D$315,2,FALSE),0) -> 0
C118: 4231100000 RESULTADO POR TENENCIA FCI | D118: =IF(F118>0,F118,0) -> 0 | E118: =IF(F118<0,-F118,0) -> 21805.53 | F118: =IFERROR(VLOOKUP(C118,$C$228:$D$315,2,FALSE),0) -> -21805.53
C119: 4120100000 RECUPERO DE GASTOS | D119: =IF(F119>0,F119,0) -> 0 | E119: =IF(F119<0,-F119,0) -> 0 | F119: =IFERROR(VLOOKUP(C119,$C$228:$D$315,2,FALSE),0) -> 0
C120: 412 OTROS INGRESOS | D120: =IF(F120>0,F120,0) -> 0 | E120: =IF(F120<0,-F120,0) -> 0 | F120: =IFERROR(VLOOKUP(C120,$C$228:$D$315,2,FALSE),0) -> 0
C121: 4120300000 VENTA RODADO | D121: =IF(F121>0,F121,0) -> 0 | E121: =IF(F121<0,-F121,0) -> 0 | F121: =IFERROR(VLOOKUP(C121,$C$228:$D$315,2,FALSE),0) -> 0
C122: 4120200000 DIFERENCIA DE COTIZACION | D122: =IF(F122>0,F122,0) -> 0 | E122: =IF(F122<0,-F122,0) -> 0 | F122: =IFERROR(VLOOKUP(C122,$C$228:$D$315,2,FALSE),0) -> 0
C123: 4120500000 INTERESES GANADOS | D123: =IF(F123>0,F123,0) -> 0 | E123: =IF(F123<0,-F123,0) -> 0 | F123: =IFERROR(VLOOKUP(C123,$C$228:$D$315,2,FALSE),0) -> 0
C124: 4210100000 GASTOS GENERALES | D124: =IF(F124>0,F124,0) -> 0 | E124: =IF(F124<0,-F124,0) -> 0 | F124: =IFERROR(VLOOKUP(C124,$C$228:$D$315,2,FALSE),0) -> 0
C125: 4210200000 MOVILIDAD Y VIÁTICOS | D125: =IF(F125>0,F125,0) -> 2518.73 | E125: =IF(F125<0,-F125,0) -> 0 | F125: =IFERROR(VLOOKUP(C125,$C$228:$D$315,2,FALSE),0) -> 2518.73
C126: 4210300000 SUELDOS | D126: =IF(F126>0,F126,0) -> 711028.12 | E126: =IF(F126<0,-F126,0) -> 0 | F126: =IFERROR(VLOOKUP(C126,$C$228:$D$315,2,FALSE),0) -> 711028.12
C127: 4210400000 HONORARIOS PROFESIONALES | D127: =IF(F127>0,F127,0) -> 123093.34 | E127: =IF(F127<0,-F127,0) -> 0 | F127: =IFERROR(VLOOKUP(C127,$C$228:$D$315,2,FALSE),0) -> 123093.34
... C208: 4230400000 INTERESES RESARCITORIOS | D208: =IF(F208>0,F208,0) -> 0 | E208: =IF(F208<0,-F208,0) -> 0 | F208: =IFERROR(VLOOKUP(C208,$C$228:$D$315,2,FALSE),0) -> 0
C209: DIFERENCIA DE CAMBIO | E209: 107528.26 | F209: -107528.26 | G209: =SUM(F116:F209) -> 1959559.9
D211: =SUM(D5:D209) -> 6040921.9 | E211: =SUM(E5:E209) -> 6040921.9 | F211: Diferencia | G211: =+D211-E211 -> 0
C213: EXPLICACIÓN DIF DE CAMBIO
C214: ENERO 01/01/2026-31/01/2026 | D214: 6262.5
C215: FEBRERO 01/02/2026-28/02/2026 | D215: 626.6
C216: MARZO 01/03/2026-31/03/2026 | D216: -1326.48
C217: ABRIL 01/04/2026-30/04/2026 | D217: 3111.17
C218: MAYO 01/05/2026-31/05/2026 | D218: 37.643899
C219: JUNIO 01/06/2026-30/06/2026 | D219: 2602.16
C220: JULIO 01/07/2026-31/07/2026 | D220: 3231.78
C221: ACUMULADO 01/01/2026 - 30/06/2026 | D221: 92982.884
D222: =SUM(D214:D221) -> 107528.26 | E222: =+E209-D222-D209 -> 0 | F222: DIF
C228: 1110100330 FONDO FIJO BS. AS. | D228: 16641.694 | E228: 16641.694
C229: 1110100420 BANCO FRANCES C/C | D229: 749.53559 | E229: 749.53559
C230: 1120100100 FORD | D230: 778.03901 | E230: 778.03901
C231: 1120100400 TRANSPORTES FURLONG S.A. AR | D231: -1392772.1 | E231: -1392772.1
C232: 1120101300 VOLKSWAGEN ARGENTINA S.A. | D232: 2474.5724 | E232: 2474.5724
C233: 1120138000 STELLANTIS AUTOMOVILES DE ARGENTINA S. A | D233: 532.77103 | E233: 532.77103
C234: 1140300100 ANTICIPO A PDT | D234: 96140.963 | E234: 96140.963
C235: 1140600300 PRESTAMO A. VELASCO | D235: 5457.4782 | E235: 5457.4782
C236: 1140601100 PRESTAMO LORENA ALVES | D236: 2387.6467 | E236: 2387.6467
C237: 1140601300 PRESTAMO CUBA | D237: 682.18478 | E237: 682.18478
C238: 1140900700 SEGUROS A DEV. ZURICH ASEG. S.A. | D238: 56508.601 | E238: 56508.601
C239: 1140900800 SEGUROS A DEV. ARG LA MERIDIONAL | D239: 9.8349215 | E239: 9.8349215
... C315: 4231100000 RESULTADO POR TENENCIA FCI | D315: -21805.53 | E315: 65.43
D316: -107528.26 | E316: 3210.92
E317: -107528.26

Sheet EESP
A5: TRANSPORTES FURLONG S.A
A7: Al 31 de Julio 2026
A9: Estado de Situación Patrimonial
F13: 46234 | G13: 38717 | L13: =+F13 -> 46234 | M13: 38717
B14: ACTIVO: | I14: PASIVO
C15: ACTIVO CORRIENTE | I15: PASIVO CORRIENTE
D16: Caja y bancos (Nota 4.a) | F16: =+Activo!F17 -> 17391.229 | K16: Comerciales (Nota 4.e) | L16: =+Pasivo!E10 -> 1965572.4
D17: Inversiones Temporarias (Nota 4.b) | F17: =+Activo!F22 -> 61778.081 | K17: Remuneraciones y cs.sociales (Nota 4.f) | L17: =+Pasivo!E16 -> 46146.185
D18: Créditos por ventas (Nota 4.c) | F18: =+Activo!F27 -> 3785.3825 | K18: Cargas fiscales (Nota 4.g) | L18: =+Pasivo!E24 -> 4689.4147
D19: Otros Créditos (Nota 4.d) | F19: =+Activo!F49 -> 161186.71
C22: Total del Activo corriente | F22: =SUM(F16:F19) -> 244141.4 | I22: Total del Pasivo Corriente | L22: =SUM(L16:L21) -> 2016408
I23: Total del Pasivo | L23: =+L22 -> 2016408
C26: ACTIVO NO CORRIENTE
D27: Bienes de uso (Anexo I) | F27: =+'Anexo I'!K21 -> 264268.1 | I27: PATRIMONIO NETO (Según estado respec.) | L27: =+EEPN!J17 -> -1507998.5
C29: Total del Activo no corriente | F29: =SUM(F27:F28) -> 264268.1 | L29: =+L27 -> -1507998.5
C31: Total del Activo | F31: =+F22+F29 -> 508409.5 | I31: Total del Pasivo y Patrimonio Neto | L31: =+L23+L29 -> 508409.5
A33: Las notas y anexos adjuntos forman parte integrante de los estados contables.
A34: Informe profesional por separado.
E39: Miguel Ángel Alonso | K39: Tomas Furlong
E40: Contador Público (UCA) | K40: Transportes Furlong S.A.
E41: C.P.C.E.C.A.B.A. Tº176 Fº3 | K41: Apoderado

Sheet EERR
A4: TRANSPORTES FURLONG S.A
A6: =+EESP!A7 -> Al 31 de Julio 2026
A8: Estado de Resultados
C12: =+EESP!F13 -> 46234 | D12: =+EESP!G13 -> 38717
A15: Ingresos por servicios prestados | C15: =+SALDOS!E116 -> 115882.33
A17: Gastos de comercialización (Anexo II) | C17: =+'Anexo II'!E84 -> 1930642.2
A18: Gastos de administración (Anexo II) | C18: =+'Anexo II'!D84 -> 244242.16
A19: Gastos de financieros (Anexo II) | C19: =+'Anexo II'!F84 -> 29891.64
A21: Subtotal | C21: =+C15-C17-C18-C19 -> -2088893.7
A22: Otros ingresos y egresos | C22: =+SALDOS!E118+SALDOS!E123+SALDOS!E189+SALDOS!E119 -> 21805.53
A23: Diferencia de cotización | C23: =+SALDOS!E209 -> 107528.26
A24: Intereses | C24: =+SALDOS!E117 -> 0
A25: Venta Bienes de Uso | C25: =+SALDOS!E121 -> 0
A26: Ganancia antes de impuesto | C26: =+C21+C22+C23+C25+C24 -> -1959559.9
A27: Impuesto a las Ganancias
A29: Ganancia (Pérdida) del ejercicio | C29: =+C26-C27 -> -1959559.9
A33: Las notas y anexos adjuntos forman parte integrante de los estados contables.
A34: Informe profesional por separado.
A39: =+EESP!E39 -> Miguel Ángel Alonso | C39: =+EESP!K39 -> Tomas Furlong
A40: =+EESP!E40 -> Contador Público (UCA) | C40: =+EESP!K40 -> Transportes Furlong S.A.
A41: =+EESP!E41 -> C.P.C.E.C.A.B.A. Tº176 Fº3 | C41: Apoderado

Sheet EEPN
A1: =+EESP!A5 -> TRANSPORTES FURLONG S.A
A2: =+EESP!A7 -> Al 31 de Julio 2026 | B2: =+EESP!A7 -> Al 31 de Julio 2026
A3: Estado de Evolución del Patrimonio Neto
J5: =+EESP!F13 -> 46234 | K5: =+EESP!G13 -> 38717
B6: CONCEPTO | C6: Aportes de los propietarios | F6: Ganancias | G6: Reservadas | I6: Resultados | J6: Total del | K6: Total del
C7: Capital | D7: Ajuste | E7: Total de | F7: Reserva | G7: Otras | H7: Aportes | I7: no | J7: patrimonio | K7: patrimonio
D8: de Capital | E8: Capital | F8: legal | G8: reservas | H8: Irrevocables | I8: asignados | J8: neto | K8: neto
C9: $ | D9: $ | E9: $ | F9: $ | G9: $ | I9: $ | J9: $ | K9: $
B11: Saldos al inicio del ejercicio | C11: 0 | D11: 0 | E11: =+C11+D11 -> 0 | F11: 0 | G11: 0 | H11: 0 | I11: =+SALDOS!E111-SALDOS!D112 -> 451561.39 | J11: =+I11 -> 451561.39
B13: Ganancia (Pérdida) del ejercicio | I13: =+EERR!C29 -> -1959559.9 | J13: =+I13 -> -1959559.9
B14: Reasignación casa matriz | J14: =+I14 -> 0
B17: Total al 31.7.2026 | C17: =SUM(C11:C16) -> 0 | D17: =SUM(D11:D16) -> 0 | E17: =SUM(E11:E16) -> 0 | F17: =SUM(F11:F16) -> 0 | G17: =SUM(G11:G16) -> 0 | H17: =SUM(H11:H16) -> 0 | I17: =SUM(I11:I16) -> -1507998.5 | J17: =SUM(J11:J16) -> -1507998.5 | K17: =+#REF!+K13 -> #REF!
B18: Total al 31.12.05 | E18: =+C18+D18 -> 0 | G18: 0 | I18: 0 | J18: =+E18 -> 0 | K18: =+G18 -> 0
B20: Las notas y anexos adjuntos forman parte integrante de los estados contables.
B21: Informe profesional por separado.
C25: =+EESP!E39 -> Miguel Ángel Alonso | H25: =+EERR!C39 -> Tomas Furlong
C26: =+EESP!E40 -> Contador Público (UCA) | H26: =+EERR!C40 -> Transportes Furlong S.A.
C27: =+EESP!E41 -> C.P.C.E.C.A.B.A. Tº176 Fº3 | H27: =+EERR!C41 -> Apoderado

Sheet Activo
B1: NOTA 4: | E1: COMPOSICION DE LOS RUBROS
B3: =+EESP!A7 -> Al 31 de Julio 2026
F5: =+EESP!F13 -> 46234 | H5: 38717
B6: ACTIVO
B7: Activo Corriente
B8: a. | C8: Caja y bancos
D9: - Caja
D10: - Fondo Fijo | F10: =+SALDOS!D7 -> 16641.694
D11: - Fondo Fijo SENASA | F11: =+SALDOS!D8 -> 0
D12: - Fondo Fijo Adelantos PDT | F12: =+SALDOS!D10 -> 0
D13: - Banco Francés c/c | F13: =+SALDOS!D9-SALDOS!E9 -> 749.53559
D14: - Valores a Depositar
D15: - Efectivo Casa Matriz | F15: 0
D16: - Cheques no depositados | F16: 0
F17: =+SUM(F10:F16) -> 17391.229
B19: b. | C19: Inversione temporarias
D20: - Plazo Fijo | F20: =+SALDOS!D27 -> 0
D21: - Fondo común inversión BBVA | F21: =+SALDOS!D26 -> 61778.081
F22: =SUM(F20:F21) -> 61778.081
B24: c. | C24: Creditos por Ventas
D25: - Deudores por ventas | F25: =+SALDOS!D14+SALDOS!D15+SALDOS!D11+SALDOS!D16+SALDOS!D17 -> 3785.3825
D26: - Anticipo a proveedores | F26: 0
F27: =SUM(F25:F26) -> 3785.3825
B29: d. | C29: Otros créditos
D30: - Transportes Furlong Cba.
D31: - Adelantos Tomás Furlong
D32: - Adelantos PDT | F32: =+SALDOS!D18 -> 96140.963
D33: - Adelanto de gastos
D35: - ANTICIPO COMBUSTIBLE Velasco
D36: - Adelanto de sac
D37: - Prestamos al personal | F37: =+SALDOS!F20+SALDOS!F22+SALDOS!F19 -> 8527.3097
D38: - Anticipo a proveedores
D39: - Gastos a recuperar
D40: - Prov. Fc a recibir transportistas
D41: - Retenciones IIBB
D42: - Retenciones ganancias
D43: - Retenciones suss
D44: - Retenciones y Percepciones IVA
D45: - Crédito Imp. Ley 25413
D46: - Fondo fijo a rendir
D48: - Seguros a Devengar | F48: =+SALDOS!D23+SALDOS!D24+SALDOS!D25 -> 56518.436
F49: =SUM(F30:F48) -> 161186.71

Sheet Pasivo
E1: =+EESP!F13 -> 46234 | G1: 31.03.04 | K1: 31.03.03 | L1: =+EESP!G13 -> 38717
A2: Pasivo
A3: Pasivo Corriente
A4: e. | B4: Deudas comerciales
C5: - Anticipos de clientes | E5: 0
C6: - Adelanto casa matriz | E6: =-SALDOS!F12-SALDOS!F82 -> 1827260.7
C7: - Proveedores | E7: =-SUM(SALDOS!F53:F72)-SALDOS!F80-SUM(SALDOS!F84:F106) -> 138311.72
C8: - Previsiones
C9: - Cheques Emitidos
E10: =+E6+E7 -> 1965572.4
A12: f. | B12: Remuneraciones y cs. Sociales
C13: - Suss a pagar | E13: =+SALDOS!E74 -> 46146.185 | G13: 70 | K13: 0
C14: - Sueldos a pagar | E14: =+SALDOS!E73 -> 0
C15: - Indemnización a pagar
E16: =+E13+E14+E15 -> 46146.185
G17: =SUM(G13:G16) -> 70 | K17: =SUM(#REF!) -> #REF!
A19: g. | B19: Cargas fiscales
C20: - Plan mis Facilidades | E20: =+SALDOS!E76 -> 2005.0118
C21: - Intereses a devengar | E21: =-SALDOS!D77 -> -203.53505
C22: - Sicore a pagar | E22: =+SALDOS!E75 -> 2887.938
C23: - Bs. Pers. Acc. Y Participaciones a Pagar
E24: =SUM(E20:E23) -> 4689.4147
A26: h. | B26: Otras Deudas
C27: - Prestamos a pagar
C28: - Convenio HSBC
C29: - Rodados a pagar
C30: - Acuerdos CNRT a pagar | E30: =+SALDOS!E83 -> 0
C31: - Provision Siniestro Ford
C32: - Prestamo Carlos Furlong | E32: =+SALDOS!E21 -> 0
C33: - Prestamo Lorena Alves | E33: =+SALDOS!E22 -> 0
E34: =+E32+E30+E33 -> 0
A35: Las notas y anexos adjuntos forman parte integrante de los estados contables.
A36: Informe profesional por separado.
C43: Miguel Angel Alonso | E43: Tomas Furlong
C44: Contador Publico (UCA) | E44: Transportes Furlong S.A.
C45: C.P.C.E.C.A.B.A. Tº176 Fº3 | E45: Apoderado

Sheet Anexo I
A4: B I E N E S D E U S O
A5: =+Activo!B3 -> Al 31 de Julio 2026
B8: VALOR DE ORIGEN | F8: DEPRECIACIONES
B9: VALORES AL | E9: VALORES AL | F9: ACUMULADAS | H9: DEL EJERCICIO | J9: ACUMULADAS | K9: NETO
A10: CONCEPTO | B10: COMIENZO DEL | C10: AUMENTOS | D10: DISMINUCIONES | E10: CIERRE DEL | F10: AL INICIO DEL | G10: BAJAS | H10: ALIC | I10: MONTO | J10: AL CIERRE DEL | K10: RESULTANTE
B11: EJERCICIO | E11: EJERCICIO | F11: EJERCICIO | J11: EJERCICIO | K11: =+EESP!F13 -> 46234
B12: $ | C12: $ | D12: $ | E12: $ | F12: $ | G12: $ | I12: $ | J12: $ | K12: $
A14: Software | B14: =+SALDOS!D29 -> 2572.1412 | C14: =+E14-B14 -> 0 | D14: 0 | E14: =+B14 -> 2572.1412 | F14: =+J14-I14 -> 2572.1412 | G14: 0 | H14: 0.2 | I14: 0 | J14: =-SALDOS!F39 -> 2572.1412 | K14: =+E14-J14 -> 0
A15: Hardware | B15: =+SALDOS!D31+SALDOS!D32 -> 1191.9639 | C15: =+E15-B15 -> 0 | D15: 0 | E15: =+B15 -> 1191.9639 | F15: =+J15-I15 -> 1191.9639 | G15: 0 | H15: 0.2 | I15: 0 | J15: =-SALDOS!F43 -> 1191.9639 | K15: =+E15-J15 -> 0
A16: Computadoras | B16: =+SALDOS!D33 -> 65735.004 | C16: =+E16-B16 -> 0 | D16: 0 | E16: =+B16 -> 65735.004 | F16: =+J16-I16 -> 58793.583 | G16: 0 | H16: 0.2 | I16: 487.6 | J16: =-SALDOS!F44 -> 59281.183 | K16: =+E16-J16 -> 6453.8209
A17: Equipos | B17: =+SALDOS!D34 -> 9663.3986 | C17: =+E17-B17 -> 0 | D17: 0 | E17: =+B17 -> 9663.3986 | F17: =+J17-I17 -> 9663.3986 | G17: 0 | H17: 0.2 | I17: 0 | J17: =-SALDOS!F41 -> 9663.3986 | K17: =+E17-J17 -> 0
A18: Muebles y Utiles | B18: =+SALDOS!D30 -> 9937.4078 | C18: =+E18-B18 -> 0 | D18: 0 | E18: =+B18 -> 9937.4078 | F18: =+J18-I18 -> 9398.4611 | G18: 0 | H18: 0.1 | I18: 21 | J18: =-SALDOS!F40 -> 9419.4611 | K18: =+E18-J18 -> 517.94664
A19: Instalaciones | B19: =+SALDOS!D35+SALDOS!D36 -> 33885.505 | C19: =+E19-B19 -> 0 | D19: 0 | E19: =+B19 -> 33885.505 | F19: =+J19-I19 -> 33885.505 | G19: 0 | H19: 0.1 | I19: 0 | J19: =-SALDOS!F42 -> 33885.505 | K19: =+E19-J19 -> 0
A20: Rodados | B20: =+SALDOS!D38 -> 567044.31 | C20: =+E20-B20 -> 0 | D20: 0 | E20: =+B20 -> 567044.31 | F20: =+J20-I20 -> 296166.08 | G20: 0 | H20: 0.2 | I20: 13581.9 | J20: =-SALDOS!F45 -> 309747.98 | K20: =+E20-J20 -> 257296.33
A21: =+EEPN!B17 -> Total al 31.7.2026 | B21: =SUM(B14:B20) -> 690029.73 | C21: =SUM(C14:C20) -> 0 | D21: =SUM(D14:D20) -> 0 | E21: =SUM(E14:E20) -> 690029.73 | F21: =SUM(F14:F20) -> 411671.13 | G21: =SUM(G14:G20) -> 0 | I21: =SUM(I14:I20) -> 14090.5 | J21: =SUM(J14:J20) -> 425761.63 | K21: =SUM(K14:K20) -> 264268.1
A23: Las notas y anexos adjuntos forman parte integrante de los estados contables.
A24: Informe profesional por separado.
C27: =+EEPN!C25 -> Miguel Ángel Alonso | I27: =+EEPN!H25 -> Tomas Furlong
C28: =+EEPN!C26 -> Contador Público (UCA) | I28: =+EEPN!H26 -> Transportes Furlong S.A.
C29: =+EEPN!C27 -> C.P.C.E.C.A.B.A. Tº176 Fº3 | I29: =+EEPN!H27 -> Apoderado

Sheet Anexo II
G1: ANEXO II
A5: Información Requerida por el Art. 64 Inc. b) de la Ley 19.550 | F5: Anexo II
A6: =+Activo!B3 -> Al 31 de Julio 2026
C8: TOTALES | D8: GASTOS | E8: GASTOS | F8: GASTOS | G8: TOTALES
B9: CONCEPTOS | C9: AL | D9: DE | E9: DE | G9: AL
C10: =+EESP!F13 -> 46234 | D10: ADMINISTRACION | E10: COMERCIALIZACION | F10: FINANCIEROS | G10: 31.03.02
B11: Amortizaciones | C11: =SUM(D11:F11) -> 63260.99 | D11: =+SALDOS!D134 -> 63260.99 | E11: 0 | F11: 0
B12: Accidentes | C12: =SUM(D12:F12) -> 0 | D12: 0 | E12: =+SALDOS!D173 -> 0 | F12: 0
B13: Acuerdo SECLO | C13: =SUM(D13:F13) -> 204.11 | D13: 0 | E13: =+SALDOS!D139 -> 204.11 | F13: 0
B14: Adelanto Viaje | C14: =SUM(D14:F14) -> 0 | D14: 0 | E14: =+SALDOS!D194 -> 0 | F14: 0
B15: Alquiler de autos | C15: =SUM(D15:F15) -> 0 | D15: 0 | E15: =+SALDOS!D172 -> 0 | F15: 0
B16: Alquileres | C16: =SUM(D16:F16) -> 4365.51 | D16: =+SALDOS!D177+SALDOS!D179+SALDOS!D136-SALDOS!E136 -> 4365.51 | E16: 0 | F16: 0
B17: Adicional obra social | C17: =SUM(D17:F17) -> 0 | D17: 0 | E17: =+SALDOS!D131 -> 0 | F17: 0
B18: Indemnizaciones | C18: =SUM(D18:F18) -> 0 | D18: 0 | E18: 0 | F18: 0
B19: Cargas Sociales | C19: =SUM(D19:F19) -> 220136.64 | D19: 0 | E19: =+SALDOS!D129 -> 220136.64 | F19: 0
B20: Reparaciones | C20: =SUM(D20:F20) -> 27649.36 | D20: =-SALDOS!E162 -> 0 | E20: =+SALDOS!D162 -> 27649.36 | F20: 0
B21: Catering | C21: =SUM(D21:F21) -> 0 | D21: 0 | E21: 0 | F21: 0
B22: Cesión de Derechos | C22: =SUM(D22:F22) -> 0 | D22: =+SALDOS!D193+SALDOS!D188 -> 0 | E22: 0 | F22: 0
B23: Combustible | C23: =SUM(D23:F23) -> 18371.81 | D23: 0 | E23: =+SALDOS!D156+SALDOS!D205 -> 18371.81 | F23: 0
B24: Comunicaciones | C24: =SUM(D24:F24) -> -3460.15 | D24: 0 | E24: =+SALDOS!D151+SALDOS!D130-SALDOS!E151 -> -3460.15 | F24: 0
B25: Custodia | C25: =SUM(D25:F25) -> 0 | D25: =SALDOS!D153 -> 0 | E25: 0 | F25: 0
B26: Capacitación | C26: =SUM(D26:F26) -> 0 | D26: 0 | E26: 0 | F26: 0
B27: Deudores incobrables | C27: =SUM(D27:F27) -> 0 | D27: 0 | E27: =+SALDOS!D189 -> 0 | F27: 0
B28: Despachantes | C28: =SUM(D28:F28) -> 388278.17 | D28: 0 | E28: =+SALDOS!D154 -> 388278.17 | F28: 0
B29: Donaciones | C29: =SUM(D29:F29) -> 8627.79 | D29: 0 | E29: =+SALDOS!D175 -> 8627.79 | F29: 0
B30: Estadía | C30: =SUM(D30:F30) -> 0 | D30: 0 | E30: =+SALDOS!D168 -> 0 | F30: 0
B31: Estibajes | C31: =SUM(D31:F31) -> 0 | D31: 0 | E31: =+SALDOS!D176 -> 0 | F31: 0
B32: Estacionamiento | C32: =SUM(D32:F32) -> 530.79 | D32: 0 | E32: =+SALDOS!D161 -> 530.79 | F32: 0
B33: Embargo radicación vehicular | C33: =SUM(D33:F33) -> 0 | D33: 0 | E33: =+SALDOS!D201 -> 0 | F33: 0
B34: Fletes | C34: =SUM(D34:F34) -> 3356.67 | D34: =+SALDOS!D167 -> 3356.67 | E34: =-SALDOS!E167 -> 0 | F34: 0
B35: Gastos de logística | C35: =SUM(D35:F35) -> 2519.38 | D35: 0 | E35: =+SALDOS!D171 -> 2519.38 | F35: 0
B36: Gastos de representación | C36: =SUM(D36:F36) -> 770.81 | D36: 0 | E36: =+SALDOS!D170 -> 770.81 | F36: 0
B37: Gastos Generales | C37: =SUM(D37:F37) -> 0 | D37: =+SALDOS!D124 -> 0 | E37: 0 | F37: 0
B38: Gastos PC | C38: =SUM(D38:F38) -> 0 | D38: 0 | E38: 0 | F38: 0
B39: Gastos varios | C39: =SUM(D39:F39) -> 1118.36 | D39: =+SALDOS!D163 -> 1118.36 | E39: =-SALDOS!E163 -> 0 | F39: 0
B40: Gastos varios clientes | C40: =SUM(D40:F40) -> 0 | D40: 0 | E40: =+SALDOS!D192 -> 0 | F40: 0
B41: Gastos varios personal | C41: =SUM(D41:F41) -> 1360.76 | D41: =+SALDOS!D202+SALDOS!D133 -> 1360.76 | E41: 0 | F41: 0
B42: Publicidad | C42: =SUM(D42:F42) -> 0 | D42: 0 | E42: =+SALDOS!D184 -> 0 | F42: 0
B43: Gastos y comisiones bancarias | C43: =SUM(D43:F43) -> 29891.64 | D43: 0 | E43: 0 | F43: =+SALDOS!D195+SALDOS!D207 -> 29891.64
B44: Gastos obra social | C44: =SUM(D44:F44) -> 0 | D44: =-SALDOS!E131 -> 0 | E44: 0 | F44: 0
B45: Gastos Hotelería | C45: =SUM(D45:F45) -> 31892.49 | D45: =+SALDOS!D148 -> 31892.49 | E45: 0 | F45: 0
B46: Gastos Gestoría | C46: =SUM(D46:F46) -> 0 | D46: =+SALDOS!D149 -> 0 | E46: 0 | F46: 0
B47: Gastos Telefonía | C47: =SUM(D47:F47) -> 0 | D47: 0 | E47: 0 | F47: 0
B48: Habilitaciones | C48: =SUM(D48:F48) -> 0 | D48: =+SALDOS!D147 -> 0 | E48: =+SALDOS!D146 -> 0 | F48: 0
B49: Honorarios profesionales | C49: =SUM(D49:F49) -> 123093.34 | D49: 0 | E49: =+SALDOS!D127 -> 123093.34 | F49: 0
B50: Honorarios directores | C50: =SUM(D50:F50) -> 0 | D50: 0 | E50: 0 | F50: 0
B51: Honorarios legales | C51: =SUM(D51:F51) -> 6917.72 | D51: =+SALDOS!D145 -> 6917.72 | E51: 0 | F51: 0
B52: Indumentaria | C52: =SUM(D52:F52) -> 0 | D52: 0 | E52: 0 | F52: 0
B53: Impuestos varios | C53: =SUM(D53:F53) -> 0 | D53: 0 | E53: 0 | F53: 0
B54: Imp. Bienes Acc. Y Part. Soc. | C54: =SUM(D54:F54) -> 2342.32 | D54: 0 | E54: =+SALDOS!D181 -> 2342.32 | F54: 0
B55: Imp. A los créditos | C55: =SUM(D55:F55) -> 0 | D55: 0 | E55: 0 | F55: =+SALDOS!D198 -> 0
B56: Imp. A los débitos y créditos | C56: =SUM(D56:F56) -> 0 | D56: 0 | E56: 0 | F56: =+SALDOS!D196 -> 0
B57: imp. Al cheque | C57: =SUM(D57:F57) -> 0 | D57: 0 | E57: 0 | F57: =+SALDOS!D203 -> 0
B58: Intereses resarcitorios | C58: =SUM(D58:F58) -> 65.43 | D58: 0 | E58: =+SALDOS!D199 -> 65.43 | F58: =+SALDOS!D208 -> 0
B59: Juicios | C59: =SUM(D59:F59) -> 0 | D59: 0 | E59: =+SALDOS!D185 -> 0 | F59: 0
B60: Librería | C60: =SUM(D60:F60) -> 1883.11 | D60: =+SALDOS!D128 -> 1883.11 | E60: 0 | F60: 0
B61: Leasing | C61: =SUM(D61:F61) -> 0 | D61: 0 | E61: =+SALDOS!D200 -> 0 | F61: 0
B62: Legalizaciones | C62: =SUM(D62:F62) -> 0 | D62: 0 | E62: 0 | F62: 0
B63: Locomoción | C63: =SUM(D63:F63) -> 0 | D63: 0 | E63: =+SALDOS!D152 -> 0 | F63: 0
B64: Mantenimiento | C64: =SUM(D64:F64) -> 4934.13 | D64: 0 | E64: =+SALDOS!D141-SALDOS!E135 -> 4934.13 | F64: 0
B65: Mantenimiento y lav. de flota | C65: =SUM(D65:F65) -> 275.24 | D65: 0 | E65: =+SALDOS!D155+SALDOS!D157+SALDOS!D187+SALDOS!D190 -> 275.24 | F65: 0
B66: Mensajería y trámites | C66: =SUM(D66:F66) -> 0 | D66: =+SALDOS!D158 -> 0 | E66: 0 | F66: 0
B67: Molilidad y viáticos | C67: =SUM(D67:F67) -> 2518.73 | D67: =+SALDOS!D125 -> 2518.73 | E67: 0 | F67: 0
B68: Multas | C68: =SUM(D68:F68) -> 3033.18 | D68: 0 | E68: =+SALDOS!D160+SALDOS!D169 -> 3033.18 | F68: 0
B69: Patentes | C69: =SUM(D69:F69) -> 0 | D69: 0 | E69: =+SALDOS!D182 -> 0 | F69: 0
B70: Peajes | C70: =SUM(D70:F70) -> 13081.47 | D70: 0 | E70: =+SALDOS!D159 -> 13081.47 | F70: 0
B71: Serv de Transporte y Almacenamiento | C71: =SUM(D71:F71) -> 3210.92 | D71: 0 | E71: =+SALDOS!D206-SALDOS!E125 -> 3210.92 | F71: 0
B72: Reparaciones flota | C72: =SUM(D72:F72) -> 0 | D72: 0 | E72: =+SALDOS!D166 -> 0 | F72: 0
B73: Refrigerios | C73: =SUM(D73:F73) -> 0 | D73: =+SALDOS!D165+SALDOS!D135 -> 0 | E73: 0 | F73: 0
B74: Ropa de trabajo | C74: =SUM(D74:F74) -> 0 | D74: 0 | E74: =+SALDOS!D180+SALDOS!D191 -> 0 | F74: 0
B75: Seguros | C75: =SUM(D75:F75) -> 278459.11 | D75: 0 | E75: =-SALDOS!E150+SALDOS!D150 -> 278459.11 | F75: 0
B76: Seguridad y vigilancia | C76: =SUM(D76:F76) -> 776.06 | D76: 0 | E76: =+SALDOS!D164 -> 776.06 | F76: 0
B77: Servicios de limpieza | C77: =SUM(D77:F77) -> 0 | D77: 0 | E77: 0 | F77: 0
B78: Siniestros | C78: =SUM(D78:F78) -> 0 | D78: =+SALDOS!D174 -> 0 | E78: =+SALDOS!D204 -> 0 | F78: 0
B79: Sueldos | C79: =SUM(D79:F79) -> 711028.12 | D79: 0 | E79: =+SALDOS!D126+SALDOS!D143 -> 711028.12 | F79: 0
B80: Salario Complementario del decreto 332/20 | C80: =SUM(D80:F80) -> 0 | D80: 0 | E80: =-SALDOS!E140 -> 0 | F80: 0
B81: Tasas Senasa | C81: =SUM(D81:F81) -> 126714.18 | D81: 0 | E81: =+SALDOS!D183 -> 126714.18 | F81: 0
B82: Tasas IGJ, AFIP | C82: =SUM(D82:F82) -> 0 | D82: =+SALDOS!D138+SALDOS!D137 -> 0 | E82: 0 | F82: 0
B83: Gastos Médicos | C83: =SUM(D83:F83) -> 127567.82 | D83: =SALDOS!D144 -> 127567.82 | E83: 0 | F83: 0
B84: =+EEPN!B17 -> Total al 31.7.2026 | C84: =SUM(C11:C83) -> 2204776 | D84: =SUM(D11:D83) -> 244242.16 | E84: =SUM(E11:E83) -> 1930642.2 | F84: =SUM(F11:F83) -> 29891.64 | G84: =SUM(#REF!) -> #REF!
B85: Total al 31.12.05 | C85: =SUM(C15:C84) -> 4346086.9 | D85: 0 | E85: 0 | F85: 0 | G85: =SUM(D85:F85) -> 0
A87: Las notas y anexos adjuntos forman parte integrante de los estados contables.
A88: Informe profesional por separado.
C93: =+'Anexo I'!C27 -> Miguel Ángel Alonso | E93: =+'Anexo I'!I27 -> Tomas Furlong
C94: =+'Anexo I'!C28 -> Contador Público (UCA) | E94: =+'Anexo I'!I28 -> Transportes Furlong S.A.
C95: =+'Anexo I'!C29 -> C.P.C.E.C.A.B.A. Tº176 Fº3 | E95: =+'Anexo I'!I29 -> Apoderado

Sheet Bienes
A3: Calculo De Bienes Societarios de Transporte Furlong Barsil 2009
A4: =+EESP!F31 -> 508409.5 | B4: Activo
A5: =+EESP!L23 -> 2016408 | B5: Pasivo
A6: =+A4-A5 -> -1507998.5 | B6: Patrimonio Neto
A7: =+A6*0.005 -> -7539.9925 | B7: Impuesto
D11: ,
