Workbook

Sheet SALDOS
B1: TRANSPORTES FURLONG S.A.
B2: del 01/07/2026 al 31/07/2026 | F2: T.C. Reales al 31/7/26 | G2: 293.17575
C3: Deudor | D3: Acreedor | E3: saldo
B5: Activo
B7: 1110100330 FONDO FIJO BS. AS. | C7: =IF(E7>0,E7,0) -> 0 | D7: =IF(E7<0,E7*-1,0) -> 904.95437 | E7: =IFERROR(VLOOKUP(B7,$B$229:$C$286,2,FALSE),0) -> -904.95437
B8: 1110100340 FONDO FIJO SENASA | C8: =IF(E8>0,E8,0) -> 0 | D8: =IF(E8<0,E8*-1,0) -> 0 | E8: =IFERROR(VLOOKUP(B8,$B$229:$C$286,2,FALSE),0)
B9: 1110100420 BANCO FRANCES C/C | C9: =IF(E9>0,E9,0) -> 0 | D9: =IF(E9<0,E9*-1,0) -> 85668.934 | E9: =IFERROR(VLOOKUP(B9,$B$229:$C$286,2,FALSE),0) -> -85668.934
B10: 1110101050 FONDO FIJO ADELANTOS PDT | C10: =IF(E10>0,E10,0) -> 0 | D10: =IF(E10<0,E10*-1,0) -> 0 | E10: =IFERROR(VLOOKUP(B10,$B$229:$C$286,2,FALSE),0)
B11: 1120100100 FORD | C11: =IF(E11>0,E11,0) -> 0 | D11: =IF(E11<0,E11*-1,0) -> 2183.6622 | E11: =IFERROR(VLOOKUP(B11,$B$229:$C$286,2,FALSE),0) -> -2183.6622
B12: 1120100400 TRANSPORTES FURLONG S.A. AR | C12: =IF(E12>0,E12,0) -> 0 | D12: =IF(E12<0,E12*-1,0) -> 338665.61 | E12: =IFERROR(VLOOKUP(B12,$B$229:$C$286,2,FALSE),0) -> -338665.61
B13: 1120100700 RENAULT ARG. S.A. | C13: =IF(E13>0,E13,0) -> 0 | D13: =IF(E13<0,E13*-1,0) -> 0 | E13: =IFERROR(VLOOKUP(B13,$B$229:$C$286,2,FALSE),0)
B14: 1120101300 VOLKSWAGEN ARGENTINA S.A. | C14: =IF(E14>0,E14,0) -> 1039.3258 | D14: =IF(E14<0,E14*-1,0) -> 0 | E14: =IFERROR(VLOOKUP(B14,$B$229:$C$286,2,FALSE),0) -> 1039.3258
B15: 1120101600 FCA AUTOMOBILES ARGENTINA S.A. | C15: =IF(E15>0,E15,0) -> 0 | D15: =IF(E15<0,E15*-1,0) -> 0 | E15: =IFERROR(VLOOKUP(B15,$B$229:$C$286,2,FALSE),0)
B16: 1120131000 CNH ARGENTINA S.A. | C16: =IF(E16>0,E16,0) -> 0 | D16: =IF(E16<0,E16*-1,0) -> 371.40425 | E16: =IFERROR(VLOOKUP(B16,$B$229:$C$286,2,FALSE),0) -> -371.40425
B17: 1120138000 STELLANTIS AUTOMOVILES DE ARGENTINA S. A | C17: =IF(E17>0,E17,0) -> 0 | D17: =IF(E17<0,E17*-1,0) -> 655.71819 | E17: =IFERROR(VLOOKUP(B17,$B$229:$C$286,2,FALSE),0) -> -655.71819
B18: 1140300100 ANTICIPO A PDT | C18: =IF(E18>0,E18,0) -> 14061.316 | D18: =IF(E18<0,E18*-1,0) -> 0 | E18: =IFERROR(VLOOKUP(B18,$B$229:$C$286,2,FALSE),0) -> 14061.316
... B46: 1220400000 AMORT. ACUM. INSTALACIONES | C46: =IF(E46>0,E46,0) -> 0 | D46: =IF(E46<0,E46*-1,0) -> 0 | E46: =IFERROR(VLOOKUP(B46,$B$229:$C$286,2,FALSE),0)
B47: 1220600000 AMORT. ACUM. COMPUTADORAS | C47: =IF(E47>0,E47,0) -> 0 | D47: =IF(E47<0,E47*-1,0) -> 293.35549 | E47: =IFERROR(VLOOKUP(B47,$B$229:$C$286,2,FALSE),0) -> -293.35549 | G47: =SUM(E29:E48) -> -8477.1634
B48: 1220700000 AMORT. ACUM. RODADOS | C48: =IF(E48>0,E48,0) -> 0 | D48: =IF(E48<0,E48*-1,0) -> 8171.1751 | E48: =IFERROR(VLOOKUP(B48,$B$229:$C$286,2,FALSE),0) -> -8171.1751
E49: =SUM(E7:E48) -> -516470.14 | F49: =+E49-EESP!F33 -> -338665.61 | G49: =-F49+E12 -> 0
B50: Pasivo
A52: COTELCAM | B52: 2110100300 COTELCAM | C52: =IF(E52>0,E52,0) -> 0 | D52: =IF(E52<0,E52*-1,0) -> 0 | E52: =IFERROR(VLOOKUP(B52,$B$229:$C$286,2,FALSE),0)
B53: 2110102400 OSDE | C53: =IF(E53>0,E53,0) -> 0 | D53: =IF(E53<0,E53*-1,0) -> 0 | E53: =IFERROR(VLOOKUP(B53,$B$229:$C$286,2,FALSE),0)
A54: ESTUDIO CORTES | B54: 2110100900 ESTUDIO CORTES | C54: =IF(E54>0,E54,0) -> 0 | D54: =IF(E54<0,E54*-1,0) -> 0 | E54: =IFERROR(VLOOKUP(B54,$B$229:$C$286,2,FALSE),0)
A55: VENEZIA AUTOS SA | B55: 2110101500 VENEZIA AUTOS SA | C55: =IF(E55>0,E55,0) -> 0 | D55: =IF(E55<0,E55*-1,0) -> 0 | E55: =IFERROR(VLOOKUP(B55,$B$229:$C$286,2,FALSE),0)
A56: TRANSPORTES FURLONG ARG. S.A | B56: 2110101800 TRANSPORTES FURLONG ARG. S.A | C56: =IF(E56>0,E56,0) -> 0 | D56: =IF(E56<0,E56*-1,0) -> 0 | E56: =IFERROR(VLOOKUP(B56,$B$229:$C$286,2,FALSE),0)
A57: MERCOVIA S.A. | B57: 2110105400 MERCOVIA S.A. | C57: =IF(E57>0,E57,0) -> 202.40027 | D57: =IF(E57<0,E57*-1,0) | E57: =IFERROR(VLOOKUP(B57,$B$229:$C$286,2,FALSE),0) -> 202.40027
A58: OKINET SRL | B58: 2110106800 OKINET SRL | C58: =IF(E58>0,E58,0) -> 554.38087 | D58: =IF(E58<0,E58*-1,0) | E58: =IFERROR(VLOOKUP(B58,$B$229:$C$286,2,FALSE),0) -> 554.38087
A59: LA MERIDIONAL S.A. | B59: 2110108900 LA MERIDIONAL S.A. | C59: =IF(E59>0,E59,0) | D59: =IF(E59<0,E59*-1,0) | E59: =IFERROR(VLOOKUP(B59,$B$229:$C$286,2,FALSE),0)
A60: GIULI SERGIO ALBERTO | B60: 2110115100 GIULI SERGIO ALBERTO | C60: =IF(E60>0,E60,0) | D60: =IF(E60<0,E60*-1,0) | E60: =IFERROR(VLOOKUP(B60,$B$229:$C$286,2,FALSE),0)
A61: CARLOS ALEJANDRO DUMA | B61: 2110116700 CARLOS ALEJANDRO DUMA | C61: =IF(E61>0,E61,0) | D61: =IF(E61<0,E61*-1,0) | E61: =IFERROR(VLOOKUP(B61,$B$229:$C$286,2,FALSE),0)
A62: MANGGINI PABLO Y ULISES S.H | B62: 2110118000 MANGGINI PABLO Y ULISES S.H | C62: =IF(E62>0,E62,0) | D62: =IF(E62<0,E62*-1,0) | E62: =IFERROR(VLOOKUP(B62,$B$229:$C$286,2,FALSE),0)
A63: QBE SEGUROS LA BUENOS AIRES S.A. | B63: 2110120600 QBE SEGUROS LA BUENOS AIRES S.A. | C63: =IF(E63>0,E63,0) -> 76974.842 | D63: =IF(E63<0,E63*-1,0) | E63: =IFERROR(VLOOKUP(B63,$B$229:$C$286,2,FALSE),0) -> 76974.842
B64: 2110131700 LIBRERIA MAYA SA | C64: =IF(E64>0,E64,0) | D64: =IF(E64<0,E64*-1,0) | E64: =IFERROR(VLOOKUP(B64,$B$229:$C$286,2,FALSE),0)
A65: SERVI OESTE S.A | B65: 2110125800 SERVI OESTE S.A | C65: =IF(E65>0,E65,0) | D65: =IF(E65<0,E65*-1,0) | E65: =IFERROR(VLOOKUP(B65,$B$229:$C$286,2,FALSE),0)
A66: RODRIGO E. FONTAN | B66: 2110126900 RODRIGO E. FONTAN | C66: =IF(E66>0,E66,0) | D66: =IF(E66<0,E66*-1,0) | E66: =IFERROR(VLOOKUP(B66,$B$229:$C$286,2,FALSE),0)
B67: 2110132900 AURELIA S.A.C.I.F. | C67: =IF(E67>0,E67,0) | D67: =IF(E67<0,E67*-1,0) -> 27115.822 | E67: =IFERROR(VLOOKUP(B67,$B$229:$C$286,2,FALSE),0) -> -27115.822
A68: AB Fiduciaria S.A. | B68: 2110127300 AB Fiduciaria S.A. | C68: =IF(E68>0,E68,0) | D68: =IF(E68<0,E68*-1,0) | E68: =IFERROR(VLOOKUP(B68,$B$229:$C$286,2,FALSE),0)
A69: LAURA DI GIROLAMO | B69: 2110129600 LAURA DI GIROLAMO | C69: =IF(E69>0,E69,0) | D69: =IF(E69<0,E69*-1,0) | E69: =IFERROR(VLOOKUP(B69,$B$229:$C$286,2,FALSE),0)
A70: LUCIO JORGE ZEMBORAIN | B70: 2110130100 LUCIO JORGE ZEMBORAIN | C70: =IF(E70>0,E70,0) | D70: =IF(E70<0,E70*-1,0) | E70: =IFERROR(VLOOKUP(B70,$B$229:$C$286,2,FALSE),0)
A71: HOCO S.A. | B71: 2110134300 HOCO S.A. | C71: =IF(E71>0,E71,0) | D71: =IF(E71<0,E71*-1,0) | E71: =IFERROR(VLOOKUP(B71,$B$229:$C$286,2,FALSE),0)
A72: FIDEICOMISO RS CAMPANA | B72: 2110141500 FIDEICOMISO RS CAMPANA | C72: =IF(E72>0,E72,0) | D72: =IF(E72<0,E72*-1,0) | E72: =IFERROR(VLOOKUP(B72,$B$229:$C$286,2,FALSE),0)
A73: ZOPPI MARIANO | B73: 2110160100 ZOPPI MARIANO | C73: =IF(E73>0,E73,0) | D73: =IF(E73<0,E73*-1,0) | E73: =IFERROR(VLOOKUP(B73,$B$229:$C$286,2,FALSE),0)
A74: TANCO PADILLA ALFREDO | B74: 2110160500 TANCO PADILLA ALFREDO | C74: =IF(E74>0,E74,0) | D74: =IF(E74<0,E74*-1,0) | E74: =IFERROR(VLOOKUP(B74,$B$229:$C$286,2,FALSE),0)
A75: QUEREJETA LUIS | B75: 2110161200 QUEREJETA LUIS | C75: =IF(E75>0,E75,0) | D75: =IF(E75<0,E75*-1,0) | E75: =IFERROR(VLOOKUP(B75,$B$229:$C$286,2,FALSE),0)
A76: Marcos Gabriel Giordano | B76: 2116100000 Marcos Gabriel Giordano | C76: =IF(E76>0,E76,0) | D76: =IF(E76<0,E76*-1,0) | E76: =IFERROR(VLOOKUP(B76,$B$229:$C$286,2,FALSE),0)
A77: OPUS INSPECTION S.A. | B77: 2110803600 OPUS INSPECTION S.A. | C77: =IF(E77>0,E77,0) | D77: =IF(E77<0,E77*-1,0) | E77: =IFERROR(VLOOKUP(B77,$B$229:$C$286,2,FALSE),0)
A78: FEDERACION PATRONAL SEGUROS S.A | B78: 2110192100 FEDERACION PATRONAL SEGUROS S.A | C78: =IF(E78>0,E78,0) -> 654.07723 | D78: =IF(E78<0,E78*-1,0) | E78: =IFERROR(VLOOKUP(B78,$B$229:$C$286,2,FALSE),0) -> 654.07723
A79: RUBIN DE CELIS AGUSTIN | B79: 2110195000 RUBIN DE CELIS AGUSTIN | C79: =IF(E79>0,E79,0) | D79: =IF(E79<0,E79*-1,0) | E79: =IFERROR(VLOOKUP(B79,$B$229:$C$286,2,FALSE),0)
... A88: INTERESES A DEVENGAR T064177 | B88: 2110406000 INTERESES A DEVENGAR T064177 | C88: =IF(E88>0,E88,0) | D88: =IF(E88<0,E88*-1,0) | E88: =IFERROR(VLOOKUP(B88,$B$229:$C$286,2,FALSE),0)
B89: 2110800400 SEGURA PADILLA DOLORES DEL VALLE | C89: =IF(E89>0,E89,0) | D89: =IF(E89<0,E89*-1,0) | E89: =IFERROR(VLOOKUP(B89,$B$229:$C$286,2,FALSE),0)
A90: ADELANTO CASA MATRIZ | B90: 2110700100 ADELANTO CASA MATRIZ | C90: =IF(E90>0,E90,0) -> 27115.822 | D90: =IF(E90<0,E90*-1,0) | E90: =IFERROR(VLOOKUP(B90,$B$229:$C$286,2,FALSE),0) -> 27115.822 | G90: =+E12 -> -338665.61
A91: ACUERDOS CNRT A PAGAR | B91: 2110700600 ACUERDOS CNRT A PAGAR | C91: =IF(E91>0,E91,0) | D91: =IF(E91<0,E91*-1,0) | E91: =IFERROR(VLOOKUP(B91,$B$229:$C$286,2,FALSE),0)
A92: LETE MARIO NELSON | B92: 2110801500 LETE MARIO NELSON | C92: =IF(E92>0,E92,0) | D92: =IF(E92<0,E92*-1,0) | E92: =IFERROR(VLOOKUP(B92,$B$229:$C$286,2,FALSE),0)
A93: ESTUDIO ADUANERO BERTORELLO & Asoc SRL | B93: 2110801800 ESTUDIO ADUANERO BERTORELLO & Asoc SRL | C93: =IF(E93>0,E93,0) | D93: =IF(E93<0,E93*-1,0) | E93: =IFERROR(VLOOKUP(B93,$B$229:$C$286,2,FALSE),0)
A94: SERGIO MARCELO MARTIN | B94: 2113200000 SERGIO MARCELO MARTIN | C94: =IF(E94>0,E94,0) | D94: =IF(E94<0,E94*-1,0) | E94: =IFERROR(VLOOKUP(B94,$B$229:$C$286,2,FALSE),0)
A95: AUTOPISTAS DEL SOL S.A. | B95: 2110803300 AUTOPISTAS DEL SOL S.A. | C95: =IF(E95>0,E95,0) | D95: =IF(E95<0,E95*-1,0) | E95: =IFERROR(VLOOKUP(B95,$B$229:$C$286,2,FALSE),0)
B96: 2110803700 AUTOPISTAS URBANAS S.A. | C96: =IF(E96>0,E96,0) | D96: =IF(E96<0,E96*-1,0) | E96: =IFERROR(VLOOKUP(B96,$B$229:$C$286,2,FALSE),0)
B97: 2110804300 ZURICH ASEGURADORA ARGENTINA S.A | C97: =IF(E97>0,E97,0) | D97: =IF(E97<0,E97*-1,0) -> 33250.099 | E97: =IFERROR(VLOOKUP(B97,$B$229:$C$286,2,FALSE),0) -> -33250.099
B98: 2110804800 AUTOPISTAS DE BUENOS AIRES SA | C98: =IF(E98>0,E98,0) | D98: =IF(E98<0,E98*-1,0) | E98: =IFERROR(VLOOKUP(B98,$B$229:$C$286,2,FALSE),0)
A99: AUTOPISTAS DE BUENOS AIRES SA | B99: 2110804100 FERNANDO ATILIO BERTORELLO | C99: =IF(E99>0,E99,0) | D99: =IF(E99<0,E99*-1,0) | E99: =IFERROR(VLOOKUP(B99,$B$229:$C$286,2,FALSE),0)
A100: MARCOS RAUL RODRIGUEZ | B100: 2110804400 MARCOS RAUL RODRIGUEZ | C100: =IF(E100>0,E100,0) | D100: =IF(E100<0,E100*-1,0) | E100: =IFERROR(VLOOKUP(B100,$B$229:$C$286,2,FALSE),0)
B101: 2110805400 HOTEL RENTAL SUITES CAMPANA | C101: =IF(E101>0,E101,0) | D101: =IF(E101<0,E101*-1,0) | E101: =IFERROR(VLOOKUP(B101,$B$229:$C$286,2,FALSE),0)
B102: 2116300000 Sistemas Bejerman | C102: =IF(E102>0,E102,0) -> 166.02559 | D102: =IF(E102<0,E102*-1,0) | E102: =IFERROR(VLOOKUP(B102,$B$229:$C$286,2,FALSE),0) -> 166.02559
B103: 2116400000 AUTOVIA DEL MERCOSUR | C103: =IF(E103>0,E103,0) | D103: =IF(E103<0,E103*-1,0) | E103: =IFERROR(VLOOKUP(B103,$B$229:$C$286,2,FALSE),0)
B104: 2110805100 Concesionaria Rodovias | C104: =IF(E104>0,E104,0) | D104: =IF(E104<0,E104*-1,0) -> 3720.6358 | E104: =IFERROR(VLOOKUP(B104,$B$229:$C$286,2,FALSE),0) -> -3720.6358
B105: 2112100000 ARTEAGA PEDRO | C105: =IF(E105>0,E105,0) | D105: =IF(E105<0,E105*-1,0) | E105: =IFERROR(VLOOKUP(B105,$B$229:$C$286,2,FALSE),0)
B106: 2115900000 ROMERO SILVIA ADRIANA | C106: =IF(E106>0,E106,0) | D106: =IF(E106<0,E106*-1,0) | E106: =IFERROR(VLOOKUP(B106,$B$229:$C$286,2,FALSE),0)
A107: FERNANDEZ MEDINA MARIA ELSA | B107: 2113000000 FERNANDEZ MEDINA MARIA ELSA | C107: =IF(E107>0,E107,0) | D107: =IF(E107<0,E107*-1,0) | E107: =IFERROR(VLOOKUP(B107,$B$229:$C$286,2,FALSE),0)
A108: FRONTAR LIBRE | B108: 2113400000 FRONTAR LIBRE | C108: =IF(E108>0,E108,0) | D108: =IF(E108<0,E108*-1,0) -> 516.76152 | E108: =IFERROR(VLOOKUP(B108,$B$229:$C$286,2,FALSE),0) -> -516.76152
A109: POLIPREN ARGENTINA SRL | B109: 2113700000 POLIPREN ARGENTINA SRL | C109: =IF(E109>0,E109,0) | D109: =IF(E109<0,E109*-1,0) | E109: =IFERROR(VLOOKUP(B109,$B$229:$C$286,2,FALSE),0)
E110: =SUM(E52:E109) -> 169852.01 | F110: =+E110+E12+EESP!L24 -> -0.010477529
B111: Patrimonio Neto
B113: 331000000 RNA EJERCICIO ANTERIOR | C113: =+IF(E113>0,E113,0) | D113: =+IF(E113<0,-E113,0) | E113: =IFERROR(VLOOKUP(B113,$B$229:$C$286,2,FALSE),0)
B114: 332000000 RESULTADO DEL EJERCICIO | C114: =+IF(E114>0,E114,0) | D114: =-IF(E114<0,E114,0) | E114: =IFERROR(VLOOKUP(B114,$B$229:$C$286,2,FALSE),0)
B115: 333000000 A.R.E.A | C115: 0 | D115: 0 | E115: =IFERROR(VLOOKUP(B115,$B$229:$C$286,2,FALSE),0)
E116: =SUM(E113:E115)
B117: Resultados
B119: 4110100000 SERVICIOS PRESTADOS | C119: =IF(E119>0,E119,0) | D119: =IF(E119<0,E119*-1,0) | E119: =IFERROR(VLOOKUP(B119,$B$229:$C$286,2,FALSE),0)
B120: 4120200000 DIFERENCIA DE COTIZACIÓN | C120: =IF(E120>0,E120,0) | D120: =IF(E120<0,E120*-1,0) | E120: =IFERROR(VLOOKUP(B120,$B$229:$C$286,2,FALSE),0)
B121: 4231100000 RESULTADO POR TENENCIA FCI | C121: =IF(E121>0,E121,0) | D121: =IF(E121<0,E121*-1,0) -> 2310.25 | E121: =IFERROR(VLOOKUP(B121,$B$229:$C$286,2,FALSE),0) -> -2310.25
B122: RECUPERO DE GASTOS | C122: =IF(E122>0,E122,0) | D122: =IF(E122<0,E122*-1,0) | E122: =IFERROR(VLOOKUP(B122,$B$229:$C$286,2,FALSE),0)
B123: 412020000 DIFERENCIA DE COTIZACION | C123: =IF(E123>0,E123,0) | D123: =IF(E123<0,E123*-1,0) | E123: =IFERROR(VLOOKUP(B123,$B$229:$C$286,2,FALSE),0)
B124: 4120400000 RECUPERO DE SINIESTRO | C124: =IF(E124>0,E124,0) | D124: =IF(E124<0,E124*-1,0) | E124: =IFERROR(VLOOKUP(B124,$B$229:$C$286,2,FALSE),0)
B125: 4120300000 VENTA RODADO | C125: =IF(E125>0,E125,0) | D125: =IF(E125<0,E125*-1,0) | E125: =IFERROR(VLOOKUP(B125,$B$229:$C$286,2,FALSE),0)
B126: 4120500000 INTERESES GANADOS | C126: =IF(E126>0,E126,0) | D126: =IF(E126<0,E126*-1,0) | E126: =IFERROR(VLOOKUP(B126,$B$229:$C$286,2,FALSE),0)
B127: 421010000 GASTOS GENERALES | C127: =IF(E127>0,E127,0) | D127: =IF(E127<0,E127*-1,0) | E127: =IFERROR(VLOOKUP(B127,$B$229:$C$286,2,FALSE),0)
B128: 4210200000 MOVILIDAD Y VIÁTICOS | C128: =IF(E128>0,E128,0) | D128: =IF(E128<0,E128*-1,0) | E128: =IFERROR(VLOOKUP(B128,$B$229:$C$286,2,FALSE),0)
B129: 4210300000 SUELDOS | C129: =IF(E129>0,E129,0) -> 93970.96 | D129: =IF(E129<0,E129*-1,0) | E129: =IFERROR(VLOOKUP(B129,$B$229:$C$286,2,FALSE),0) -> 93970.96
B130: 4210400000 HONORARIOS PROFESIONALES | C130: =IF(E130>0,E130,0) -> 15732.21 | D130: =IF(E130<0,E130*-1,0) | E130: =IFERROR(VLOOKUP(B130,$B$229:$C$286,2,FALSE),0) -> 15732.21
... B221: 4230400000 INTERESES RESARCITORIOS | C221: =IF(E221>0,E221,0) -> 61.24 | D221: =IF(E221<0,E221*-1,0) | E221: =IFERROR(VLOOKUP(B221,$B$229:$C$286,2,FALSE),0) -> 61.24
B222: DIFERENCIA DE CAMBIO | C222: =IF(E222>0,E222,0) | D222: 3231.7768 | E222: -3231.7768
E223: =SUM(E119:E222) -> 346618.12
C224: =+SUM(C6:C223) -> 719985.24 | D224: =+SUM(D6:D222) -> 719985.24 | F224: =+C224-D224 | G224: Diferencia
B229: Cuenta | C229: Monto
B230: 1110100330 FONDO FIJO BS. AS. | C230: -904.95437 | D230: -904.95437
B231: 1110100420 BANCO FRANCES C/C | C231: -85668.934 | D231: -85668.934
B232: 1120100100 FORD | C232: -2183.6622 | D232: -2183.6622
B233: 1120100400 TRANSPORTES FURLONG S.A. AR | C233: -338665.61 | D233: -338665.61
B234: 1120101300 VOLKSWAGEN ARGENTINA S.A. | C234: 1039.3258 | D234: 1039.3258
...

Sheet EESP
A1: TRANSPORTES FURLONG S.A
A3: 31 de Julio de 2026
A5: Estado de Situación Patrimonial
F9: 46234 | L9: =+F9 -> 46234 | M9: 38717
B10: ACTIVO: | I10: PASIVO
C11: ACTIVO CORRIENTE | I11: PASIVO CORRIENTE
D12: Caja y bancos (Nota 4.a) | F12: =+Activo!F16 -> -86573.889 | J12: Deudas
D13: Creditos comerciales | F13: 0 | K13: Deudas impositivas
D14: Creditos Impositivos | F14: =+Activo!F34 -> 0 | K14: Deudas accionistas | L14: 0
D15: Inversiones temporarias (Nota 4.b) | F15: =+Activo!F23 -> -70990.504 | K15: Comerciales (Nota 4.e) | L15: =+Pasivo!E16 -> 297601.37
K16: Otras deudas (Nota 4.f) | L16: =+Pasivo!E22 -> 0
D17: Créditos por ventas (Nota 4.c) | F17: =+Activo!F26 -> -2171.4588 | K17: Remuneraciones y cs.sociales (Nota 4.f) | L17: =+Pasivo!E28 -> -129433.41
K18: Cargas fiscales (Nota 4.h) | L18: =+Pasivo!E35 -> 645.62953
D19: Otros activos | F19: 0 | K19: Anticipos de clientes | L19: 0
K20: Dividendos a pagar | L20: 0
D22: Otros Creditos (Nota 4.d) | F22: =+Activo!F57 -> -9591.5153 | J22: Total deudas | L22: =SUM(L13:L21) -> 168813.58
J23: Previsones | L23: 0
C24: Total del Activo corriente | F24: =SUM(F12:G22) -> -169327.37 | I24: Total del Pasivo Corriente | L24: =+L22+L23 -> 168813.58
I25: Total del Pasivo | L25: =+L24 -> 168813.58
C28: ACTIVO NO CORRIENTE
D29: Bienes de uso (Anexo l ) | F29: =+'Anexo I'!K18 -> -8477.1634 | I29: PATRIMONIO NETO (Según estado respec.) | L29: =+EEPN!J18 -> -346618.12
C31: Total del Activo no corriente | F31: =SUM(F29:F30) -> -8477.1634 | L31: =+L29 -> -346618.12
C33: Total del Activo | F33: =+F24+F31 -> -177804.53 | I33: Total del Pasivo y Patrimonio Neto | L33: =+L25+L31+0.01 -> -177804.53

Sheet EERR
A1: TRANSPORTES FURLONG S.A
A3: =+EESP!A3 -> 31 de Julio de 2026
A5: Estado de Resultados
C9: =+EESP!F9 -> 46234 | D9: =+EESP!G9 -> 0
A12: Ingresos por servicios prestados | C12: =+SALDOS!D119-SALDOS!C119
A15: Gastos de comercialización (Anexo II) | C15: =+'Anexo II'!E108 -> 317420.98
A16: Gastos de administración (Anexo II) | C16: =+'Anexo II'!D108 -> 28817.34
A17: Gastos de financieros (Anexo II) | C17: =+'Anexo II'!F108 -> 5921.83
A19: Subtotal | C19: =+C12+C13-C15-C16-C17 -> -352160.15
A20: Resultado venta bienes de uso | C20: =+SALDOS!D125
A21: Otros Ingresos | C21: =+SALDOS!D121+SALDOS!D124+SALDOS!D205+SALDOS!D122 -> 2310.25
A22: Diferencia de cambio | C22: =+SALDOS!D222 -> 3231.7768
A23: Diferencia de cotización | C23: =-SALDOS!C222
A24: Intereses | C24: =+SALDOS!D126
A25: Ganancia antes de impuesto | C25: =+C19+C20+C22+C21+C24+C23 -> -346618.12
A26: Impuesto a las Ganancias
A28: Ganancia del ejercicio | C28: =+C25-C26 -> -346618.12

Sheet EEPN
A1: =+EESP!A1 -> TRANSPORTES FURLONG S.A
A2: =+EESP!A3 -> 31 de Julio de 2026 | B2: =+EESP!A3 -> 31 de Julio de 2026
A3: Estado de Evolución del Patrimonio Neto
J5: =+EESP!F9 -> 46234 | K5: =+EESP!G9 -> 0
B6: CONCEPTO | C6: Aportes de los propietarios | F6: Ganancias | G6: Reservadas | I6: Resultados | J6: Total del | K6: Total del
C7: Capital | D7: Ajuste | E7: Total de | F7: Reserva | G7: Otras | H7: Aportes | I7: no | J7: patrimonio | K7: patrimonio
D8: de Capital | E8: Capital | F8: legal | G8: reservas | H8: Irrevocables | I8: asignados | J8: neto | K8: neto
C9: $ | D9: $ | E9: $ | F9: $ | G9: $ | H9: $ | I9: $ | J9: $ | K9: $
B11: Saldos al inicio del ejercicio | C11: 0 | D11: 0 | E11: =+C11+D11 -> 0 | F11: 0 | G11: 0 | H11: 0 | I11: =-SALDOS!E116 | J11: =+E11+F11+G11+I11 -> 0
C13: =SUM(C11:C11) -> 0 | D13: =SUM(D11:D11) -> 0 | E13: =SUM(E11:E11) -> 0 | F13: =SUM(F11:F11) -> 0 | G13: =SUM(G11:G11) -> 0 | H13: =SUM(H11:H11) -> 0 | I13: =+I12+I11 -> 0 | J13: =+J12+J11 -> 0 | K13: =SUM(K11:K11) -> 0
B15: Reasignación Casa Matriz | I15: 0 | J15: =+E15+F15+G15+I15 -> 0
B16: Ganancia (Pérdida) del ejercicio | I16: =+EERR!C28 -> -346618.12 | J16: =+I16 -> -346618.12
B18: Total al 31/7/26 | C18: =+C13 -> 0 | D18: =+D13 -> 0 | E18: =+E13 -> 0 | F18: =+F13 -> 0 | G18: =+G13 -> 0 | H18: =+H13 -> 0 | I18: =+I13+I16+I14+I15 -> -346618.12 | J18: =+J13+J16+J15 -> -346618.12 | K18: =+K13+K16 -> 0
B19: Total al 31.12.05 | E19: =+C19+D19 -> 0 | G19: 0 | I19: 0 | J19: =+E19 -> 0 | K19: =+G19 -> 0
B21: Las notas y anexos adjuntos forman parte integrante de los estados contables
B22: Informe profesional por separado

Sheet Activo
B1: NOTA 4: | E1: COMPOSICION DE LOS RUBROS
B3: =+EESP!A3 -> 31 de Julio de 2026
F5: =+EESP!F9 -> 46234 | H5: 38717
B6: ACTIVO
B7: Activo Corriente
B8: a. | C8: Caja y bancos
D9: - Caja
D10: - Fondo Fijo SENASA | F10: =+SALDOS!D8+SALDOS!C8 -> 0
D11: - Fondo Fijo | F11: =SALDOS!C7-SALDOS!D7 -> -904.95437
D12: - Banco Francés c/c | F12: =SALDOS!C9-SALDOS!D9 -> -85668.934
D13: - Fondo fijo Adelantos PDT | F13: =+SALDOS!D10+SALDOS!C10 -> 0
D14: - Adelanto casa matriz
D15: - Valores a depositar
F16: =SUM(F9:F15) -> -86573.889
B18: b. | C18: Inversiones temporarias
D19: - Fondo Común de inversión | F19: =-SALDOS!D28+SALDOS!C28 -> -70990.504
D20: - Plazo Fijo
D21: - Plazo Fijo | F21: =-SALDOS!D40 -> 0
D22: - Intereses a dev Plazo Fijo | F22: =+SALDOS!C41 -> 0
F23: =SUM(F19:F22) -> -70990.504
B24: c. | C24: Creditos por Ventas
D25: - Deudores por ventas | F25: =+SALDOS!C14+SALDOS!C16+SALDOS!C17-SALDOS!D11-SALDOS!D14-SALDOS!D16-SALDOS!D15-SALDOS!D17 -> -2171.4588
F26: =SUM(F25:F25) -> -2171.4588
C28: Creditos impositivos
D29: - Retencion de Gcias. | F29: 0
D30: - Retenc. Suss | F30: 0
D31: - Reten. Ingresos Brutos | F31: 0
D32: - Retenciones y Percepciones IVA | F32: 0
D33: - Crédito ley 25413 | F33: 0
F34: =SUM(F29:F33) -> 0
B36: d. | C36: Otros créditos
D37: - Transportes Furlong Uruguay
D38: - Transportes Furlong Cordoba
D39: - Adelanto de gastos
D40: - Adelantos Tomás Furlong
D41: - Adelantos PDT | F41: =+SALDOS!C18-SALDOS!D18 -> 14061.316
D42: - Adelanto honorarios CF
D43: - Anticipo de vacaciones | F43: =+SALDOS!E22 -> 0
D44: - Prestamo Vera | F44: =+SALDOS!C24-SALDOS!D24 -> 0
D45: - Adelanto SAC
D46: - Prestamo Velasco | F46: =+SALDOS!C20 -> 5457.4782
D47: - Prestamo Lorena Alves | F47: =+SALDOS!C21-SALDOS!D21 -> -170.54619
D48: - Seguros a devengar | F48: =-SALDOS!D25-SALDOS!D26-SALDOS!D27+SALDOS!C25+SALDOS!C26 -> -28257.579
D49: - Anticipos de Vacaciones
D50: - Prestamo Cuba | F50: =-SALDOS!D23 -> -682.18478
D51: - Anticipo patentamientos
D52: - Donaciones
D53: - Seguros A Devengar
D54: - Adicional obral social
D55: - Honorarios Directores Tomas
D56: - Honorarios Directores
F57: =SUM(F37:F56) -> -9591.5153
B59: Las notas y anexos adjuntos forman parte integrante de los estados contables
B60: Informe profesional por separado

Sheet Pasivo
E1: =+Activo!F5 -> 46234 | G1: 31.03.04 | K1: 31.03.03 | L1: =+EESP!G9 -> 0
A2: Pasivo
A3: Pasivo Corriente
A4: e. | B4: Deudas comerciales
C5: - Provisión Multas a pagar
C6: - Provisión fletes esporádicos
C7: - Previsiones
C8: - Proveedores | E8: =-SALDOS!E57-SALDOS!E58-SALDOS!E63-SALDOS!E67-SALDOS!E78-SALDOS!E97-SALDOS!E102-SALDOS!E104-SALDOS!E108-0.01 -> -13948.418
C9: - Adelanto casa matriz | E9: =-SALDOS!E12-SALDOS!E90 -> 311549.78
C10: - Adelanto de clientes
C11: - Siniestros a pagar
C12: - Prestamos a pagar
C13: - Prestamo Amx - Claro
C14: - Rodados a patentar
C15: - Cheques emitidos
E16: =SUM(E5:E15) -> 297601.37
A18: f. | B18: Otras Deudas
C19: - Acuerdos CNRT a pagar | E19: =-SALDOS!C91
C20: - Prestamo Carlos Furlong | E20: =-SALDOS!C19 -> 0
C21: - Prestamo Lorena Alves
E22: =+SUM(E19:E21) -> 0
A25: f. | B25: Remuneraciones y cs. Sociales
C26: - SUSS a pagar | E26: =-SALDOS!E83 -> -20201.506
C27: - Sueldos a pagar | E27: =-SALDOS!E82 -> -109231.91
E28: =SUM(E26:E27) -> -129433.41
A31: h. | B31: Cargas Fiscales
C32: - Plan Mis Facilidades | E32: =-SALDOS!E85 -> -286.43025
C33: - Interes a devengar | E33: =-SALDOS!E86 -> 55.880723
C34: - SICORE a pagar | E34: =-SALDOS!E84 -> 876.17906 | G34: 70 | K34: 0
E35: =SUM(E32:E34) -> 645.62953 | G35: =SUM(G34:G34) -> 70 | K35: =SUM(#REF!) -> #REF!

Sheet Anexo I
A1: B I E N E S D E U S O
A2: =+EESP!A3 -> 31 de Julio de 2026
B5: VALOR DE ORIGEN | F5: DEPRECIACIONES
B6: VALORES AL | E6: VALORES AL | F6: ACUMULADAS | H6: DEL EJERCICIO | J6: ACUMULADAS | K6: NETO
A7: CONCEPTO | B7: COMIENZO DEL | C7: AUMENTOS | D7: DISMINUCIONES | E7: CIERRE DEL | F7: AL INICIO DEL | G7: BAJAS | H7: ALICUOTA | I7: MONTO | J7: AL CIERRE DEL | K7: RESULTANTE
B8: EJERCICIO | E8: EJERCICIO | F8: EJERCICIO | J8: EJERCICIO | K8: =+EESP!F9 -> 46234
B9: $ | C9: $ | D9: $ | E9: $ | F9: $ | G9: $ | I9: $ | J9: $ | K9: $
A11: Software | B11: 0 | C11: 0 | E11: 0 | F11: 0 | H11: 0.2 | I11: 0 | J11: =+I11 -> 0 | K11: =+E11-J11 -> 0
A12: Hardware | B12: 0 | C12: 0 | E12: 0 | F12: 0 | H12: 0.2 | I12: 0 | J12: =+I12 -> 0 | K12: =+E12-J12 -> 0
A13: Computadoras | B13: 0 | C13: 0 | E13: 0 | F13: 0 | H13: 0.2 | I13: =-SALDOS!E47 -> 293.35549 | J13: =+I13 -> 293.35549 | K13: =+E13-J13 -> -293.35549
A14: Equipos | B14: 0 | C14: 0 | D14: 0 | E14: 0 | F14: 0 | H14: 0.2 | I14: 0 | J14: =+I14 -> 0 | K14: =+E14-J14 -> 0
A15: Muebles y Utiles | B15: 0 | C15: 0 | E15: 0 | F15: 0 | H15: 0.1 | I15: =-SALDOS!E42 -> 12.632834 | J15: =+I15 -> 12.632834 | K15: =+E15-J15 -> -12.632834
A16: Instalaciones | B16: 0 | C16: 0 | E16: 0 | F16: 0 | H16: 0.1 | I16: 0 | J16: =+I16 -> 0 | K16: =+E16-J16 -> 0
A17: Rodados | B17: 0 | C17: 0 | D17: =+#REF! -> #REF! | E17: 0 | F17: 0 | G17: 0 | H17: 0.2 | I17: =-SALDOS!E48 -> 8171.1751 | J17: =+I17 -> 8171.1751 | K17: =+E17-J17 -> -8171.1751
A18: =+EEPN!B18 -> Total al 31/7/26 | B18: =SUM(B11:B17) -> 0 | C18: =SUM(C11:C17) -> 0 | D18: =SUM(D11:D17) -> #REF! | E18: =SUM(E11:E17) -> 0 | F18: =SUM(F11:F17) -> 0 | G18: =SUM(G17) -> 0 | I18: =SUM(I11:I17) -> 8477.1634 | J18: =SUM(J11:J17) -> 8477.1634 | K18: =SUM(K11:K17) -> -8477.1634
A21: Las notas y anexos adjuntos forman parte integrante de los estados contables
A22: Informe profesional por separado

Sheet Anexo II
G1: ANEXO II
A3: Información Requerida por el Art. 64 Inc. b) de la Ley 19.550 | F3: Anexo II
A4: =+Activo!B3 -> 31 de Julio de 2026
C6: TOTALES | D6: GASTOS | E6: GASTOS | F6: GASTOS | G6: TOTALES
B7: CONCEPTOS | C7: AL | D7: DE | E7: DE | G7: AL | J7: GASTOS ADM CTRAL | K7: GASTOS PACHECO | L7: GASTOS CORDOBA | M7: COSTOS TRANSPORTES | N7: TOTAL | O7: PAGOS ANTIC | P7: TRANF CASA MATRIZ | Q7: TOTAL EGRESO
C8: =+EESP!F9 -> 46234 | D8: ADMINISTRACION | E8: COMERCIALIZACION | F8: FINANCIEROS | G8: 31.03.02
B9: Acuerdo SECLO | C9: =SUM(D9:F9) -> 0 | D9: 0 | E9: =+SALDOS!C151 | F9: 0
B10: Adelanto Viaje | C10: =SUM(D10:F10) -> 0 | D10: 0 | E10: =+SALDOS!C204 | F10: 0
B11: Alquiler de autos | C11: =SUM(D11:F11) -> 0 | D11: 0 | E11: =+SALDOS!C187 | F11: 0
B12: Alquiler cochera | C12: =SUM(D12:F12) -> 0 | D12: 0 | E12: =+SALDOS!C194 | F12: 0
B13: Alquiler dpto. | C13: =SUM(D13:F13) -> 0 | D13: 0 | E13: =+SALDOS!C192 | F13: 0
B14: Alquiler fotocopiadora | C14: =SUM(D14:F14) -> 1633.99 | D14: =+SALDOS!C150 -> 1633.99 | E14: 0 | F14: 0
B15: Alquiler Oficina Móvil | C15: =SUM(D15:F15) -> 0 | D15: =+SALDOS!C153 | E15: 0 | F15: 0
B16: Amortizaciones | C16: =SUM(D16:F16) -> 8674.63 | D16: =+SALDOS!C148 -> 8674.63 | E16: 0 | F16: 0
B17: Publicidad | C17: =SUM(D17:F17) -> 0 | D17: 0 | E17: =+SALDOS!C200 | F17: 0
B18: Almuerzos | C18: =SUM(D18:F18) -> 0 | D18: 0 | E18: 0 | F18: 0
B19: Autónomos Directores | C19: =SUM(D19:F19) -> 251.68 | D19: =+SALDOS!C180 -> 251.68 | E19: 0 | F19: 0
B20: Agua | C20: =SUM(D20:F20) -> 0 | D20: =+SALDOS!C149 | E20: 0 | F20: 0
B21: Ajuste saldo proveedores | C21: =SUM(D21:F21) -> 0 | D21: 0 | E21: =+SALDOS!C219 | F21: 0
B22: Bs Personales Acc. Y Participacion | C22: =SUM(D22:F22) -> 0 | D22: =++SALDOS!C186 | E22: 0 | F22: 0
B23: Sueldos | C23: =SUM(D23:F23) -> 0 | D23: 0 | E23: 0 | F23: 0
B24: Comisiones | C24: =SUM(D24:F24) -> 0 | D24: 0 | E24: =+SALDOS!C193 | F24: 0
B25: Gastos varios clientes | C25: =SUM(D25:F25) -> 0 | D25: 0 | E25: 0 | F25: 0
B26: Verificación Técnica Vehicular | C26: =SUM(D26:F26) -> 275.24 | D26: 0 | E26: =+SALDOS!C203+SALDOS!C176 -> 275.24 | F26: 0
B27: Amortizaciones | C27: =SUM(D27:F27) -> 0 | D27: 0 | E27: 0 | F27: 0
B28: Accidentes | C28: =SUM(D28:F28) -> 0 | D28: 0 | E28: =+SALDOS!C188 | F28: 0 | I28: OBRA SOCIAL | J28: 3400.5126 | K28: 5282.0813 | L28: 3714.6061 | P28: 4372 | R28: ACA ES LA FACTURA QUE SE VA A PAGAR EL MES PRÓXIMO SE INCLUYE EN CARGAS SOCIALES (EN EL BALANCE)
B29: Cargas Sociales | C29: =SUM(D29:F29) -> 30470.95 | D29: 0 | E29: =+SALDOS!C132 -> 30470.95 | F29: 0 | I29: C SOCIALES | J29: 7385.6622 | K29: 30178.815 | L29: 9981.5423 | R29: CORRESPONDE AL MES DE MAYO / SE PAGA EN JUNIO
B30: Telefonos | C30: =SUM(D30:F30) -> 0 | D30: 0 | E30: 0 | F30: 0
B31: Librería | C31: =SUM(D31:F31) -> 0 | D31: 0 | E31: 0 | F31: 0
B32: Leasing | C32: =SUM(D32:F32) -> 0 | D32: 0 | E32: =+SALDOS!C213 | F32: 0 | I32: ALQUILER | L32: =+E32 -> 0
B33: Viaticos | C33: =SUM(D33:F33) -> 0 | D33: 0 | E33: 0 | F33: 0
B34: Repuestos y reparaciones | C34: =SUM(D34:F34) -> 0 | D34: =+SALDOS!C181 | E34: 0 | F34: 0
B35: Catering | C35: =SUM(D35:F35) -> 0 | D35: 0 | E35: 0 | F35: 0 | I35: COMIDA | J35: 474 | K35: 528
B36: CNRT | C36: =SUM(D36:F36) -> 0 | D36: 0 | E36: 0 | F36: 0 | I36: MULTAS | P36: =+C36 -> 0
B37: Gastos bancarios | C37: =SUM(D37:F37) -> 0 | D37: 0 | E37: 0 | F37: 0
B38: Intereses | C38: =SUM(D38:F38) -> 0 | D38: 0 | E38: 0 | F38: 0 | I38: F. FIJOS FORD/VW/PTO 14 | K38: =4800+5000+3000+5000 -> 17800 | L38: 7200 | R38: SON FACTURAS DE COMBUSTIBLE / POR ESO SE SUMA EN COMBUSTIBLES
B39: Combustible | C39: =SUM(D39:F39) -> 1760.8 | D39: 0 | E39: =+SALDOS!C171+SALDOS!C217 -> 1760.8 | F39: 0 | I39: COMBUSTIBLE | J39: 281.16 | K39: =3211.01+4543.6 -> 7754.61 | L39: 1075.53
B40: Comunicaciones | C40: =SUM(D40:F40) -> 1732.02 | D40: 0 | E40: =+SALDOS!C166+SALDOS!D166 -> 1732.02 | F40: 0 | I40: TELEFONOS | J40: =2248.27+2043.98+1241.35 -> 5533.6 | K40: =2543.13+2338.55+2410.41 -> 7292.09 | L40: =1803.75+2112.36+2202.79 -> 6118.9 | M40: 1098.32 | R40: HAY CARGADAS 2 FACTURAS VIEJAS DE NEXTEL QUE NO ESTABAN
B41: Correo | C41: =SUM(D41:F41) -> 0 | D41: 0 | E41: 0 | F41: 0
B42: Custodia | C42: =SUM(D42:F42) -> 0 | D42: =SALDOS!C168 | E42: 0 | F42: 0
B43: Despachantes | C43: =SUM(D43:F43) -> 178280.72 | D43: 0 | E43: =+SALDOS!C169 -> 178280.72 | F43: 0 | I43: DESPACHANTES | K43: =3200+3115 -> 6315 | L43: =4800+1400+3115 -> 9315 | M43: =29395.55+31000.65 -> 60396.2 | O43: 3180
B44: Donaciones | C44: =SUM(D44:F44) -> 2084.42 | D44: 0 | E44: =+SALDOS!C190 -> 2084.42 | F44: 0
B45: Estadía | C45: =SUM(D45:F45) -> 0 | D45: 0 | E45: =+SALDOS!C182 | F45: 0
B46: Estacionamiento | C46: =SUM(D46:F46) -> 0 | D46: 0 | E46: =+SALDOS!C175 | F46: 0
B47: Estibajes | C47: =SUM(D47:F47) -> 0 | D47: 0 | E47: =+SALDOS!C191 | F47: 0 | I47: ESTIBAJES | M47: =+C47 -> 0
B48: Embargo Rdicación Vehicular | C48: =SUM(D48:F48) -> 0 | D48: 0 | E48: =+SALDOS!C216 | F48: 0
B49: Fletes | C49: =SUM(D49:F49) -> -17162.57 | D49: =+SALDOS!C157-SALDOS!D157 -> -17162.57 | E49: 0 | F49: 0 | I49: TRANSPORTES | M49: =+C49 -> -17162.57 | R49: ACA QUEDA LA DIFERENCIA DE PROVISION
B50: Gastos Capacitación | C50: =SUM(D50:F50) -> 0 | D50: =+SALDOS!C142 | E50: 0 | F50: 0
B51: Gastos Medicos | C51: =SUM(D51:F51) -> 18657.1 | D51: =+SALDOS!C155 -> 18657.1 | E51: 0 | F51: 0
B52: Gastos de Representación | C52: =SUM(D52:F52) -> 0 | D52: 0 | E52: =+SALDOS!C184-SALDOS!D184 | F52: 0 | I52: TOMAS (FF Y VISA) | J52: 1949.3367 | K52: 1949.3367 | L52: 1949.3367
B53: Gastos Generales | C53: =SUM(D53:F53) -> 0 | D53: 0 | E53: =+SALDOS!C127-SALDOS!D127 | F53: 0
B54: Gastos de instalación | C54: =SUM(D54:F54) -> 0 | D54: 0 | E54: 0 | F54: 0
B55: Gs Ropa de Trabajo | C55: =SUM(D55:F55) -> 0 | D55: 0 | E55: =+SALDOS!C208 | F55: 0
B56: Gastos trámites | C56: =SUM(D56:F56) -> 0 | D56: =+SALDOS!C139 | E56: 0 | F56: 0 | H56: EN VARIOS
B57: Gastos PC | C57: =SUM(D57:F57) -> 0 | D57: =+SALDOS!C135 | E57: 0 | F57: 0 | H57: EN MANTEN
B58: Gastos varios | C58: =SUM(D58:F58) -> 1030.3 | D58: =+SALDOS!C177 -> 1030.3 | E58: 0 | F58: 0 | I58: VARIOS | J58: =+C56 -> 0 | K58: =+C58 -> 1030.3 | P58: =+C44 -> 2084.42
B59: Gastos varios personal | C59: =SUM(D59:F59) -> 0 | D59: 0 | E59: =+SALDOS!C147-SALDOS!D147 | F59: 0
B60: Gastos varios clientes | C60: =SUM(D60:F60) -> 0 | D60: 0 | E60: =+SALDOS!C207 | F60: 0
B61: Gastos y comisiones bancarias | C61: =SUM(D61:F61) -> 5860.59 | D61: 0 | E61: 0 | F61: =-SALDOS!D209+SALDOS!C209+SALDOS!C220 -> 5860.59 | I61: GASTOS BANCARIOS | J61: =+C61 -> 5860.59
B62: Gastos Obra Social | C62: =SUM(D62:F62) -> 0 | D62: =+SALDOS!C138-SALDOS!D138 | E62: 0 | F62: 0
B63: Gastos Hotelería | C63: =SUM(D63:F63) -> 0 | D63: =+SALDOS!C159-SALDOS!D159 | E63: 0 | F63: 0
B64: Gastos Gestoria | C64: =SUM(D64:F64) -> 0 | D64: =+SALDOS!C160 | E64: 0 | F64: 0
B65: Habilitaciones | C65: =SUM(D65:F65) -> 0 | D65: =+SALDOS!C161 | E65: 0 | F65: 0
B66: Honorarios director | C66: =SUM(D66:F66) -> 0 | D66: 0 | E66: =+SALDOS!C140 | F66: 0
B67: Honorarios profesionales | C67: =SUM(D67:F67) -> 15732.21 | D67: =+SALDOS!C156+SALDOS!C130 -> 15732.21 | E67: 0 | F67: 0 | I67: HONORARIOS | J67: =9400+850+550 -> 10800 | K67: =850+700 -> 1550
B68: Honorarios Legales | C68: =SUM(D68:F68) -> 0 | D68: 0 | E68: =-SALDOS!D156 | F68: 0
B69: Imp. A los créditos | C69: =SUM(D69:F69) -> 0 | D69: 0 | E69: 0 | F69: 0
B70: Imp. A los débitos | C70: =SUM(D70:F70) -> 0 | D70: 0 | E70: 0 | F70: =+SALDOS!C210
B71: Imp. Bienes Sociedades | C71: =SUM(D71:F71) -> 0 | D71: 0 | E71: 0 | F71: 0 | I71: IMPUESTOS | J71: =+$C$19/3+C71 -> 83.893333 | K71: =+$C$19/3 -> 83.893333 | L71: =+$C$19/3 -> 83.893333
B72: Intereses resarcitorios | C72: =SUM(D72:F72) -> 61.24 | D72: =-SALDOS!D212 | E72: 0 | F72: =+SALDOS!C221 -> 61.24
B73: Impuestos varios | C73: =SUM(D73:F73) -> 0 | D73: 0 | E73: 0 | F73: =+SALDOS!C214
B74: Impuestos al Cheuque | C74: =SUM(D74:F74) -> 0 | D74: 0 | E74: 0 | F74: =+SALDOS!C215
B75: Juicios | C75: =SUM(D75:F75) -> 0 | D75: =+SALDOS!C201 | E75: 0 | F75: 0
B76: Librería | C76: =SUM(D76:F76) -> 0 | D76: =+SALDOS!C131 | E76: 0 | F76: 0 | I76: LIBRERÍA | J76: =213.333333333333+500 -> 713.33333 | K76: =213.333333333333+500 -> 713.33333 | L76: =213.333333333333+17.55 -> 230.88333 | R76: SE REGISTRAN LAS FC X FECHA DE EMISION
B77: Legalizaciones | C77: =SUM(D77:F77) -> 0 | D77: =+SALDOS!C146 | E77: 0 | F77: 0 | I77: LEGALIZACIONES | J77: 270
B78: Locomoción | C78: =SUM(D78:F78) -> 0 | D78: 0 | E78: =+SALDOS!C167-SALDOS!D167 | F78: 0
B79: Logística | C79: =SUM(D79:F79) -> 0 | D79: 0 | E79: =+SALDOS!C196 | F79: 0
B80: Mantenimiento | C80: =SUM(D80:F80) -> 1776.98 | D80: 0 | E80: =+SALDOS!C145 -> 1776.98 | F80: 0 | I80: MANTENIMIENTO | J80: =+C57 -> 0 | K80: 250 | L80: =595-250 -> 345
B81: Mantenimiento de flota | C81: =SUM(D81:F81) -> 0 | D81: 0 | E81: =+SALDOS!C170 | F81: 0
B82: Mantenimiento de maquinas | C82: =SUM(D82:F82) -> 0 | D82: 0 | E82: 0 | F82: 0
B83: Mensajería | C83: =SUM(D83:F83) -> 0 | D83: =+SALDOS!C173 | E83: 0 | F83: 0 | I83: MENSAJERIA | J83: 3500 | K83: 3500
B84: Medicina Laboral | C84: =SUM(D84:F84) -> 0 | D84: 0 | E84: 0 | F84: 0
B85: Molilidad y viáticos | C85: =SUM(D85:F85) -> 0 | D85: =+SALDOS!C128-SALDOS!D128 | E85: 0 | F85: 0
B86: Multas | C86: =SUM(D86:F86) -> 3033.18 | D86: 0 | E86: =+SALDOS!C183-SALDOS!D183 -> 3033.18 | F86: 0
B87: Gastos PC | C87: =SUM(D87:F87) -> 0 | D87: =-SALDOS!D135 | E87: 0 | F87: 0
B88: Gastos de logistica | C88: =SUM(D88:F88) -> -5088.91 | D88: 0 | E88: =+SALDOS!C185-SALDOS!D185 -> -5088.91 | F88: 0
B89: Patentes | C89: =SUM(D89:F89) -> 0 | D89: 0 | E89: =+SALDOS!C198 | F89: 0 | I89: PATENTES | J89: 546.19 | K89: =723.69-546.19 -> 177.5 | R89: SE PAGARAN EL MES PROXIMO
B90: Peajes | C90: =SUM(D90:F90) -> -89628.1 | D90: 0 | E90: =+SALDOS!C174-SALDOS!D174 -> -89628.1 | F90: 0
B91: Reparaciones | C91: =SUM(D91:F91) -> 27617.54 | D91: 0 | E91: =+SALDOS!C143-SALDOS!D143 -> 27617.54 | F91: 0
B92: Refrigerios | C92: =SUM(D92:F92) -> 0 | D92: =+SALDOS!C179 | E92: 0 | F92: 0 | I92: FONDOS FIJOS | K92: =37+14+36.5+E81+88 -> 175.5 | L92: =302.7-37+63 -> 328.7
B93: Ropa de trabajo | C93: =SUM(D93:F93) -> 0 | D93: 0 | E93: =+SALDOS!C195 | F93: 0
B94: Seguros | C94: =SUM(D94:F94) -> 37882.9 | D94: 0 | E94: =+SALDOS!C165-SALDOS!D165 -> 37882.9 | F94: 0 | I94: SEGUROS | K94: =528.01-1.9 -> 526.11 | L94: 426.07 | M94: 59330.35
B95: Seguridad | C95: =SUM(D95:F95) -> 0 | D95: 0 | E95: =+SALDOS!C178 | F95: 0 | I95: ANTICIPOS | M95: =+E88 -> -5088.91 | O95: =+C95 -> 0
B96: Servicio de limpieza | C96: =SUM(D96:F96) -> 0 | D96: =+SALDOS!C141 | E96: 0 | F96: 0 | I96: FUMIGACION | J96: 240 | K96: 240
B97: Deudores Incobrables | C97: =SUM(D97:F97) -> 0 | D97: 0 | E97: =+SALDOS!C205 | F97: 0
B98: Sellados | C98: =SUM(D98:F98) -> 0 | D98: =+SALDOS!C162-SALDOS!D162 | E98: 0 | F98: 0
B99: Siniestros | C99: =SUM(D99:F99) -> 0 | D99: 0 | E99: =+SALDOS!C189 | F99: 0
B100: Sueldos | C100: =SUM(D100:F100) -> 93970.96 | D100: 0 | E100: =+SALDOS!C129 -> 93970.96 | F100: 0 | I100: SALARIOS | J100: =+E100*27% -> 25372.159 | K100: =+E100*39% -> 36648.674 | L100: =+E100*34% -> 31950.126 | R100: ACA VA EL TOTAL DE LOS SUELDOS BRUTOS (EN PAGOS EL NETO)
B101: Salario Complementario del Decreto 332/20 | C101: =SUM(D101:F101) -> 0 | D101: 0 | E101: =-SALDOS!D152 | F101: 0
B102: Verificación Policial | C102: =SUM(D102:F102) -> 0 | D102: 0 | E102: =+SALDOS!C206 | F102: 0
...
