Workbook

Sheet SALDOS
A1: TRANSPORTES FURLONG S.A.
A2: del 01/7/2026 al 31/7/2026
B3: Deudor | C3: Acreedor
A5: Activo
A7: 1110100330 FONDO FIJO BS. AS. | B7: =IF(D7>0,D7,0) -> 0 | C7: =IF(D7<0,-D7,0) -> 265310.63 | D7: =IFERROR(VLOOKUP(A7,$A$242:$B$359,2,FALSE),0) -> -265310.63
A8: 1110100340 FONDO FIJO SENASA | B8: =IF(D8>0,D8,0) -> 0 | C8: =IF(D8<0,-D8,0) -> 0 | D8: =IFERROR(VLOOKUP(A8,$A$242:$B$359,2,FALSE),0)
A9: 1110100420 BANCO FRANCES C/C | B9: =IF(D9>0,D9,0) -> 0 | C9: =IF(D9<0,-D9,0) -> 25116050 | D9: =IFERROR(VLOOKUP(A9,$A$242:$B$359,2,FALSE),0) -> -25116050
A10: 1110101050 FONDO FIJO ADELANTOS PDT | B10: =IF(D10>0,D10,0) -> 0 | C10: =IF(D10<0,-D10,0) -> 0 | D10: =IFERROR(VLOOKUP(A10,$A$242:$B$359,2,FALSE),0)
A11: 1120100100 FORD | B11: =IF(D11>0,D11,0) -> 0 | C11: =IF(D11<0,-D11,0) -> 640196.69 | D11: =IFERROR(VLOOKUP(A11,$A$242:$B$359,2,FALSE),0) -> -640196.69
A12: 1120100400 TRANSPORTES FURLONG S.A. AR | B12: =IF(D12>0,D12,0) -> 0 | C12: =IF(D12<0,-D12,0) -> 99288526 | D12: =IFERROR(VLOOKUP(A12,$A$242:$B$359,2,FALSE),0) -> -99288526
A13: 1120100700 RENAULT ARG. S.A. | B13: =IF(D13>0,D13,0) -> 0 | C13: =IF(D13<0,-D13,0) -> 0 | D13: =IFERROR(VLOOKUP(A13,$A$242:$B$359,2,FALSE),0)
A14: 1120101300 VOLKSWAGEN ARGENTINA S.A. | B14: =IF(D14>0,D14,0) -> 304705.08 | C14: =IF(D14<0,-D14,0) -> 0 | D14: =IFERROR(VLOOKUP(A14,$A$242:$B$359,2,FALSE),0) -> 304705.08
A15: 1120101600 FCA AUTOMOBILES ARGENTINA S.A. | B15: =IF(D15>0,D15,0) -> 0 | C15: =IF(D15<0,-D15,0) -> 0 | D15: =IFERROR(VLOOKUP(A15,$A$242:$B$359,2,FALSE),0)
A16: 1120131000 CNH ARGENTINA S.A. | B16: =IF(D16>0,D16,0) -> 0 | C16: =IF(D16<0,-D16,0) -> 108886.7 | D16: =IFERROR(VLOOKUP(A16,$A$242:$B$359,2,FALSE),0) -> -108886.7
A17: 1120138000 STELLANTIS AUTOMOVILES DE ARGENTINA S. A | B17: =IF(D17>0,D17,0) -> 0 | C17: =IF(D17<0,-D17,0) -> 192240.64 | D17: =IFERROR(VLOOKUP(A17,$A$242:$B$359,2,FALSE),0) -> -192240.64
A18: 1140300100 ANTICIPO A PDT | B18: =IF(D18>0,D18,0) -> 4122436.3 | C18: =IF(D18<0,-D18,0) -> 0 | D18: =IFERROR(VLOOKUP(A18,$A$242:$B$359,2,FALSE),0) -> 4122436.3
... A46: 1220500000 AMORT. ACUM. HARDWARE | B46: =IF(D46>0,D46,0) -> 0 | C46: =IF(D46<0,-D46,0) -> 0 | D46: =IFERROR(VLOOKUP(A46,$A$242:$B$359,2,FALSE),0)
A47: 1220700000 AMORT. ACUM. RODADOS | B47: =IF(D47>0,D47,0) -> 0 | C47: =IF(D47<0,-D47,0) -> 2395590 | D47: =IFERROR(VLOOKUP(A47,$A$242:$B$359,2,FALSE),0) -> -2395590 | E47: =SUM(D32:D47) -> -2485298.3
A48: 2.1.1.01.01.0.0 BOSTON CIA ARG DE SEGUROS | B48: =IF(D48>0,D48,0) -> 0 | C48: =IF(D48<0,-D48,0) -> 0 | D48: =IFERROR(VLOOKUP(A48,$A$242:$B$359,2,FALSE),0)
A49: 2.1.1.01.02.0.0 EL COMERCIO CIA DE SEGUROS | B49: =IF(D49>0,D49,0) -> 0 | C49: =IF(D49<0,-D49,0) -> 0 | D49: =IFERROR(VLOOKUP(A49,$A$242:$B$359,2,FALSE),0)
D50: =SUM(D7:D49) -> -1.5141649e+08 | E50: =SUM(B7:B49) -> 6027141.4 | F50: =SUM(C7:C49) -> 1.5744363e+08 | G50: =+E50-F50-D50 -> 0
A51: Pasivo
A53: 2110100300 COTELCAM | B53: =IF(D53>0,D53,0) -> 0 | C53: =IF(D53<0,-D53,0) -> 0 | D53: =IFERROR(VLOOKUP(A53,$A$242:$B$359,2,FALSE),0)
A54: 2110100900 ESTUDIO CORTES | B54: =IF(D54>0,D54,0) -> 0 | C54: =IF(D54<0,-D54,0) -> 0 | D54: =IFERROR(VLOOKUP(A54,$A$242:$B$359,2,FALSE),0)
A55: 2110101500 VENEZIA AUTOS SA | B55: =IF(D55>0,D55,0) -> 0 | C55: =IF(D55<0,-D55,0) -> 0 | D55: =IFERROR(VLOOKUP(A55,$A$242:$B$359,2,FALSE),0)
A56: 2110101800 TRANSPORTES FURLONG ARG. S.A | B56: =IF(D56>0,D56,0) -> 0 | C56: =IF(D56<0,-D56,0) -> 0 | D56: =IFERROR(VLOOKUP(A56,$A$242:$B$359,2,FALSE),0)
A57: 2110102400 OSDE | B57: =IF(D57>0,D57,0) -> 0 | C57: =IF(D57<0,-D57,0) -> 0 | D57: =IFERROR(VLOOKUP(A57,$A$242:$B$359,2,FALSE),0)
A58: 2110105400 MERCOVIA S.A. | B58: =IF(D58>0,D58,0) -> 59338.84 | C58: =IF(D58<0,-D58,0) -> 0 | D58: =IFERROR(VLOOKUP(A58,$A$242:$B$359,2,FALSE),0) -> 59338.84
A59: 2110106800 OKINET SRL | B59: =IF(D59>0,D59,0) -> 162531 | C59: =IF(D59<0,-D59,0) -> 0 | D59: =IFERROR(VLOOKUP(A59,$A$242:$B$359,2,FALSE),0) -> 162531
A60: 2110108900 LA MERIDIONAL S.A. | B60: =IF(D60>0,D60,0) -> 0 | C60: =IF(D60<0,-D60,0) -> 0 | D60: =IFERROR(VLOOKUP(A60,$A$242:$B$359,2,FALSE),0)
A61: 2110115100 GIULI SERGIO ALBERTO | B61: =IF(D61>0,D61,0) -> 0 | C61: =IF(D61<0,-D61,0) -> 0 | D61: =IFERROR(VLOOKUP(A61,$A$242:$B$359,2,FALSE),0)
A62: 2110116700 CARLOS ALEJANDRO DUMA | B62: =IF(D62>0,D62,0) -> 0 | C62: =IF(D62<0,-D62,0) -> 0 | D62: =IFERROR(VLOOKUP(A62,$A$242:$B$359,2,FALSE),0)
A63: 2110118000 MANGGINI PABLO Y ULISES S.H | B63: =IF(D63>0,D63,0) -> 0 | C63: =IF(D63<0,-D63,0) -> 0 | D63: =IFERROR(VLOOKUP(A63,$A$242:$B$359,2,FALSE),0)
A64: 2110120600 QBE SEGUROS LA BUENOS AIRES S.A. | B64: =IF(D64>0,D64,0) -> 22567153 | C64: =IF(D64<0,-D64,0) -> 0 | D64: =IFERROR(VLOOKUP(A64,$A$242:$B$359,2,FALSE),0) -> 22567153
... A109: 2113200000 SERGIO MARCELO MARTIN | B109: =IF(D109>0,D109,0) -> 0 | C109: =IF(D109<0,-D109,0) -> 0 | D109: =IFERROR(VLOOKUP(A109,$A$242:$B$359,2,FALSE),0)
B110: =IF(D110>0,D110,0) -> 0 | C110: =IF(D110<0,-D110,0) -> 0 | D110: =IFERROR(VLOOKUP(A110,$A$242:$B$359,2,FALSE),0)
B111: =IF(D111>0,D111,0) -> 0 | C111: =IF(D111<0,-D111,0) -> 0 | D111: =IFERROR(VLOOKUP(A111,$A$242:$B$359,2,FALSE),0)
A112: 2110805400 HOTEL RENTAL SUITES CAMPANA | B112: =IF(D112>0,D112,0) -> 0 | C112: =IF(D112<0,-D112,0) -> 0 | D112: =IFERROR(VLOOKUP(A112,$A$242:$B$359,2,FALSE),0)
A113: 2116400000 AUTOVIA DEL MERCOSUR | B113: =IF(D113>0,D113,0) -> 0 | C113: =IF(D113<0,-D113,0) -> 0 | D113: =IFERROR(VLOOKUP(A113,$A$242:$B$359,2,FALSE),0)
A114: 2116300000 Sistemas Bejerman | B114: =IF(D114>0,D114,0) -> 48674.67 | C114: =IF(D114<0,-D114,0) -> 0 | D114: =IFERROR(VLOOKUP(A114,$A$242:$B$359,2,FALSE),0) -> 48674.67
A115: 2113400000 FRONTAR LIBRE | B115: =IF(D115>0,D115,0) -> 0 | C115: =IF(D115<0,-D115,0) -> 151501.92 | D115: =IFERROR(VLOOKUP(A115,$A$242:$B$359,2,FALSE),0) -> -151501.92
A116: 2113700000 POLIPREN ARGENTINA SRL | B116: =IF(D116>0,D116,0) -> 0 | C116: =IF(D116<0,-D116,0) -> 0 | D116: =IFERROR(VLOOKUP(A116,$A$242:$B$359,2,FALSE),0)
D117: =SUM(D53:D116) -> 49796483 | E117: =SUM(B53:B116) -> 69009863 | F117: =SUM(C53:C116) -> 19213380 | G117: =+E117-F117-D117 -> 0
A118: 212010000 PREV.DIF.DE CAMBIO FIAT
A119: 212020000 PREV. PARA DESPIDOS
A120: 2110700250 PROVISIÓN SINIESTRO FORD
A121: Patrimonio neto
A123: 331000000 RNA EJERCICIO ANTERIOR | B123: =IF(D123>0,D123,0) -> 0 | C123: =IF(D123<0,-D123,0) -> 0 | D123: =IFERROR(VLOOKUP(A123,$A$242:$B$359,2,FALSE),0)
A124: 332000000 RESULTADO DEL EJERCICIO | B124: =IF(D124>0,D124,0) -> 0 | C124: =IF(D124<0,-D124,0) -> 0 | D124: =IFERROR(VLOOKUP(A124,$A$242:$B$359,2,FALSE),0)
A125: 333000000 A.R.E.A | B125: =IF(D125>0,D125,0) -> 0 | C125: =IF(D125<0,-D125,0) -> 0 | D125: 0
D126: =SUM(D123:D125) -> 0
A127: Resultados
A129: 4110100000 SERVICIOS PRESTADOS | B129: =IF(D129>0,D129,0) -> 0 | C129: =IF(D129<0,-D129,0) -> 0 | D129: =IFERROR(VLOOKUP(A129,$A$242:$B$359,2,FALSE),0)
A130: 4120200000 DIFERENCIA DE COTIZACIÓN | B130: =IF(D130>0,D130,0) -> 0 | C130: =IF(D130<0,-D130,0) -> 0 | D130: =IFERROR(VLOOKUP(A130,$A$242:$B$359,2,FALSE),0)
A131: 4231100000 RESULTADO POR TENENCIA FCI | B131: =IF(D131>0,D131,0) -> 0 | C131: =IF(D131<0,-D131,0) -> 677309.44 | D131: =IFERROR(VLOOKUP(A131,$A$242:$B$359,2,FALSE),0) -> -677309.44
A132: RECUPERO DE GASTOS | B132: =IF(D132>0,D132,0) -> 0 | C132: =IF(D132<0,-D132,0) -> 0 | D132: =IFERROR(VLOOKUP(A132,$A$242:$B$359,2,FALSE),0)
A133: 412020000 DIFERENCIA DE COTIZACION | B133: =IF(D133>0,D133,0) -> 0 | C133: =IF(D133<0,-D133,0) -> 0 | D133: =IFERROR(VLOOKUP(A133,$A$242:$B$359,2,FALSE),0)
A134: 4120400000 RECUPERO DE SINIESTRO | B134: =IF(D134>0,D134,0) -> 0 | C134: =IF(D134<0,-D134,0) -> 0 | D134: =IFERROR(VLOOKUP(A134,$A$242:$B$359,2,FALSE),0)
A135: 4120300000 VENTA RODADO | B135: =IF(D135>0,D135,0) -> 0 | C135: =IF(D135<0,-D135,0) -> 0 | D135: =IFERROR(VLOOKUP(A135,$A$242:$B$359,2,FALSE),0)
A136: 4120500000 INTERESES GANADOS | B136: =IF(D136>0,D136,0) -> 0 | C136: =IF(D136<0,-D136,0) -> 0 | D136: =IFERROR(VLOOKUP(A136,$A$242:$B$359,2,FALSE),0)
A137: 421010000 GASTOS GENERALES | B137: =IF(D137>0,D137,0) -> 0 | C137: =IF(D137<0,-D137,0) -> 0 | D137: =IFERROR(VLOOKUP(A137,$A$242:$B$359,2,FALSE),0)
A138: 4210200000 MOVILIDAD Y VIÁTICOS | B138: =IF(D138>0,D138,0) -> 0 | C138: =IF(D138<0,-D138,0) -> 0 | D138: =IFERROR(VLOOKUP(A138,$A$242:$B$359,2,FALSE),0)
A139: 4210300000 SUELDOS | B139: =IF(D139>0,D139,0) -> 27550004 | C139: =IF(D139<0,-D139,0) -> 0 | D139: =IFERROR(VLOOKUP(A139,$A$242:$B$359,2,FALSE),0) -> 27550004
A140: 4210400000 HONORARIOS PROFESIONALES | B140: =IF(D140>0,D140,0) -> 4577701.1 | C140: =IF(D140<0,-D140,0) -> 0 | D140: =IFERROR(VLOOKUP(A140,$A$242:$B$359,2,FALSE),0) -> 4577701.1
... A234: 4231000000 RECPAM | B234: =IF(D234>0,D234,0) | C234: =IF(D234<0,-D234,0) | D234: =IFERROR(VLOOKUP(A234,$A$242:$B$359,2,FALSE),0)
B235: =SUM(B7:B234) -> 2.1044476e+08 | C235: =SUM(C7:C234) -> 2.1044476e+08 | D235: =SUM(D129:D234) -> 1.0162001e+08 | E235: =+D235+D126+D117+D50 | F235: =+E235+D117+D50 -> -1.0162001e+08
B236: =+B235-C235
D237: =+D235+EERR!C28
B240: =SUM(B241:B359) -> 8.137431e-08
A242: 1110100330 FONDO FIJO BS. AS. | B242: -265310.63 | D242: -265310.63
A243: 1110100420 BANCO FRANCES C/C | B243: -25116050 | D243: -25116050
A244: 1120100100 FORD | B244: -640196.69 | D244: -640196.69
A245: 1120100400 TRANSPORTES FURLONG S.A. AR | B245: -99288526 | D245: -99288526
A246: 1120101300 VOLKSWAGEN ARGENTINA S.A. | B246: 304705.08 | D246: 304705.08
A247: 1120131000 CNH ARGENTINA S.A. | B247: -108886.7 | D247: -108886.7
A248: 1120138000 STELLANTIS AUTOMOVILES DE ARGENTINA S. A | B248: -192240.64 | D248: -192240.64
A249: 1140300100 ANTICIPO A PDT | B249: 4122436.3 | D249: 4122436.3
A250: 1140600300 PRESTAMO A. VELASCO | B250: 1600000 | D250: 1600000
A251: 1140601100 PRESTAMO LORENA ALVES | B251: -50000 | D251: -50000
A252: 1140601300 PRESTAMO CUBA | B252: -200000 | D252: -200000
A253: 1140900700 SEGUROS A DEV. ZURICH ASEG. S.A. | B253: -8283474.4 | D253: -8283474.4
... A298: 4231100000 RESULTADO POR TENENCIA FCI | B298: -677309.44 | D298: 17725.23

Sheet EESP
A1: TRANSPORTES FURLONG S.A
A3: 31 de Julio de 2026
A5: Estado de Situación Patrimonial
F9: 46234 | L9: =+F9 -> 46234 | M9: 38717
B10: ACTIVO: | I10: PASIVO
C11: ACTIVO CORRIENTE | I11: PASIVO CORRIENTE
D12: Caja y bancos (Nota 4.a) | F12: =+Activo!F19 -> -25381360 | J12: Deudas
D13: Creditos comerciales | F13: =+Activo!F21 -> 0 | K13: Deudas impositivas | L13: =+Pasivo!E29 -> -32024141
D14: Creditos Impositivos | F14: =+Activo!F37 -> 0 | K14: Deudas accionistas | L14: 0
D15: Inversiones temporarias (Nota 4.b) | F15: =+Activo!F25 -> -20812691 | K15: Comerciales (Nota 4.e) | L15: =+Pasivo!E16 -> 87249492
K16: Otras deudas (Nota 4.f) | L16: 0
D17: Créditos por ventas (Nota 4.c) | F17: =+Activo!F29 -> -636618.95 | K17: Remuneraciones y cs.sociales (Nota 4.f) | L17: =+Pasivo!E30 -> -37946732
K18: Cargas fiscales (Nota 4.h) | L18: =+Pasivo!E37 -> 189282.89
K19: Anticipos de clientes | L19: 0
K20: Dividendos a pagar | L20: 0
K21: Otras deudas (Nota 4.g) | L21: =+Pasivo!E19 -> 0
D22: Otros Creditos (Nota 4.d) | F22: =+Activo!F62 -> -2811999.2 | J22: Total deudas | L22: =+L15+L16+L17+L18 -> 49492043
L23: 0
C24: Total del Activo corriente | F24: =SUM(F12:F22) -> -49642669 | I24: Total del Pasivo Corriente | L24: =+L22 -> 49492043
I25: Total del Pasivo | L25: =+L24 -> 49492043
C28: ACTIVO NO CORRIENTE
D29: Bienes de uso | F29: =+SALDOS!E47 -> -2485298.3 | I29: PATRIMONIO NETO (Según estado respec.) | L29: =+EEPN!I18 -> -1.0162001e+08
C31: Total del Activo no corriente | F31: =SUM(F29:F30) -> -2485298.3 | L31: =+L29 -> -1.0162001e+08
C33: Total del Activo | F33: =+F24+F31 -> -52127967 | I33: Total del Pasivo y Patrimonio Neto | L33: =+L25+L31 -> -52127967

Sheet EERR
A1: TRANSPORTES FURLONG S.A
A3: =+EESP!A3 -> 31 de Julio de 2026
A5: Estado de Resultados
C9: =+EESP!F9 -> 46234 | D9: =+EESP!G9 -> 0
A12: Ingresos por servicios prestados | C12: =+SALDOS!C129-SALDOS!B129 -> 0
A15: Gastos de comercialización (Anexo II) | C15: =+'Anexo II'!E113 -> 94344997
A16: Gastos de administración (Anexo II) | C16: =+'Anexo II'!D113 -> 6217669.7
A17: Gastos de financieros (Anexo II) | C17: =+'Anexo II'!F113 -> 1734653.4
A19: Subtotal | C19: =+C12+C13-C15-C16-C17 -> -1.0229732e+08
A20: Resultado venta bienes de uso | C20: =+SALDOS!C135 -> 0
A21: Recupero de Gastos | C21: =-SALDOS!B132+SALDOS!C132 -> 0
A22: Diferencia de cotización | C22: =-SALDOS!B130+SALDOS!C130 -> 0
A23: Intereses | C23: =+SALDOS!C131+SALDOS!C136 -> 677309.44
A24: Otros ingresos | C24: =+SALDOS!C218
A25: Ganancia antes de impuesto | C25: =+C19+C20+C22+C21+C23+C24 -> -1.0162001e+08
A26: Impuesto a las Ganancias | C26: 0
A28: Ganancia del ejercicio | C28: =+C25-C26 -> -1.0162001e+08

Sheet EEPN
A1: =+EESP!A1 -> TRANSPORTES FURLONG S.A
A2: =+EESP!A3 -> 31 de Julio de 2026 | B2: =+EESP!A3 -> 31 de Julio de 2026
A3: Estado de Evolución del Patrimonio Neto
J5: =+EESP!F9 -> 46234 | K5: =+EESP!G9 -> 0
B6: CONCEPTO | C6: Aportes de los propietarios | F6: Ganancias | G6: Reservadas | I6: Resultados | J6: Total del | K6: Total del
C7: Capital | D7: Ajuste | E7: Total de | F7: Reserva | G7: Otras | H7: Aportes | I7: no | J7: patrimonio | K7: patrimonio
D8: de Capital | E8: Capital | F8: legal | G8: reservas | H8: Irrevocables | I8: asignados | J8: neto | K8: neto
C9: $ | D9: $ | E9: $ | F9: $ | G9: $ | I9: $ | J9: $ | K9: $
B11: Saldos al inicio del ejercicio | C11: 0 | D11: 0 | E11: =+C11+D11 -> 0 | F11: 0 | G11: 0 | H11: 0 | I11: =-SALDOS!D126 -> 0 | J11: =+E11+F11+G11+I11 -> 0
C13: =SUM(C11:C11) -> 0 | D13: =SUM(D11:D11) -> 0 | E13: =SUM(E11:E11) -> 0 | F13: =SUM(F11:F11) -> 0 | G13: =SUM(G11:G11) -> 0 | H13: =SUM(H11:H11) -> 0 | I13: =SUM(I11:I12) -> 0 | J13: =SUM(J11:J12) -> 0 | K13: =SUM(K11:K11) -> 0
B15: Reasignación casa matriz
B16: Ganancia (Pérdida) del ejercicio | I16: =EERR!C28 -> -1.0162001e+08 | J16: =+I16 -> -1.0162001e+08
B18: Total al 31/7/26 | C18: =+C13 -> 0 | D18: =+D13 -> 0 | E18: =+E13 -> 0 | F18: =+F13 -> 0 | G18: =+G13 -> 0 | H18: =+H13 -> 0 | I18: =+I13+I16+I15 -> -1.0162001e+08 | J18: =+J13+J16+J15 -> -1.0162001e+08 | K18: =+K13+K16 -> 0
B19: Total al 31.12.05 | E19: =+C19+D19 -> 0 | G19: 0 | I19: 0 | J19: =+E19 -> 0 | K19: =+G19 -> 0
B21: Las notas y anexos adjuntos forman parte integrante de los estados contables
B22: Informe profesional por separado

Sheet Activo
B1: NOTA 4: | E1: COMPOSICION DE LOS RUBROS
B3: Al 31 de Julio del 2026 - cifras expresadas en Pesos
F6: =+EESP!F9 -> 46234 | H6: 38717
B7: ACTIVO
B8: Activo Corriente
B9: a. | C9: Caja y bancos
D10: - Caja
D11: - Fondo Fijo a rendir
D12: - Fondo Fijo | F12: =-SALDOS!C7+SALDOS!B7 -> -265310.63
D13: - Banco Francés c/c | F13: =-SALDOS!C9+SALDOS!B9 -> -25116050
D14: - Cheques no depositados
D15: - Efectivo casa matriz
D16: - Fondo fijo SENASA | F16: =-SALDOS!C8+SALDOS!B8 -> 0
D17: - Fondo fijo Adelando PDT | F17: =+SALDOS!C10+SALDOS!B10 -> 0
D18: - Valores a depositar
F19: =SUM(F10:F18) -> -25381360
B21: b. | C21: Inversiones temporarias
D22: - Plazo fijo | F22: =-SALDOS!C30 -> 0
D23: - Fondo común de inversión BBVA | F23: =-SALDOS!C29+SALDOS!B29 -> -20812691
D24: - Intereses a dev Plazo Fijo | F24: =+SALDOS!B31 -> 0
F25: =SUM(F22:F24) -> -20812691
B27: c. | C27: Creditos por Ventas
D28: - Deudores por ventas | F28: =+SALDOS!D11+SALDOS!D14+SALDOS!D15+SALDOS!D17+SALDOS!D16 -> -636618.95
F29: =SUM(F28:F28) -> -636618.95
C31: Creditos impositivos
D32: - Retencion de Gcias. | F32: 0
D33: - Retenc. Suss | F33: 0
D34: - Reten. Ingresos Brutos | F34: 0
D35: - Percepcion y Retencion IVA | F35: 0
D36: - Crédito ley 25413 | F36: 0
F37: =SUM(F32:F36) -> 0
B39: d. | C39: Otros créditos
D40: - Transportes Furlong Uruguay
D41: - Transportes Furlong Cordoba
D42: - Adelanto de gastos
D43: - Adelantos Tomás Furlong
D44: - Adelantos PDT | F44: =+SALDOS!B18-SALDOS!C18 -> 4122436.3
D45: - Adelanto honorarios CF
D46: - Adelanto al personal
D47: - Anticipo Combustible Velasco
D48: - Adelanto SAC
D49: - Anticipo de vacaciones | F49: =+SALDOS!D25 -> 0
D50: - Seguros a devengar | F50: =-SALDOS!C26-SALDOS!C27-SALDOS!C28+SALDOS!B26+SALDOS!B27 -> -8284435.5
D51: - Anticipos de Vacaciones
D52: - Préstamo Paccielo | F52: =-SALDOS!C23 -> 0
D53: - Préstamo A Velasco | F53: =-SALDOS!C19+SALDOS!B19 -> 1600000
D54: - Préstamo Lorena Alves | F54: =-SALDOS!C21 -> -50000
D55: - Anticipo patentamientos
D56: - Donaciones
D57: - Seguros a Devengar
D58: - Adicional obral social
D59: - Honorarios Directores Tomas
D60: - Honorarios Directores
D61: - Prestamo Cuba | F61: =-SALDOS!C22+SALDOS!B22 -> -200000
F62: =SUM(F40:F61) -> -2811999.2
B69: Las notas y anexos adjuntos forman parte integrante de los estados contables
B70: Informe profesional por separado

Sheet Pasivo
E1: =+Activo!F6 -> 46234 | G1: 31.03.04 | K1: 31.03.03 | L1: =+EESP!G9 -> 0
A2: Pasivo
A3: Pasivo Corriente
A4: e. | B4: Deudas comerciales
C5: - Provisión Multas a Pagar | E5: 0
C6: - Provisión fletes esporádicos | E6: 0
C7: - Previsiones | E7: 0
C8: - Proveedores | E8: =-SUM(SALDOS!D53:D79)-SALDOS!D88-SALDOS!D101-SALDOS!D114-SALDOS!D115 -> -4089334
C9: - Adelanto casa matriz | E9: =-SALDOS!D95-SALDOS!D12 -> 91338826
C10: - Adelanto de clientes | E10: 0
C11: - Siniestros a pagar | E11: 0
C12: - Prestamos Amx - Claro | E12: 0
C13: - Convenio HSBC | E13: 0
C14: - Rodados a patentar | E14: 0
C15: -Cheques Emitidos | E15: 0
E16: =SUM(E5:E15) -> 87249492
A18: f. | B18: Otras deudas
C19: - Acuerdos CNRT a pagar | E19: 0
C20: - Prestamo Carlos Furlong | E20: 0
C21: - Prestamo Lorena Alves | E21: 0
C22: - Prestamo Cuba | E22: 0
C23: - Prestamo Vera | E23: 0
E24: =SUM(E19:L23) -> 0
A27: f. | B27: Remuneraciones y cs. Sociales
C28: - SUSS a pagar | E28: =+SALDOS!C83-SALDOS!B83 -> -5922590.5
C29: - Sueldos a pagar | E29: =+SALDOS!C82-SALDOS!B82 -> -32024141 | G29: 938.38 | K29: 0
E30: =SUM(E28:E29) -> -37946732 | G30: =SUM(G28:G29) -> 938.38 | K30: =SUM(#REF!) -> #REF!
A32: h. | B32: Cargas Fiscales
C34: - Plan Mis Facilidades | E34: =+SALDOS!C85-SALDOS!B85 -> -83974.39
C35: - Interes a devengar | E35: =+SALDOS!C86-SALDOS!B86 -> 16382.87
C36: - SICORE a pagar | E36: =-SALDOS!B84+SALDOS!C84 -> 256874.41
E37: =SUM(E34:E36) -> 189282.89

Sheet Anexo I
A1: B I E N E S D E U S O
A2: =+EESP!A3 -> 31 de Julio de 2026
B5: VALOR DE ORIGEN | E5: DEPRECIACIONES
B6: VALORES AL | D6: VALORES AL | E6: ACUMULADAS | G6: ALTAS | H6: DEL EJERCICIO | J6: ACUMULADAS | K6: NETO
A7: CONCEPTO | B7: COMIENZO DEL | C7: AUMENTOS | D7: CIERRE DEL | E7: AL INICIO DEL | F7: BAJAS | G7: DEL EJERCICIO | H7: ALICUOTA | I7: MONTO | J7: AL CIERRE DEL | K7: RESULTANTE
B8: EJERCICIO | D8: EJERCICIO | E8: EJERCICIO | J8: EJERCICIO | K8: =+EESP!F9 -> 46234
B9: $ | C9: $ | D9: $ | E9: $ | F9: $ | I9: $ | J9: $ | K9: $
A11: Software | B11: 754089.29 | C11: 0 | D11: =+B11 -> 754089.29 | E11: 754089.29 | H11: 0.2 | I11: =+J11-E11 -> 0 | J11: 754089.29 | K11: =+D11-J11 -> 0
A12: Hardware | B12: 349454.86 | C12: 0 | D12: =+B12 -> 349454.86 | E12: 349454.86 | H12: 0.2 | I12: =+J12-E12 -> 0 | J12: 349454.86 | K12: =+D12-J12 -> 0
A13: Computadoras | B13: 19271906 | C13: 0 | D13: =+B13 -> 19271906 | E13: 16777769 | H13: 0.2 | I13: =+J13-E13 -> 430023.51 | J13: 17207793 | K13: =+D13-J13 -> 2064112.9
A14: Equipos | B14: 2833073.7 | C14: 0 | D14: =+B14 -> 2833073.7 | E14: 2833073.7 | H14: 0.2 | I14: =+J14-E14 -> 0 | J14: 2833073.7 | K14: =+D14-J14 -> 0
A15: Muebles y Utiles | B15: 2913406.5 | C15: 0 | D15: =+B15 -> 2913406.5 | E15: 2735631.6 | H15: 0.1 | I15: =+J15-E15 -> 18518.22 | J15: 2754149.8 | K15: =+D15-J15 -> 159256.65
A16: Instalaciones | B16: 9934406.7 | C16: 0 | D16: =+B16 -> 9934406.7 | E16: 9934406.7 | H16: 0.1 | I16: =+J16-E16 -> 0 | J16: 9934406.7 | K16: =+D16-J16 -> 0
A17: Rodados | B17: 1.6624361e+08 | C17: 0 | D17: =+B17 -> 1.6624361e+08 | E17: 74041451 | F17: 0 | H17: 0.2 | I17: =+J17-E17 -> 11977950 | J17: 86019401 | K17: =+D17-J17 -> 80224213
A18: =+EEPN!B18 -> Total al 31/7/26 | B18: =SUM(B11:B17) -> 2.0229995e+08 | C18: =SUM(C11:C17) -> 0 | D18: =SUM(D11:D17) -> 2.0229995e+08 | E18: =SUM(E11:E17) -> 1.0742588e+08 | F18: =SUM(F17) -> 0 | I18: =+SALDOS!B161 -> 2485298.3 | J18: =SUM(J11:J17) -> 1.1985237e+08 | K18: =SUM(K11:K17) -> 82447582
A21: Las notas y anexos adjuntos forman parte integrante de los estados contables
A22: Informe profesional por separado

Sheet Anexo II
G1: ANEXO II
A3: Información Requerida por el Art. 64 Inc. b) de la Ley 19.550 | F3: Anexo II
A4: =+Activo!B3 -> Al 31 de Julio del 2026 - cifras expresadas en Pesos
C6: TOTALES | D6: GASTOS | E6: GASTOS | F6: GASTOS | G6: TOTALES
B7: CONCEPTOS | C7: AL | D7: DE | E7: DE | G7: AL | J7: GASTOS ADM CTRAL | K7: GASTOS PACHECO | L7: GASTOS CORDOBA | M7: COSTOS TRANSPORTES | N7: TOTAL | O7: PAGOS ANTIC | P7: TRANF CASA MATRIZ | Q7: TOTAL EGRESO
C8: =+EESP!F9 -> 46234 | D8: ADMINISTRACION | E8: COMERCIALIZACION | F8: FINANCIEROS | G8: 31.03.02
B9: Acuerdo Seclo | C9: =SUM(D9:F9) -> 0 | D9: 0 | E9: =+SALDOS!B164 -> 0 | F9: 0
B10: Adelanto Viaje | C10: =SUM(D10:F10) -> 0 | D10: 0 | E10: =+SALDOS!B216 | F10: 0
B11: Alquiler de autos | C11: =SUM(D11:F11) -> 0 | D11: 0 | E11: =+SALDOS!B198 | F11: 0
B12: Alquiler cochera | C12: =SUM(D12:F12) -> 0 | D12: 0 | E12: =+SALDOS!B206 | F12: 0
B13: Alquiler dpto. | C13: =SUM(D13:F13) -> 0 | D13: 0 | E13: =+SALDOS!B204 | F13: 0
B14: Alquiler fotocopiadora | C14: =SUM(D14:F14) -> 467976.4 | D14: =+SALDOS!B163-SALDOS!C163 -> 467976.4 | E14: =+SALDOS!B205 | F14: 0
B15: Alquiler Oficina Móvil | C15: =SUM(D15:F15) -> 0 | D15: =+SALDOS!B167 -> 0 | E15: 0 | F15: 0
B16: Amortizaciones | C16: =SUM(D16:F16) -> 2485298.3 | D16: 0 | E16: =+SALDOS!B161 -> 2485298.3 | F16: 0
B17: Almuerzos | C17: =SUM(D17:F17) -> 0 | D17: 0 | E17: =+SALDOS!B208 | F17: 0
B18: Autónomos Directores | C18: =SUM(D18:F18) -> 72446.22 | D18: =+SALDOS!B160-SALDOS!C160 -> 72446.22 | E18: =+SALDOS!B209 | F18: 0
B19: Agua | C19: =SUM(D19:F19) -> 0 | D19: =+SALDOS!B162 -> 0 | E19: 0 | F19: 0
B20: Ajuste saldo proveedores | C20: =SUM(D20:F20) -> 0 | D20: 0 | E20: 0 | F20: 0
B21: Bs Personales Acc. Y Participacion | C21: =SUM(D21:F21) -> 0 | D21: =++SALDOS!B197 | E21: =+SALDOS!B213 | F21: 0
B22: Sueldos | C22: =SUM(D22:F22) -> 0 | D22: 0 | E22: =+SALDOS!B214 | F22: 0
B23: Cargas Sociales | C23: =SUM(D23:F23) -> 0 | D23: 0 | E23: 0 | F23: 0
B24: Salario Complementario del Decreto 332/20 | C24: =SUM(D24:F24) -> 0 | D24: 0 | E24: =-SALDOS!C165 -> 0 | F24: 0
B25: Cesión de Derechos | C25: =SUM(D25:F25) -> 0 | D25: =+SALDOS!B217 | E25: 0 | F25: 0
B26: Comisiones | C26: =SUM(D26:F26) -> 0 | D26: 0 | E26: 0 | F26: 0
B27: Gastos varios clientes | C27: =SUM(D27:F27) -> 0 | D27: 0 | E27: =+SALDOS!B220 | F27: 0
B28: Verificación Técnica Vehicular | C28: =SUM(D28:F28) -> 80711 | D28: 0 | E28: =+SALDOS!B215 -> 80711 | F28: 0
B29: Amortizaciones | C29: =SUM(D29:F29) -> 0 | D29: 0 | E29: 0 | F29: 0
B30: Accidentes | C30: =SUM(D30:F30) -> 0 | D30: 0 | E30: =+SALDOS!B199 | F30: 0 | I30: OBRA SOCIAL | J30: 3400.5126 | K30: 5282.0813 | L30: 3714.6061 | P30: 4372 | R30: ACA ES LA FACTURA QUE SE VA A PAGAR EL MES PRÓXIMO SE INCLUYE EN CARGAS SOCIALES (EN EL BALANCE)
B31: Cargas Sociales | C31: =SUM(D31:F31) -> 8933342.3 | D31: 0 | E31: =+SALDOS!B143+SALDOS!B145 -> 8933342.3 | F31: 0 | I31: C SOCIALES | J31: 7385.6622 | K31: 30178.815 | L31: 9981.5423 | R31: CORRESPONDE AL MES DE MAYO / SE PAGA EN JUNIO
B32: Telefonos | C32: =SUM(D32:F32) -> 0 | D32: 0 | E32: 0 | F32: 0
B33: Librería | C33: =SUM(D33:F33) -> 0 | D33: =+SALDOS!B141 -> 0 | E33: 0 | F33: 0
B34: Leasing | C34: =SUM(D34:F34) -> 0 | D34: 0 | E34: =+SALDOS!B226 | F34: 0 | I34: ALQUILER | L34: =+E34 -> 0
B35: Viaticos | C35: =SUM(D35:F35) -> 0 | D35: 0 | E35: 0 | F35: 0
B36: Repuestos y reparaciones | C36: =SUM(D36:F36) -> 0 | D36: 0 | E36: 0 | F36: 0
B37: Catering | C37: =SUM(D37:F37) -> 0 | D37: =+SALDOS!B155 -> 0 | E37: 0 | F37: 0 | I37: COMIDA | J37: 474 | K37: 528
B38: CNRT | C38: =SUM(D38:F38) -> 0 | D38: 0 | E38: =+SALDOS!B187 | F38: 0 | I38: MULTAS | P38: =+C38 -> 0
B39: Gastos bancarios | C39: =SUM(D39:F39) -> 0 | D39: 0 | E39: 0 | F39: 0
B40: Intereses | C40: =SUM(D40:F40) -> 0 | D40: 0 | E40: 0 | F40: 0 | I40: F. FIJOS FORD/VW/PTO 14 | K40: =4800+5000+3000+5000 -> 17800 | L40: 7200 | R40: SON FACTURAS DE COMBUSTIBLE / POR ESO SE SUMA EN COMBUSTIBLES
B41: Combustible | C41: =SUM(D41:F41) -> 506825.21 | D41: 0 | E41: =+SALDOS!B182+SALDOS!B230 -> 506825.21 | F41: 0 | I41: COMBUSTIBLE | J41: 281.16 | K41: =3211.01+4543.6 -> 7754.61 | L41: 1075.53
B42: Comunicaciones | C42: =SUM(D42:F42) -> 505527.94 | D42: 0 | E42: =-SALDOS!C176+SALDOS!B176 -> 505527.94 | F42: 0 | I42: TELEFONOS | J42: =2248.27+2043.98+1241.35 -> 5533.6 | K42: =2543.13+2338.55+2410.41 -> 7292.09 | L42: =1803.75+2112.36+2202.79 -> 6118.9 | M42: 1098.32 | R42: HAY CARGADAS 2 FACTURAS VIEJAS DE NEXTEL QUE NO ESTABAN
B43: Correo | C43: =SUM(D43:F43) -> 0 | D43: 0 | E43: 0 | F43: 0
B44: Custodia | C44: =SUM(D44:F44) -> 0 | D44: =SALDOS!B178 | E44: 0 | F44: 0
B45: Despachantes | C45: =SUM(D45:F45) -> 52270571 | D45: 0 | E45: =+SALDOS!B179 -> 52270571 | F45: 0 | I45: DESPACHANTES | K45: =3200+3115 -> 6315 | L45: =4800+1400+3115 -> 9315 | M45: =29395.55+31000.65 -> 60396.2 | O45: 3180
B46: Donaciones | C46: =SUM(D46:F46) -> 600000 | D46: 0 | E46: =+SALDOS!B201 -> 600000 | F46: 0
B47: Publicidad | C47: =SUM(D47:F47) -> 0 | D47: 0 | E47: =+SALDOS!B212 | F47: 0
B48: Estadía | C48: =SUM(D48:F48) -> 0 | D48: 0 | E48: =+SALDOS!B193 | F48: 0
B49: Estacionamiento | C49: =SUM(D49:F49) -> 0 | D49: 0 | E49: =+SALDOS!B186 | F49: 0
B50: Estibajes | C50: =SUM(D50:F50) -> 0 | D50: 0 | E50: =+SALDOS!B203 | F50: 0 | I50: ESTIBAJES | M50: =+C50 -> 0
B51: Embargo Rdicación Vehicular | C51: =SUM(D51:F51) -> 0 | D51: 0 | E51: =+SALDOS!B229 | F51: 0
B52: Fletes | C52: =SUM(D52:F52) -> -5080374 | D52: 0 | E52: =+SALDOS!B192-SALDOS!C192+SALDOS!B157-SALDOS!C157 -> -5080374 | F52: 0 | I52: TRANSPORTES | M52: =+C52 -> -5080374 | R52: ACA QUEDA LA DIFERENCIA DE PROVISION
B53: Gastos Capacitación | C53: =SUM(D53:F53) -> 0 | D53: =+SALDOS!B153 -> 0 | E53: 0 | F53: 0
B54: Gastos Medicos | C54: =SUM(D54:F54) -> 5380203.4 | D54: =+SALDOS!B168 -> 5380203.4 | E54: 0 | F54: 0
B55: Gastos de Representación | C55: =SUM(D55:F55) -> 0 | D55: 0 | E55: =+SALDOS!B195-SALDOS!C195 | F55: 0 | I55: TOMAS (FF Y VISA) | J55: 1949.3367 | K55: 1949.3367 | L55: 1949.3367
B56: Gastos Generales | C56: =SUM(D56:F56) -> 0 | D56: 0 | E56: =+SALDOS!B137-SALDOS!C137-SALDOS!C188 | F56: 0
B57: Gastos de instalación | C57: =SUM(D57:F57) -> 0 | D57: 0 | E57: 0 | F57: 0
B58: Gs Ropa de Trabajo | C58: =SUM(D58:F58) -> 0 | D58: =+SALDOS!B202 | E58: =+SALDOS!B207 | F58: 0
B59: Gastos trámites | C59: =SUM(D59:F59) -> 0 | D59: =+SALDOS!B150 -> 0 | E59: 0 | F59: 0
B60: Gastos PC | C60: =SUM(D60:F60) -> 0 | D60: =+SALDOS!B146 -> 0 | E60: 0 | F60: 0
B61: Gastos varios | C61: =SUM(D61:F61) -> 297043.66 | D61: =SALDOS!B188 -> 297043.66 | E61: 0 | F61: 0 | I61: VARIOS | J61: =+C59 -> 0 | K61: =+C61 -> 297043.66 | P61: =+C46 -> 600000
B62: Gastos varios personal | C62: =SUM(D62:F62) -> 0 | D62: 0 | E62: =+SALDOS!B159-SALDOS!C159 -> 0 | F62: 0
B63: Gastos varios clientes | C63: =SUM(D63:F63) -> 0 | D63: 0 | E63: =+SALDOS!B214-SALDOS!C214 | F63: 0
B64: Gastos y comisiones bancarias | C64: =SUM(D64:F64) -> 1716928.2 | D64: 0 | E64: 0 | F64: =+SALDOS!B222-SALDOS!C222+SALDOS!B233 -> 1716928.2 | I64: GASTOS BANCARIOS | J64: =+C64 -> 1716928.2
B65: Gastos Obra Social | C65: =SUM(D65:F65) -> 0 | D65: =-SALDOS!C149 -> 0 | E65: 0 | F65: 0
B66: Gastos Hotelería | C66: =SUM(D66:F66) -> 0 | D66: =+SALDOS!B170 -> 0 | E66: 0 | F66: 0
B67: Gastos Gestoria | C67: =SUM(D67:F67) -> 0 | D67: =+SALDOS!B171 -> 0 | E67: 0 | F67: 0
B68: Habilitaciones | C68: =SUM(D68:F68) -> 0 | D68: =+SALDOS!B172 -> 0 | E68: 0 | F68: 0
B69: Honorarios director | C69: =SUM(D69:F69) -> 0 | D69: 0 | E69: =+SALDOS!B151 -> 0 | F69: 0
B70: Honorarios profesionales | C70: =SUM(D70:F70) -> 4577701.1 | D70: 0 | E70: =+SALDOS!B140 -> 4577701.1 | F70: 0 | I70: HONORARIOS | J70: =9400+850+550 -> 10800 | K70: =850+700 -> 1550
B71: Honorarios Legales | C71: =SUM(D71:F71) -> 0 | D71: 0 | E71: =+SALDOS!B169 -> 0 | F71: 0
B72: Imp. A los créditos | C72: =SUM(D72:F72) -> 0 | D72: 0 | E72: 0 | F72: =+SALDOS!B224
B73: Imp. A los débitos | C73: =SUM(D73:F73) -> 0 | D73: 0 | E73: 0 | F73: =+SALDOS!B223
B74: Imp. Bienes Sociedades | C74: =SUM(D74:F74) -> 0 | D74: 0 | E74: 0 | F74: 0 | I74: IMPUESTOS | J74: =+$C$18/3+C74 -> 24148.74 | K74: =+$C$18/3 -> 24148.74 | L74: =+$C$18/3 -> 24148.74
B75: Intereses resarcitorios | C75: =SUM(D75:F75) -> 17725.23 | D75: =-SALDOS!C225 | E75: 0 | F75: =+SALDOS!B225 -> 17725.23
B76: Impuestos varios | C76: =SUM(D76:F76) -> 0 | D76: 0 | E76: 0 | F76: =+SALDOS!B227
B77: Impuestos al Cheuque | C77: =SUM(D77:F77) -> 0 | D77: 0 | E77: 0 | F77: =+SALDOS!B228
B78: Juicios | C78: =SUM(D78:F78) -> 0 | D78: =+SALDOS!B213 | E78: 0 | F78: 0
B79: Indemnizaciones | C79: =SUM(D79:F79) -> 0 | D79: =+SALDOS!B142-SALDOS!C142 -> 0 | E79: 0 | F79: 0 | I79: LIBRERÍA | J79: =213.333333333333+500 -> 713.33333 | K79: =213.333333333333+500 -> 713.33333 | L79: =213.333333333333+17.55 -> 230.88333 | R79: SE REGISTRAN LAS FC X FECHA DE EMISION
B80: Legalizaciones | C80: =SUM(D80:F80) -> 0 | D80: =+SALDOS!B158 -> 0 | E80: 0 | F80: 0 | I80: LEGALIZACIONES | J80: 270
B81: Locomoción | C81: =SUM(D81:F81) -> 0 | D81: 0 | E81: =+SALDOS!B177-SALDOS!C177 | F81: 0
B82: Logística | C82: =SUM(D82:F82) -> 0 | D82: 0 | E82: =+SALDOS!B208 | F82: 0
B83: Mantenimiento | C83: =SUM(D83:F83) -> 508928 | D83: 0 | E83: =+SALDOS!B156 -> 508928 | F83: 0 | I83: MANTENIMIENTO | J83: =+C60 -> 0 | K83: 250 | L83: =595-250 -> 345
B84: Mantenimiento de flota | C84: =SUM(D84:F84) -> 0 | E84: =+SALDOS!B180 | F84: 0
B85: Reparaciones de flota | C85: =SUM(D85:F85) -> 0 | E85: =+SALDOS!B181 | F85: 0
B86: Mantenimiento de maquinas | C86: =SUM(D86:F86) -> 0 | D86: =-SALDOS!C155 -> 0 | E86: 0 | F86: 0
B87: Mensajería | C87: =SUM(D87:F87) -> 0 | D87: =+SALDOS!B184 | E87: 0 | F87: 0 | I87: MENSAJERIA | J87: 3500 | K87: 3500
B88: Medicina Laboral | C88: =SUM(D88:F88) -> 0 | D88: 0 | E88: 0 | F88: 0
B89: Molilidad y viáticos | C89: =SUM(D89:F89) -> 0 | D89: =+SALDOS!B138-SALDOS!C138 -> 0 | E89: 0 | F89: 0
B90: Multas | C90: =SUM(D90:F90) -> 873100 | D90: 0 | E90: =-SALDOS!C194+SALDOS!B194 -> 873100 | F90: 0
B91: Gastos PC | C91: =SUM(D91:F91) -> 0 | D91: =-SALDOS!C146 -> 0 | E91: 0 | F91: 0
B92: Gastos de logistica | C92: =SUM(D92:F92) -> -1475516.7 | D92: 0 | E92: =+SALDOS!B196-SALDOS!C196 -> -1475516.7 | F92: 0
B93: Patentes | C93: =SUM(D93:F93) -> 0 | D93: 0 | E93: =+SALDOS!B210 | F93: 0 | I93: PATENTES | J93: 546.19 | K93: =723.69-546.19 -> 177.5 | R93: SE PAGARAN EL MES PROXIMO
B94: Peajes | C94: =SUM(D94:F94) -> -26554548 | D94: 0 | E94: =+SALDOS!B185-SALDOS!C185 -> -26554548 | F94: 0
B95: Multas | C95: =SUM(D95:F95) -> 0 | D95: 0 | E95: 0 | F95: 0
B96: Reparaciones | C96: =SUM(D96:F96) -> 7949700 | D96: 0 | E96: =+SALDOS!B154-SALDOS!C154 -> 7949700 | F96: 0
B97: Refrigerios | C97: =SUM(D97:F97) -> 0 | D97: =+SALDOS!B190 | E97: 0 | F97: 0 | I97: FONDOS FIJOS | K97: =37+14+36.5+E84+88 -> 175.5 | L97: =302.7-37+63 -> 328.7
B98: Ropa de trabajo | C98: =SUM(D98:F98) -> 0 | D98: =+SALDOS!B221 | E98: 0 | F98: 0
B99: Seguros | C99: =SUM(D99:F99) -> 10864966 | D99: 0 | E99: =+SALDOS!B175-SALDOS!C175 -> 10864966 | F99: 0 | I99: SEGUROS | K99: =528.01-1.9 -> 526.11 | L99: 426.07 | M99: 59330.35
B100: Seguridad | C100: =SUM(D100:F100) -> 0 | D100: 0 | E100: =+SALDOS!B189 | F100: 0 | I100: ANTICIPOS | M100: =+E92 -> -1475516.7 | O100: =+C100 -> 0
B101: Servicio de limpieza | C101: =SUM(D101:F101) -> 0 | D101: =+SALDOS!B152 -> 0 | E101: 0 | F101: 0 | I101: FUMIGACION | J101: 240 | K101: 240
B102: Deudores Incobrables | C102: =SUM(D102:F102) -> 0 | D102: 0 | E102: =+SALDOS!B218 | F102: 0
...
