Workbook

Sheet SALDOS
A1: TRANSPORTES FURLONG BRASIL | C1: Acumulado
C3: Deudor | D3: Acreedor
A4: ACTIVO
B5: 1110100330 FONDO FIJO BS. AS. | C5: =IF(E5>0,E5,0) -> 4878940.2 | D5: =IF(E5<0,-E5,0) -> 0 | E5: =IFERROR(VLOOKUP(B5,$A$235:$B$357,2,FALSE),0) -> 4878940.2
B6: 1110100340 FONDO FIJO SENASA | C6: =IF(E6>0,E6,0) -> 0 | D6: =IF(E6<0,-E6,0) -> 0 | E6: =IFERROR(VLOOKUP(B6,$A$235:$B$357,2,FALSE),0) -> 0
B7: 1110100420 BANCO FRANCES C/C | C7: =IF(E7>0,E7,0) -> 219745.62 | D7: =IF(E7<0,-E7,0) -> 0 | E7: =IFERROR(VLOOKUP(B7,$A$235:$B$357,2,FALSE),0) -> 219745.62
B8: 1110101050 FONDO FIJO ADELANTOS PDT | C8: =IF(E8>0,E8,0) -> 0 | D8: =IF(E8<0,-E8,0) -> 0 | E8: =IFERROR(VLOOKUP(B8,$A$235:$B$357,2,FALSE),0) -> 0
B9: 1120100100 FORD | C9: =IF(E9>0,E9,0) -> 228102.13 | D9: =IF(E9<0,-E9,0) -> 0 | E9: =IFERROR(VLOOKUP(B9,$A$235:$B$357,2,FALSE),0) -> 228102.13
B10: 1120100400 TRANSPORTES FURLONG S.A. AR | C10: =IF(E10>0,E10,0) -> 0 | D10: =IF(E10<0,-E10,0) -> 4.0832693e+08 | E10: =IFERROR(VLOOKUP(B10,$A$235:$B$357,2,FALSE),0) -> -4.0832693e+08
B11: 1120100700 RENAULT ARG. S.A. | C11: =IF(E11>0,E11,0) -> 0 | D11: =IF(E11<0,-E11,0) -> 0 | E11: =IFERROR(VLOOKUP(B11,$A$235:$B$357,2,FALSE),0) -> 0
B12: 1120101300 VOLKSWAGEN ARGENTINA S.A. | C12: =IF(E12>0,E12,0) -> 725484.5 | D12: =IF(E12<0,-E12,0) -> 0 | E12: =IFERROR(VLOOKUP(B12,$A$235:$B$357,2,FALSE),0) -> 725484.5
B13: 1120101600 FCA AUTOMOBILES ARGENTINA S.A. | C13: =IF(E13>0,E13,0) -> 0 | D13: =IF(E13<0,-E13,0) -> 0 | E13: =IFERROR(VLOOKUP(B13,$A$235:$B$357,2,FALSE),0) -> 0
B14: 1120131000 CNH ARGENTINA S.A. | C14: =IF(E14>0,E14,0) -> 0 | D14: =IF(E14<0,-E14,0) -> 0 | E14: =IFERROR(VLOOKUP(B14,$A$235:$B$357,2,FALSE),0) -> 0
B15: 1120138000 STELLANTIS AUTOMOVILES DE ARGENTINA S. A | C15: =IF(E15>0,E15,0) -> 156195.52 | D15: =IF(E15<0,-E15,0) -> 0 | E15: =IFERROR(VLOOKUP(B15,$A$235:$B$357,2,FALSE),0) -> 156195.52
B16: 1140300100 ANTICIPO A PDT | C16: =IF(E16>0,E16,0) -> 28186194 | D16: =IF(E16<0,-E16,0) -> 0 | E16: =IFERROR(VLOOKUP(B16,$A$235:$B$357,2,FALSE),0) -> 28186194
... B45: 1220700000 AMORT. ACUM. RODADOS | C45: =IF(E45>0,E45,0) -> 0 | D45: =IF(E45<0,-E45,0) -> 90810581 | E45: =IFERROR(VLOOKUP(B45,$A$235:$B$357,2,FALSE),0) -> -90810581
E46: =IFERROR(VLOOKUP(B46,$A$235:$B$357,2,FALSE),0) -> 0 | F46: =SUM(E5:E45) -> -2.5927362e+08
A47: PASIVO | E47: =IFERROR(VLOOKUP(B47,$A$235:$B$357,2,FALSE),0) -> 0
B48: 2110100300 COTELCAM | C48: =IF(E48>0,E48,0) -> 0 | D48: =IF(E48<0,-E48,0) -> 0 | E48: =IFERROR(VLOOKUP(B48,$A$235:$B$357,2,FALSE),0) -> 0
B49: 2110102400 - OSDE | C49: =IF(E49>0,E49,0) -> 0 | D49: =IF(E49<0,-E49,0) -> 0 | E49: =IFERROR(VLOOKUP(B49,$A$235:$B$357,2,FALSE),0) -> 0
B50: 2110100900 ESTUDIO CORTES | C50: =IF(E50>0,E50,0) -> 0 | D50: =IF(E50<0,-E50,0) -> 0 | E50: =IFERROR(VLOOKUP(B50,$A$235:$B$357,2,FALSE),0) -> 0
B51: 2110101500 VENEZIA AUTOS SA | C51: =IF(E51>0,E51,0) -> 0 | D51: =IF(E51<0,-E51,0) -> 0 | E51: =IFERROR(VLOOKUP(B51,$A$235:$B$357,2,FALSE),0) -> 0
B52: 2110101800 TRANSPORTES FURLONG ARG. S.A | C52: =IF(E52>0,E52,0) -> 0 | D52: =IF(E52<0,-E52,0) -> 0 | E52: =IFERROR(VLOOKUP(B52,$A$235:$B$357,2,FALSE),0) -> 0
B53: 2110105400 MERCOVIA S.A. | C53: =IF(E53>0,E53,0) -> 0 | D53: =IF(E53<0,-E53,0) -> 0 | E53: =IFERROR(VLOOKUP(B53,$A$235:$B$357,2,FALSE),0) -> 0
B54: 2110106800 OKINET SRL | C54: =IF(E54>0,E54,0) -> 0 | D54: =IF(E54<0,-E54,0) -> 0 | E54: =IFERROR(VLOOKUP(B54,$A$235:$B$357,2,FALSE),0) -> 0
B55: 2110108900 LA MERIDIONAL S.A. | C55: =IF(E55>0,E55,0) -> 0 | D55: =IF(E55<0,-E55,0) -> 841654.84 | E55: =IFERROR(VLOOKUP(B55,$A$235:$B$357,2,FALSE),0) -> -841654.84
B56: 2110115100 GIULI SERGIO ALBERTO | C56: =IF(E56>0,E56,0) -> 0 | D56: =IF(E56<0,-E56,0) -> 0 | E56: =IFERROR(VLOOKUP(B56,$A$235:$B$357,2,FALSE),0) -> 0
B57: 2110116700 - CARLOS ALEJANDRO DUMA | C57: =IF(E57>0,E57,0) -> 0 | D57: =IF(E57<0,-E57,0) -> 0 | E57: =IFERROR(VLOOKUP(B57,$A$235:$B$357,2,FALSE),0) -> 0
B58: 2110118000 MANGGINI PABLO Y ULISES S.H | C58: =IF(E58>0,E58,0) -> 0 | D58: =IF(E58<0,-E58,0) -> 6500 | E58: =IFERROR(VLOOKUP(B58,$A$235:$B$357,2,FALSE),0) -> -6500
B59: 2110120600 QBE SEGUROS LA BUENOS AIRES S.A. | C59: =IF(E59>0,E59,0) -> 0 | D59: =IF(E59<0,-E59,0) -> 13023315 | E59: =IFERROR(VLOOKUP(B59,$A$235:$B$357,2,FALSE),0) -> -13023315
... B108: 2116400000 Autovia del Mercosur | C108: =IF(E108>0,E108,0) -> 0 | D108: =IF(E108<0,-E108,0) -> 3423889.6 | E108: =IFERROR(VLOOKUP(B108,$A$235:$B$357,2,FALSE),0) -> -3423889.6
E109: =IFERROR(VLOOKUP(B109,$A$235:$B$357,2,FALSE),0) -> 0 | F109: =SUM(E49:E108) -> -1.828349e+08
A110: PATRIMONIO NETO | E110: =IFERROR(VLOOKUP(B110,$A$235:$B$357,2,FALSE),0) -> 0
B111: 3310000000 RNA EJERCICIO ANTERIOR | C111: =IF(E111>0,-E111,0) -> 0 | D111: =IF(E111<0,-E111,0) -> 9.7986987e+08 | E111: =IFERROR(VLOOKUP(B111,$A$235:$B$357,2,FALSE),0) -> -9.7986987e+08
B112: 3320000000 RESULTADOS DEL EJERCICIOS | C112: =IF(E112>0,E112,0) -> 8.4748304e+08 | D112: =IF(E112<0,-E112,0) -> 0 | E112: =IFERROR(VLOOKUP(B112,$A$235:$B$357,2,FALSE),0) -> 8.4748304e+08
E113: =IFERROR(VLOOKUP(B113,$A$235:$B$357,2,FALSE),0) -> 0 | F113: =SUM(E111:E112) -> -1.3238683e+08
A114: RESULTADOS | E114: =IFERROR(VLOOKUP(B114,$A$235:$B$357,2,FALSE),0) -> 0
B115: 4110100000 SERVICIOS PRESTADOS | C115: =IF(E115>0,E115,0) -> 0 | D115: =IF(E115<0,-E115,0) -> 31238043 | E115: =IFERROR(VLOOKUP(B115,$A$235:$B$357,2,FALSE),0) -> -31238043
B116: 4120500000 INTERESES GANADOS | C116: =IF(E116>0,E116,0) -> 0 | D116: =IF(E116<0,-E116,0) -> 0 | E116: =IFERROR(VLOOKUP(B116,$A$235:$B$357,2,FALSE),0) -> 0
B117: 4231100000 RESULTADO POR TENENCIA FCI | C117: =IF(E117>0,E117,0) -> 0 | D117: =IF(E117<0,-E117,0) -> 6015262.3 | E117: =IFERROR(VLOOKUP(B117,$A$235:$B$357,2,FALSE),0) -> -6015262.3
B118: 4120100000 RECUPERO DE GASTOS | C118: =IF(E118>0,E118,0) -> 0 | D118: =IF(E118<0,-E118,0) -> 0 | E118: =IFERROR(VLOOKUP(B118,$A$235:$B$357,2,FALSE),0) -> 0
B119: 412 OTROS INGRESOS | C119: =IF(E119>0,E119,0) -> 0 | D119: =IF(E119<0,-E119,0) -> 0 | E119: =IFERROR(VLOOKUP(B119,$A$235:$B$357,2,FALSE),0) -> 0
B120: 4120300000 VENTA RODADO | C120: =IF(E120>0,E120,0) -> 0 | D120: =IF(E120<0,-E120,0) -> 0 | E120: =IFERROR(VLOOKUP(B120,$A$235:$B$357,2,FALSE),0) -> 0
B121: 4120200000 DIFERENCIA DE COTIZACION | C121: =IF(E121>0,E121,0) -> 0 | D121: =IF(E121<0,-E121,0) -> 0 | E121: =IFERROR(VLOOKUP(B121,$A$235:$B$357,2,FALSE),0) -> 0
B122: 4120500000 INTERESES GANADOS | C122: =IF(E122>0,E122,0) -> 0 | D122: =IF(E122<0,-E122,0) -> 0 | E122: =IFERROR(VLOOKUP(B122,$A$235:$B$357,2,FALSE),0) -> 0
B123: 4210100000 GASTOS GENERALES | C123: =IF(E123>0,E123,0) -> 0 | D123: =IF(E123<0,-E123,0) -> 0 | E123: =IFERROR(VLOOKUP(B123,$A$235:$B$357,2,FALSE),0) -> 0
B124: 4210200000 MOVILIDAD Y VIÁTICOS | C124: =IF(E124>0,E124,0) -> 672542.18 | D124: =IF(E124<0,-E124,0) -> 0 | E124: =IFERROR(VLOOKUP(B124,$A$235:$B$357,2,FALSE),0) -> 672542.18
B125: 4210300000 SUELDOS | C125: =IF(E125>0,E125,0) -> 1.9776938e+08 | D125: =IF(E125<0,-E125,0) -> 0 | E125: =IFERROR(VLOOKUP(B125,$A$235:$B$357,2,FALSE),0) -> 1.9776938e+08
B126: 4210400000 HONORARIOS PROFESIONALES | C126: =IF(E126>0,E126,0) -> 33850774 | D126: =IF(E126<0,-E126,0) -> 0 | E126: =IFERROR(VLOOKUP(B126,$A$235:$B$357,2,FALSE),0) -> 33850774
... B142: 4211700000 GASTOS CAPACITACIÓN | C142: =IF(E142>0,E142,0) -> 0 | D142: =IF(E142<0,-E142,0) -> 0 | E142: =IFERROR(VLOOKUP(B142,$A$235:$B$357,2,FALSE),0) -> 0
C143: =IF(E143>0,E143,0) -> 0 | D143: =IF(E143<0,-E143,0) -> 0 | E143: =IFERROR(VLOOKUP(B143,$A$235:$B$357,2,FALSE),0) -> 0
B144: 4211900000 CATERING | C144: =IF(E144>0,E144,0) -> 0 | D144: =IF(E144<0,-E144,0) -> 0 | E144: =IFERROR(VLOOKUP(B144,$A$235:$B$357,2,FALSE),0) -> 0
B145: 4212100000 FLETES | C145: =IF(E145>0,E145,0) -> 0 | D145: =IF(E145<0,-E145,0) -> 0 | E145: =IFERROR(VLOOKUP(B145,$A$235:$B$357,2,FALSE),0) -> 0
B146: 4212200000 LEGALIZACIONES | C146: =IF(E146>0,E146,0) -> 0 | D146: =IF(E146<0,-E146,0) -> 0 | E146: =IFERROR(VLOOKUP(B146,$A$235:$B$357,2,FALSE),0) -> 0
B147: 421230000 GASTOS VARIOS PERSONAL | C147: =IF(E147>0,E147,0) -> 0 | D147: =IF(E147<0,-E147,0) -> 0 | E147: =IFERROR(VLOOKUP(B147,$A$235:$B$357,2,FALSE),0) -> 0
B148: 4212400000 AUTÓNOMOS DIRECTORES | C148: =IF(E148>0,E148,0) -> 383019.22 | D148: =IF(E148<0,-E148,0) -> 0 | E148: =IFERROR(VLOOKUP(B148,$A$235:$B$357,2,FALSE),0) -> 383019.22
B149: 4212500000 AMORTIZACIONES | C149: =IF(E149>0,E149,0) -> 17397088 | D149: =IF(E149<0,-E149,0) -> 0 | E149: =IFERROR(VLOOKUP(B149,$A$235:$B$357,2,FALSE),0) -> 17397088
B150: 4212600000 AGUA | C150: =IF(E150>0,E150,0) -> 0 | D150: =IF(E150<0,-E150,0) -> 0 | E150: =IFERROR(VLOOKUP(B150,$A$235:$B$357,2,FALSE),0) -> 0
B151: 4212700000 ALQUILER FOTOCOPIADORA | C151: =IF(E151>0,E151,0) -> 1228669.4 | D151: =IF(E151<0,-E151,0) -> 0 | E151: =IFERROR(VLOOKUP(B151,$A$235:$B$357,2,FALSE),0) -> 1228669.4
B152: 4212800000 TASA AFIP | C152: =IF(E152>0,E152,0) -> 0 | D152: =IF(E152<0,-E152,0) -> 0 | E152: =IFERROR(VLOOKUP(B152,$A$235:$B$357,2,FALSE),0) -> 0
B153: 4212900000 TASA IGJ | C153: =IF(E153>0,E153,0) -> 0 | D153: =IF(E153<0,-E153,0) -> 0 | E153: =IFERROR(VLOOKUP(B153,$A$235:$B$357,2,FALSE),0) -> 0
B154: 4212000000 MANTENIMIENTO | C154: =IF(E154>0,E154,0) -> 1379539 | D154: =IF(E154<0,-E154,0) -> 0 | E154: =IFERROR(VLOOKUP(B154,$A$235:$B$357,2,FALSE),0) -> 1379539
B155: 4213000000 ALQUILER OFICINA MÓVIL | C155: =IF(E155>0,E155,0) -> 0 | D155: =IF(E155<0,-E155,0) -> 0 | E155: =IFERROR(VLOOKUP(B155,$A$235:$B$357,2,FALSE),0) -> 0
... B179: 4221500000 REFRIGERIOS | C179: =IF(E179>0,E179,0) -> 0 | D179: =IF(E179<0,-E179,0) -> 0 | E179: =IFERROR(VLOOKUP(B179,$A$235:$B$357,2,FALSE),0) -> 0
D180: =IF(E180<0,-E180,0) -> 0 | E180: =IFERROR(VLOOKUP(B180,$A$235:$B$357,2,FALSE),0) -> 0
B181: 4221700100 FLETES | C181: =IF(E181>0,E181,0) -> 0 | D181: =IF(E181<0,-E181,0) -> 0 | E181: =IFERROR(VLOOKUP(B181,$A$235:$B$357,2,FALSE),0) -> 0
B182: 4221700200 GTOS PLAYA ESTADIAS | C182: =IF(E182>0,E182,0) -> 0 | D182: =IF(E182<0,-E182,0) -> 0 | E182: =IFERROR(VLOOKUP(B182,$A$235:$B$357,2,FALSE),0) -> 0
B183: 4221800000 MULTAS | C183: =IF(E183>0,E183,0) -> 873100 | D183: =IF(E183<0,-E183,0) -> 0 | E183: =IFERROR(VLOOKUP(B183,$A$235:$B$357,2,FALSE),0) -> 873100
B184: 4221900000 GASTOS DE REPRESENTACIÓN | C184: =IF(E184>0,E184,0) -> 219472.57 | D184: =IF(E184<0,-E184,0) -> 0 | E184: =IFERROR(VLOOKUP(B184,$A$235:$B$357,2,FALSE),0) -> 219472.57
B185: 4222000000 GASTOS DE LOGÍSTICA | C185: =IF(E185>0,E185,0) -> 624483.29 | D185: =IF(E185<0,-E185,0) -> 0 | E185: =IFERROR(VLOOKUP(B185,$A$235:$B$357,2,FALSE),0) -> 624483.29
B186: 4222100000 ALQUILER DE AUTOS | C186: =IF(E186>0,E186,0) -> 0 | D186: =IF(E186<0,-E186,0) -> 0 | E186: =IFERROR(VLOOKUP(B186,$A$235:$B$357,2,FALSE),0) -> 0
B187: 4222200000 ACCIDENTES | C187: =IF(E187>0,E187,0) -> 0 | D187: =IF(E187<0,-E187,0) -> 0 | E187: =IFERROR(VLOOKUP(B187,$A$235:$B$357,2,FALSE),0) -> 0
B188: 4222300000 SINIESTROS | C188: =IF(E188>0,E188,0) -> 0 | D188: =IF(E188<0,-E188,0) -> 0 | E188: =IFERROR(VLOOKUP(B188,$A$235:$B$357,2,FALSE),0) -> 0
B189: 4222400000 DONACIONES | C189: =IF(E189>0,E189,0) -> 2400000 | D189: =IF(E189<0,-E189,0) -> 0 | E189: =IFERROR(VLOOKUP(B189,$A$235:$B$357,2,FALSE),0) -> 2400000
B190: 4222900000 ROPA DE TRABAJO | C190: =IF(E190>0,E190,0) -> 0 | D190: =IF(E190<0,-E190,0) -> 0 | E190: =IFERROR(VLOOKUP(B190,$A$235:$B$357,2,FALSE),0) -> 0
B191: 4222500000 ESTIBAJES | C191: =IF(E191>0,E191,0) -> 0 | D191: =IF(E191<0,-E191,0) -> 0 | E191: =IFERROR(VLOOKUP(B191,$A$235:$B$357,2,FALSE),0) -> 0
B192: 4222600000 ALQUILER DPTO | C192: =IF(E192>0,E192,0) -> 0 | D192: =IF(E192<0,-E192,0) -> 0 | E192: =IFERROR(VLOOKUP(B192,$A$235:$B$357,2,FALSE),0) -> 0
... B214: 4230400000 INTERESES RESARCITORIOS | C214: =IF(E214>0,E214,0) -> 18860.69 | D214: =IF(E214<0,-E214,0) -> 0 | E214: =IFERROR(VLOOKUP(B214,$A$235:$B$357,2,FALSE),0) -> 18860.69
B215: 4230500000 LEASING | C215: =IF(E215>0,E215,0) -> 0 | D215: =IF(E215<0,-E215,0) -> 0 | E215: =IFERROR(VLOOKUP(B215,$A$235:$B$3703,2,FALSE),0) -> 0
B216: 4230700000 EMBARGO RADICACION VEHICULAR | C216: =IF(E216>0,E216,0) -> 0 | D216: =IF(E216<0,-E216,0) -> 0 | E216: =IFERROR(VLOOKUP(B216,$A$235:$B$3703,2,FALSE),0) -> 0
B217: 4230800000 IMPUESTOS VARIOS | C217: =IF(E217>0,E217,0) -> 0 | D217: =IF(E217<0,-E217,0) -> 0 | E217: =IFERROR(VLOOKUP(B217,$A$235:$B$3703,2,FALSE),0) -> 0
B218: 4230900000 IMP. AL CHEQUE | C218: =IF(E218>0,E218,0) -> 0 | D218: =IF(E218<0,-E218,0) -> 0 | E218: =IFERROR(VLOOKUP(B218,$A$235:$B$3703,2,FALSE),0) -> 0
B219: 4230600000 SINIESTROS CONVENIO HSBC | C219: =IF(E219>0,E219,0) -> 0 | D219: =IF(E219<0,-E219,0) -> 0 | E219: =IFERROR(VLOOKUP(B219,$A$235:$B$3703,2,FALSE),0) -> 0
B220: 4240100000 COMBUSTIBLE | C220: =IF(E220>0,E220,0) -> 0 | D220: =IF(E220<0,-E220,0) -> 0 | E220: =IFERROR(VLOOKUP(B220,$A$235:$B$3703,2,FALSE),0) -> 0
B221: 4212800000 TASAS AFIP | C221: =IF(E221>0,E221,0) -> 0 | D221: =IF(E221<0,-E221,0) -> 0 | E221: =IFERROR(VLOOKUP(B221,$A$235:$B$3703,2,FALSE),0) -> 0
B222: 4231200000 INTERESES FINANCIEROS | C222: =IF(E222>0,E222,0) -> 0 | D222: =IF(E222<0,-E222,0) -> 0 | E222: =IFERROR(VLOOKUP(B222,$A$235:$B$3703,2,FALSE),0) -> 0
F223: =SUM(E115:E222) -> 5.7449534e+08 | G223: =+F223+EERR!C30 -> 0
C224: =SUM(C4:C223) -> 1.7363562e+09 | D224: =SUM(D4:D223) -> 1.7363562e+09 | E224: Diferencia | F224: =C224-D224 -> 0
A235: 1110100330 FONDO FIJO BS. AS. | B235: 4878940.2
A236: 1110100420 BANCO FRANCES C/C | B236: 219745.62
A237: 1120100100 FORD | B237: 228102.13
A238: 1120100400 TRANSPORTES FURLONG S.A. AR | B238: -4.0832693e+08
A239: 1120101300 VOLKSWAGEN ARGENTINA S.A. | B239: 725484.5
A240: 1120138000 STELLANTIS AUTOMOVILES DE ARGENTINA S. A | B240: 156195.52
A241: 1140300100 ANTICIPO A PDT | B241: 28186194
A242: 1140600300 PRESTAMO A. VELASCO | B242: 1600000
A243: 1140601100 PRESTAMO LORENA ALVES | B243: 700000
A244: 1140601300 PRESTAMO CUBA | B244: 200000
A245: 1140900700 SEGUROS A DEV. ZURICH ASEG. S.A. | B245: 16566949
A246: 1140900800 SEGUROS A DEV. ARG LA MERIDIONAL | B246: 2883.36
...

Sheet EESP
A5: TRANSPORTES FURLONG S.A
A7: Al 31 de Julio del 2026
A9: Estado de Situación Patrimonial en Pesos
F13: 46234 | G13: 38717 | L13: =+F13 -> 46234 | M13: 38717
B14: ACTIVO: | I14: PASIVO
C15: ACTIVO CORRIENTE | I15: PASIVO CORRIENTE
D16: Caja y bancos (Nota 4.a) | F16: =+Activo!F18 -> 5098685.8 | J16: Deudas
D17: Inversiones temporarias (Nota 4.b) | F17: =+Activo!F23 -> 18111832 | K17: Comerciales (Nota 4.e) | L17: =+Pasivo!E10 -> 5.7625807e+08
D18: Créditos por ventas (Nota 4.c) | F18: =+Activo!F30 -> 1109782.1 | K18: Remuneraciones y cs.sociales (Nota 4.f) | L18: =+Pasivo!E16 -> 13528940
D19: Otros Créditos (Nota 4.d) | F19: =+Activo!F53 -> 47256026 | K19: Cargas fiscales (Nota 4.g) | L19: =+Pasivo!E24 -> 1374822.4
K20: Otras Deudas (Nota 4.h) | L20: =+Pasivo!E33 -> 0
C23: Total del Activo corriente | F23: =SUM(F16:F19) -> 71576326 | I23: Total del Pasivo Corriente | L23: =SUM(L17:L22) -> 5.9116183e+08
I24: Total del Pasivo | L24: =+L23 -> 5.9116183e+08
C27: ACTIVO NO CORRIENTE
D28: Bienes de uso (Anexo I) | F28: =+'Anexo I'!K21 -> 77476986 | I28: PATRIMONIO NETO (Según estado respec.) | L28: =+EEPN!J17 -> -4.4210852e+08
C30: Total del Activo no corriente | F30: =SUM(F28:F29) -> 77476986 | L30: =+L28 -> -4.4210852e+08
C32: Total del Activo | F32: =+F23+F30-0.02 -> 1.4905331e+08 | I32: Total del Pasivo y Patrimonio Neto | L32: =+L24+L30 -> 1.4905331e+08
A33: Las notas y anexos adjuntos forman parte integrante de los estados contables.
A34: Informe profesional por separado.
E39: Miguel Ángel Alonso | K39: Tomas Furlong
E40: Contador Público (UCA) | K40: Transportes Furlong S.A.
E41: C.P.C.E.C.A.B.A. Tº176 Fº3 | K41: Apoderado

Sheet EERR
A4: TRANSPORTES FURLONG S.A
A6: =+EESP!A7 -> Al 31 de Julio del 2026
A8: Estado de Resultados
C12: =+EESP!F13 -> 46234 | D12: =+EESP!G13 -> 38717
A15: Ingresos por servicios prestados | C15: =+SALDOS!D115 -> 31238043
A17: Gastos de comercialización (Anexo II) | C17: =+'Anexo II'!E85 -> 5.3718832e+08
A18: Gastos de administración (Anexo II) | C18: =+'Anexo II'!D85 -> 66231303
A19: Gastos de financieros (Anexo II) | C19: =+'Anexo II'!F85 -> 8329025.4
A21: Subtotal | C21: =+C15-C17-C18-C19 -> -5.8051061e+08
A22: Resultado venta bienes de uso | C22: =+SALDOS!D120 -> 0
A23: Recupero de gastos | C23: =+SALDOS!D118 -> 0
A24: Diferencia de cotización | C24: =+SALDOS!C121-SALDOS!D121 -> 0
A25: Intereses | C25: =+SALDOS!D117+SALDOS!D122+SALDOS!D116 -> 6015262.3
A26: Otros ingresos | C26: =+SALDOS!D204 -> 0
A27: Ganancia antes de impuesto | C27: =+C21+C22-C24+C23+C25+C26 -> -5.7449534e+08
A28: Impuesto a las Ganancias | C28: 0
A30: Ganancia (Pérdida) del ejercicio | C30: =+C27-C28 -> -5.7449534e+08
A34: Las notas y anexos adjuntos forman parte integrante de los estados contables.
A35: Informe profesional por separado.
A40: =+EESP!E39 -> Miguel Ángel Alonso | C40: =+EESP!K39 -> Tomas Furlong
A41: =+EESP!E40 -> Contador Público (UCA) | C41: =+EESP!K40 -> Transportes Furlong S.A.
A42: =+EESP!E41 -> C.P.C.E.C.A.B.A. Tº176 Fº3 | C42: Apoderado

Sheet EEPN
A1: =+EESP!A5 -> TRANSPORTES FURLONG S.A
A2: =+EESP!A7 -> Al 31 de Julio del 2026 | B2: =+EESP!A7 -> Al 31 de Julio del 2026
A3: Estado de Evolución del Patrimonio Neto
J5: =+EESP!F13 -> 46234 | K5: =+EESP!G13 -> 38717
B6: CONCEPTO | C6: Aportes de los propietarios | F6: Ganancias | G6: Reservadas | I6: Resultados | J6: Total del | K6: Total del
C7: Capital | D7: Ajuste | E7: Total de | F7: Reserva | G7: Otras | H7: Aportes | I7: no | J7: patrimonio | K7: patrimonio
D8: de Capital | E8: Capital | F8: legal | G8: reservas | H8: Irrevocables | I8: asignados | J8: neto | K8: neto
C9: $ | D9: $ | E9: $ | F9: $ | G9: $ | I9: $ | J9: $ | K9: $
B11: Saldos al inicio del ejercicio | C11: 0 | D11: 0 | E11: =+C11+D11 -> 0 | F11: 0 | G11: 0 | H11: 0 | I11: =+SALDOS!D111-SALDOS!C112 -> 1.3238683e+08 | J11: =+I11 -> 1.3238683e+08
B13: Ganancia (Pérdida) del ejercicio | I13: =+EERR!C30 -> -5.7449534e+08 | J13: =+I13 -> -5.7449534e+08
B14: Reasignación casa matriz | I14: 0 | J14: =+I14 -> 0
B17: Total al 31.7.2026 | C17: =SUM(C11:C16) -> 0 | D17: =SUM(D11:D16) -> 0 | E17: =SUM(E11:E16) -> 0 | F17: =SUM(F11:F16) -> 0 | G17: =SUM(G11:G16) -> 0 | H17: =SUM(H11:H16) -> 0 | I17: =SUM(I11:I16) -> -4.4210852e+08 | J17: =SUM(J11:J16) -> -4.4210852e+08 | K17: =+#REF!+K13 -> #REF!
B18: Total al 31.12.05 | E18: =+C18+D18 -> 0 | G18: 0 | I18: 0 | J18: =+E18 -> 0 | K18: =+G18 -> 0
B20: Las notas y anexos adjuntos forman parte integrante de los estados contables.
B21: Informe profesional por separado.
C25: =+EESP!E39 -> Miguel Ángel Alonso | H25: =+EERR!C40 -> Tomas Furlong
C26: =+EESP!E40 -> Contador Público (UCA) | H26: =+EERR!C41 -> Transportes Furlong S.A.
C27: =+EESP!E41 -> C.P.C.E.C.A.B.A. Tº176 Fº3 | H27: =+EERR!C42 -> Apoderado

Sheet Activo
B1: NOTA 4: | E1: COMPOSICION DE LOS RUBROS
B3: Al 31 de Julio de 2026 - cifras expresadas en Pesos
F6: =+EESP!F13 -> 46234 | H6: 38717
B7: ACTIVO
B8: Activo Corriente
B9: a. | C9: Caja y bancos
D10: - Caja | F10: 0
D11: - Fondo Fijo | F11: =+SALDOS!C5-SALDOS!D5 -> 4878940.2
D12: - Fondo Fijo SENASA | F12: =+SALDOS!E6 -> 0
D13: - Fondo Fijo Adelantos PDT | F13: =+SALDOS!E8 -> 0
D14: - Banco Francés c/c | F14: =+SALDOS!C7-SALDOS!D7 -> 219745.62
D15: - Valores a Depositar | F15: 0
D16: - Efectivo Casa Matriz | F16: 0
D17: - Cheques no depositados | F17: =+SALDOS!C223 -> 0
F18: =SUM(F10:F17) -> 5098685.8
B20: b. | C20: Inversiones temporarias
D21: - Plazo Fijo | F21: =+SALDOS!C28 -> 0
D22: - Fondo Comun de Inversión BBVA | F22: =+SALDOS!C27 -> 18111832
F23: =+F22+F21 -> 18111832
B27: c. | C27: Creditos por Ventas
D28: - Deudores por ventas | F28: =+SALDOS!C12+SALDOS!C13+SALDOS!C9+SALDOS!C14+SALDOS!C15 -> 1109782.1
D29: - Anticipo a proveedores | F29: 0
F30: =SUM(F28:F29) -> 1109782.1
B32: d. | C32: Otros créditos
D33: - Transportes Furlong Cba. | F33: 0
D34: - Adelantos Tomás Furlong | F34: 0
D35: - Adelanto de sueldos | F35: =+SALDOS!C17 -> 0
D36: - Adelantos PDT | F36: =+SALDOS!C16 -> 28186194
D37: - Adelanto de gastos | F37: 0
D38: - Adelanto de sueldos | F38: 0
D39: - Anticipo Combustible Velasco | F39: 0
D40: - Adelanto SAC | F40: 0
D41: - Adelanto al personal | F41: =+SALDOS!C20+SALDOS!C22+SALDOS!C23+SALDOS!C19+SALDOS!C21 -> 2500000
D42: - Anticipo a proveedores | F42: 0
D43: - Gastos a recuperar | F43: 0
D44: - Prov. Fc a recibir transportistas | F44: 0
D45: - Retenciones IIBB | F45: 0
D46: - Retenciones ganancias | F46: 0
D47: - Retenciones suss | F47: 0
D48: - Prestamos al personal | F48: 0
D49: - Crédito Imp. Ley 25413 | F49: 0
D50: - Fondo fijo a rendir | F50: 0
D51: - Intereses a Devengar Plazo Fijo | F51: =-SALDOS!D29 -> 0
D52: - Seguros a Devengar | F52: =+SALDOS!C24+SALDOS!C25+SALDOS!C26 -> 16569832
F53: =SUM(F33:F52) -> 47256026

Sheet Pasivo
E1: =+Activo!F6 -> 46234 | G1: 31.03.04 | K1: 31.03.03 | L1: =+EESP!G13 -> 38717
A2: Pasivo
A3: Pasivo Corriente
A4: e. | B4: Deudas comerciales
C5: - Anticipos de clientes | E5: 0
C6: - Proveedores | E6: =-SUM(SALDOS!E48:E71)-SUM(SALDOS!E81:E108)-0.02 -> 40549635
C7: - Adelanto casa matriz | E7: =+SALDOS!D80+SALDOS!D10 -> 5.3570843e+08
C8: - Previsiones | E8: 0
C9: - Cheques Emitidos | E9: 0
E10: =SUM(E5:E9) -> 5.7625807e+08
A12: f. | B12: Remuneraciones y cs. Sociales
C13: - Suss a pagar | E13: =+SALDOS!D74 -> 13528940 | G13: 70 | K13: 0
C14: - Sueldos a pagar | E14: =+SALDOS!D73 -> 0
C15: - Indemnización a pagar | E15: 0
E16: =SUM(E13:E15) -> 13528940
G17: =SUM(G13:G16) -> 70 | K17: =SUM(#REF!) -> #REF!
A19: g. | B19: Cargas fiscales
C20: - Plan mis Facilidades Bs Personales | E20: =+SALDOS!D78 -> 587820.73
C21: - Intereses a devengar | E21: =-SALDOS!C79 -> -59671.53
C22: - Sicore a pagar | E22: =+SALDOS!D75 -> 846673.24
C23: - Bs. Pers. Acc. Y Participaciones a Pagar | E23: 0
E24: =SUM(E20:E23) -> 1374822.4
A26: h. | B26: Otras Deudas
C27: - Acuerdos CNRT a pagar | E27: =+SALDOS!D83 -> 0
C28: - Convenio HSBC | E28: 0
C29: - Prov. Multas a pagar | E29: 0
C30: - Provisión Siniestro Ford | E30: 0
C31: - Préstamo Carlos Furlong | E31: =+SALDOS!D18 -> 0
C32: - Préstamo Lorena Alves | E32: =+SALDOS!D19 -> 0
E33: =SUM(E27:E32) -> 0
A35: Las notas y anexos adjuntos forman parte integrante de los estados contables.
A36: Informe profesional por separado.
C43: Miguel Ángel Alonso | E43: Tomas Furlong
C44: Contador Público (UCA) | E44: Transportes Furlong S.A.
C45: C.P.C.E.C.A.B.A. Tº176 Fº3 | E45: Apoderado

Sheet Anexo I
A4: B I E N E S D E U S O
A5: =+Activo!B3 -> Al 31 de Julio de 2026 - cifras expresadas en Pesos
B8: VALOR DE ORIGEN | F8: DEPRECIACIONES
B9: VALORES AL | E9: VALORES AL | F9: ACUMULADAS | G9: DEL EJERCICIO | J9: ACUMULADAS | K9: NETO
A10: CONCEPTO | B10: COMIENZO DEL | C10: AUMENTOS | D10: DISMINUCIONES | E10: CIERRE DEL | F10: AL INICIO DEL | G10: BAJAS | H10: ALIC | I10: MONTO | J10: AL CIERRE DEL | K10: RESULTANTE
B11: EJERCICIO | E11: EJERCICIO | F11: EJERCICIO | J11: EJERCICIO | K11: =+EESP!F13 -> 46234
B12: $ | C12: $ | D12: $ | E12: $ | F12: $ | G12: $ | I12: $ | J12: $ | K12: $
A14: Software | B14: 754089.29 | C14: =+E14-B14 -> 0 | D14: 0 | E14: =+B14 -> 754089.29 | F14: 754089.29 | G14: 0 | H14: 0.2 | I14: =+J14-F14 -> 0 | J14: =+SALDOS!D39 -> 754089.29 | K14: =+E14-J14 -> 0
A15: Hardware | B15: 349454.86 | C15: =+E15-B15 -> 0 | D15: 0 | E15: =+B15 -> 349454.86 | F15: 349454.86 | G15: 0 | H15: 0.2 | I15: =+J15-F15 -> 0 | J15: =+SALDOS!D43 -> 349454.86 | K15: =+E15-J15 -> 0
A16: Computadoras | B16: 19271906 | C16: =+SALDOS!C34-'Anexo I'!B16 -> 0 | D16: 0 | E16: =+B16+C16 -> 19271906 | F16: 16777769 | G16: 0 | H16: 0.2 | I16: =+J16-F16 -> 602032.91 | J16: =+SALDOS!D44 -> 17379802 | K16: =+E16-J16 -> 1892103.4
A17: Equipos | B17: 2833073.7 | C17: =+E17-B17 -> 0 | D17: 0 | E17: =+B17 -> 2833073.7 | F17: 2833073.7 | G17: 0 | H17: 0.2 | I17: =+J17-F17 -> 0 | J17: =+SALDOS!D41 -> 2833073.7 | K17: =+E17-J17 -> 0
A18: Muebles y Utiles | B18: 2913406.5 | C18: 0 | D18: 0 | E18: =+B18+C18 -> 2913406.5 | F18: 2735631.6 | G18: 0 | H18: 0.1 | I18: =+J18-F18 -> 25925.5 | J18: =+SALDOS!D40 -> 2761557.1 | K18: =+E18-J18 -> 151849.37
A19: Instalaciones | B19: 9934406.7 | C19: =+E19-B19 -> 0 | D19: 0 | E19: =+B19 -> 9934406.7 | F19: 9934406.7 | G19: 0 | H19: 10% | I19: =+J19-F19 -> 0 | J19: =+SALDOS!D42 -> 9934406.7 | K19: =+E19-J19 -> 0
A20: Rodados | B20: 1.6624361e+08 | C20: 0 | D20: 0 | E20: =+B20+C20-D20 -> 1.6624361e+08 | F20: 74041451 | H20: 0.2 | I20: =+J20-F20 -> 16769130 | J20: =+SALDOS!D45 -> 90810581 | K20: =+E20-J20 -> 75433033
A21: =+EEPN!B17 -> Total al 31.7.2026 | B21: =SUM(B14:B20) -> 2.0229995e+08 | C21: =SUM(C14:C20) -> 0 | D21: =SUM(D14:D20) -> 0 | E21: =SUM(E14:E20) -> 2.0229995e+08 | F21: =SUM(F14:F20) -> 1.0742588e+08 | G21: =SUM(G14:G20) -> 0 | I21: =SUM(I14:I20) -> 17397088 | J21: =SUM(J14:J20) -> 1.2482296e+08 | K21: =SUM(K14:K20) -> 77476986
A23: Las notas y anexos adjuntos forman parte integrante de los estados contables.
A24: Informe profesional por separado.
C27: =+EEPN!C25 -> Miguel Ángel Alonso | I27: =+EEPN!H25 -> Tomas Furlong
C28: =+EEPN!C26 -> Contador Público (UCA) | I28: =+EEPN!H26 -> Transportes Furlong S.A.
C29: =+EEPN!C27 -> C.P.C.E.C.A.B.A. Tº176 Fº3 | I29: =+EEPN!H27 -> Apoderado

Sheet Anexo II
G1: ANEXO II
A5: Información Requerida por el Art. 64 Inc. b) de la Ley 19.550 | F5: Anexo II
A6: =+Activo!B3 -> Al 31 de Julio de 2026 - cifras expresadas en Pesos
C8: TOTALES | D8: GASTOS | E8: GASTOS | F8: GASTOS | G8: TOTALES
B9: CONCEPTOS | C9: AL | D9: DE | E9: DE | G9: AL
C10: =+EESP!F13 -> 46234 | D10: ADMINISTRACION | E10: COMERCIALIZACION | F10: FINANCIEROS | G10: 31.03.02
B11: Amortizaciones | C11: =SUM(D11:F11) -> 17397088 | D11: =+SALDOS!C149 -> 17397088 | E11: 0 | F11: 0
B12: Accidentes | C12: =SUM(D12:F12) -> 0 | D12: 0 | E12: =+SALDOS!C186 -> 0 | F12: 0
B13: Acuerdo Seclo | C13: =SUM(D13:F13) -> 0 | D13: 0 | E13: =+SALDOS!C156 -> 0 | F13: 0
B14: Adelanto Viaje | C14: =SUM(D14:F14) -> 0 | D14: 0 | E14: =+SALDOS!C208 -> 0 | F14: 0
B15: Alquiler de cochera | C15: =SUM(D15:F15) -> 0 | D15: 0 | E15: =+SALDOS!C194 -> 0 | F15: 0
B16: Mantenimiento | C16: =SUM(D16:F16) -> 1379539 | D16: =+SALDOS!C154+SALDOS!C131 -> 1379539 | E16: =+SALDOS!C191+SALDOS!C193+SALDOS!C150-SALDOS!D150 -> 0 | F16: 0
B17: Adicional obra social | C17: =SUM(D17:F17) -> 0 | D17: 0 | E17: =+SALDOS!C129 -> 0 | F17: 0
B18: Autonomos directores | C18: =SUM(D18:F18) -> 0 | D18: =+SALDOS!C147 -> 0 | E18: 0 | F18: 0
B19: Librería | C19: =SUM(D19:F19) -> 521371.32 | D19: 0 | E19: =+SALDOS!C127 -> 521371.32 | F19: 0
B20: Publicidad | C20: =SUM(D20:F20) -> 0 | D20: 0 | E20: =+SALDOS!C199 -> 0 | F20: 0
B21: Gastos varios | C21: =SUM(D21:F21) -> 321043.66 | D21: 0 | E21: =+SALDOS!C177 -> 321043.66 | F21: 0
B22: Catering | C22: =SUM(D22:F22) -> 0 | D22: 0 | E22: =+SALDOS!C143 -> 0 | F22: 0
B23: Cesión de Derechos | C23: =SUM(D23:F23) -> 0 | D23: =+SALDOS!C207 -> 0 | E23: 0 | F23: 0
B24: Combustible | C24: =SUM(D24:F24) -> 5082689.6 | D24: 0 | E24: =+SALDOS!C171 -> 5082689.6 | F24: 0
B25: Comunicaciones | C25: =SUM(D25:F25) -> -957215.29 | D25: 0 | E25: =+SALDOS!C165-SALDOS!D165 -> -957215.29 | F25: 0
B26: Custodia | C26: =SUM(D26:F26) -> 0 | D26: =+SALDOS!C167 -> 0 | E26: 0 | F26: 0
B27: Capacitación | C27: =SUM(D27:F27) -> 0 | D27: =+SALDOS!C141 -> 0 | E27: 0 | F27: 0
B28: Deudores incobrables | C28: =SUM(D28:F28) -> 80711 | D28: 0 | E28: =+SALDOS!C203 -> 80711 | F28: 0
B29: Despachantes | C29: =SUM(D29:F29) -> 1.1083861e+08 | D29: 0 | E29: =+SALDOS!C168 -> 1.1083861e+08 | F29: 0
B30: Donaciones | C30: =SUM(D30:F30) -> 2400000 | D30: =+SALDOS!C189 -> 2400000 | E30: 0 | F30: 0
B31: Gastos Computación | C31: =SUM(D31:F31) -> 0 | D31: =+SALDOS!C138 -> 0 | E31: 0 | F31: 0
B32: Estibajes | C32: =SUM(D32:F32) -> 0 | D32: 0 | E32: =+SALDOS!C190 -> 0 | F32: 0
B33: Estacionamiento | C33: =SUM(D33:F33) -> 821541.29 | D33: 0 | E33: =+SALDOS!C174+SALDOS!C175 -> 821541.29 | F33: 0
B34: Embargo radicación vehicular | C34: =SUM(D34:F34) -> 0 | D34: 0 | E34: 0 | F34: 0
B35: Fletes | C35: =SUM(D35:F35) -> 0 | D35: 0 | E35: =+SALDOS!C181 -> 0 | F35: 0
B36: Gastos de logística | C36: =SUM(D36:F36) -> 624483.29 | D36: 0 | E36: =+SALDOS!C185 -> 624483.29 | F36: 0
B37: Gastos de representación | C37: =SUM(D37:F37) -> 219472.57 | D37: 0 | E37: =+SALDOS!C184 -> 219472.57 | F37: 0
B38: indemnizaciones | C38: =SUM(D38:F38) -> 0 | D38: =+SALDOS!C130 -> 0 | E38: 0 | F38: 0
B39: Gastos varios clientes | C39: =SUM(D39:F39) -> 0 | D39: 0 | E39: =+SALDOS!C205+SALDOS!C206 -> 0 | F39: 0
B40: Gastos varios personal | C40: =SUM(D40:F40) -> 383019.22 | D40: 0 | E40: =+SALDOS!C146+SALDOS!C135+SALDOS!C148 -> 383019.22 | F40: 0
B41: Gastos y comisiones bancarias | C41: =SUM(D41:F41) -> 0 | D41: 0 | E41: 0 | F41: =+SALDOS!C222 -> 0
B42: Gastos obra social | C42: =SUM(D42:F42) -> 0 | D42: =SALDOS!C134 -> 0 | E42: 0 | F42: 0
B43: Gastos Hotelería | C43: =SUM(D43:F43) -> 0 | D43: =+SALDOS!C161 -> 0 | E43: 0 | F43: 0
B44: Gastos Gestoría | C44: =SUM(D44:F44) -> 8580298.4 | D44: =+SALDOS!C162 -> 8580298.4 | E44: 0 | F44: 0
B45: Gastos Telefonico | C45: =SUM(D45:F45) -> 0 | D45: =+SALDOS!C133 -> 0 | E45: 0 | F45: 0
B46: Habilitaciones | C46: =SUM(D46:F46) -> 0 | D46: =+SALDOS!C176 -> 0 | E46: 0 | F46: 0
B47: Sueldos | C47: =SUM(D47:F47) -> 1.9776938e+08 | D47: 0 | E47: =+SALDOS!C125 -> 1.9776938e+08 | F47: 0
B48: Salario Complementario del Decreto 332/20 | C48: =SUM(D48:F48) -> 0 | D48: 0 | E48: =-SALDOS!D157 -> 0 | F48: 0
B49: Honorarios directores | C49: =SUM(D49:F49) -> 0 | D49: =+SALDOS!C139 -> 0 | E49: 0 | F49: 0
B50: Honorarios legales | C50: =SUM(D50:F50) -> 1887708 | D50: =+SALDOS!C160 -> 1887708 | E50: 0 | F50: 0
B51: Indumentaria | C51: =SUM(D51:F51) -> 0 | D51: 0 | E51: 0 | F51: 0
B52: Impuestos varios | C52: =SUM(D52:F52) -> 0 | D52: 0 | E52: 0 | F52: =+SALDOS!C216 -> 0
B53: Imp. Bienes Acc. Y Part. Soc. | C53: =SUM(D53:F53) -> 661934.13 | D53: =+SALDOS!C196 -> 661934.13 | E53: =+SALDOS!C195 -> 0 | F53: 0
B54: Imp. A los créditos | C54: =SUM(D54:F54) -> 0 | D54: 0 | E54: 0 | F54: =+SALDOS!C212 -> 0
B55: Imp. A los débitos y créditos | C55: =SUM(D55:F55) -> 8329025.4 | D55: 0 | E55: 0 | F55: =+SALDOS!C210 -> 8329025.4
B56: imp. Al cheque | C56: =SUM(D56:F56) -> 0 | D56: 0 | E56: 0 | F56: =+SALDOS!C217 -> 0
B57: Intereses resarcitorios | C57: =SUM(D57:F57) -> 18860.69 | D57: =+SALDOS!C214 -> 18860.69 | E57: =+SALDOS!C213 -> 0 | F57: 0
B58: Serv de Transporte y Almacenamiento | C58: =SUM(D58:F58) -> 880675.8 | D58: 0 | E58: =+SALDOS!C200 -> 880675.8 | F58: 0
B59: Honorarios profesionales | C59: =SUM(D59:F59) -> 33850774 | D59: =+SALDOS!C126 -> 33850774 | E59: 0 | F59: 0
B60: Leasing | C60: =SUM(D60:F60) -> 0 | D60: 0 | E60: =+SALDOS!C215 -> 0 | F60: 0
B61: Legalizaciones | C61: =SUM(D61:F61) -> 0 | D61: 0 | E61: =+SALDOS!C145 -> 0 | F61: 0
B62: Locomoción | C62: =SUM(D62:F62) -> 0 | D62: 0 | E62: 0 | F62: 0
B63: Cargas Sociales | C63: =SUM(D63:F63) -> 61269167 | D63: 0 | E63: =+SALDOS!C128+SALDOS!C153 -> 61269167 | F63: 0
B64: Mantenimiento y lav. de flota | C64: =SUM(D64:F64) -> 0 | D64: 0 | E64: =+SALDOS!C172+SALDOS!C169+SALDOS!C180 -> 0 | F64: 0
B65: Mensajería y trámites | C65: =SUM(D65:F65) -> 0 | D65: =+SALDOS!C173 -> 0 | E65: 0 | F65: 0
B66: Gastos Generales | C66: =SUM(D66:F66) -> 1228669.4 | D66: 0 | E66: =+SALDOS!C123+SALDOS!C151 -> 1228669.4 | F66: 0
B67: Multas | C67: =SUM(D67:F67) -> 873100 | D67: 0 | E67: =+SALDOS!C183 -> 873100 | F67: 0
B68: Patentes | C68: =SUM(D68:F68) -> 0 | D68: 0 | E68: =+SALDOS!C197 -> 0 | F68: 0
B69: Peajes | C69: =SUM(D69:F69) -> 0 | D69: 0 | E69: 0 | F69: 0
B70: Redondeo | C70: =SUM(D70:F70) -> 0 | D70: 0 | E70: =-SALDOS!D131 -> 0 | F70: 0
B71: Reparaciones | C71: =SUM(D71:F71) -> 7958700 | D71: =+SALDOS!C136 -> 0 | E71: =+SALDOS!C137 -> 7958700 | F71: 0
E72: =+SALDOS!C138 -> 0 | F72: 0
B73: Reparaciones de flota | C73: =SUM(D73:F73) -> 0 | E73: =+SALDOS!C170 -> 0
B74: Refrigerios | C74: =SUM(D74:F74) -> 0 | D74: =+SALDOS!C179+SALDOS!C132 -> 0 | E74: 0 | F74: 0
B75: Ropa de trabajo | C75: =SUM(D75:F75) -> 0 | D75: 0 | E75: 0 | F75: 0
B76: Seguros | C76: =SUM(D76:F76) -> 77279851 | D76: 0 | E76: =+SALDOS!C164 -> 77279851 | F76: 0
B77: Seguridad y vigilancia | C77: =SUM(D77:F77) -> 217000 | D77: 0 | E77: =+SALDOS!C178 -> 217000 | F77: 0
B78: Servicios de limpieza | C78: =SUM(D78:F78) -> 0 | D78: =-SALDOS!D140+SALDOS!C140 -> 0 | E78: 0 | F78: 0
B79: Siniestros | C79: =SUM(D79:F79) -> 0 | D79: =+SALDOS!C187 -> 0 | E79: =+SALDOS!C218 -> 0 | F79: 0
B80: Molilidad y viáticos | C80: =SUM(D80:F80) -> 672542.18 | D80: 0 | E80: =+SALDOS!C124+SALDOS!C155 -> 672542.18 | F80: 0
B81: Tasas Senasa | C81: =SUM(D81:F81) -> 35815367 | D81: 0 | E81: =+SALDOS!C198 -> 35815367 | F81: 0
B82: Tasas IGJ, AFIP | C82: =SUM(D82:F82) -> 0 | D82: =+SALDOS!C152 -> 0 | E82: 0 | F82: 0
B83: Gastos Médicos | C83: =SUM(D83:F83) -> 35343240 | D83: =SALDOS!C158 -> 55100 | E83: =+SALDOS!C159 -> 35288140 | F83: 0
B84: R.E.C.P.A.M. | C84: =SUM(D84:F84) -> 0 | D84: 0 | E84: 0 | F84: =+SALDOS!C220 -> 0
B85: =+EEPN!B17 -> Total al 31.7.2026 | C85: =SUM(C11:C84) -> 6.1174865e+08 | D85: =SUM(D11:D84) -> 66231303 | E85: =SUM(E11:E84) -> 5.3718832e+08 | F85: =SUM(F11:F84) -> 8329025.4 | G85: =SUM(#REF!) -> #REF!
B86: Total al 31.12.05 | C86: =SUM(C15:C85) -> 1.2061002e+09 | D86: 0 | E86: 0 | F86: 0 | G86: =SUM(D86:F86) -> 0
A88: Las notas y anexos adjuntos forman parte integrante de los estados contables.
A89: Informe profesional por separado.
C94: =+'Anexo I'!C27 -> Miguel Ángel Alonso | E94: =+'Anexo I'!I27 -> Tomas Furlong
C95: =+'Anexo I'!C28 -> Contador Público (UCA) | E95: =+'Anexo I'!I28 -> Transportes Furlong S.A.
C96: =+'Anexo I'!C29 -> C.P.C.E.C.A.B.A. Tº176 Fº3 | E96: =+'Anexo I'!I29 -> Apoderado

Sheet Bienes
A3: Calculo De Bienes Societarios de Transporte Furlong Barsil 2009 | G3: ,
A4: =+EESP!F32 -> 1.4905331e+08 | B4: Activo
A5: =+EESP!L24 -> 5.9116183e+08 | B5: Pasivo
A6: =+A4-A5 -> -4.4210852e+08 | B6: Patrimonio Neto
A7: =+A6*0.005 -> -2210542.6 | B7: Impuesto
